Workbook

Sheet Leyenda
A1: Relevamiento de servicios a afiliados en sindicatos argentinos — ideas para Colm3na / Mi Trabajo
A2: Fecha: 25/09/2026. Fuente: páginas oficiales de cada sindicato (home + 2-5 páginas de servicios). Se excluyeron prestaciones de obra social; se incluyeron mutuales, institutos y fundaciones del gremio.
A4: Hojas:
A5: Propuestas — 34 ideas evaluadas contra Colm3na. Prioridad = Impacto×2 − Esfuerzo (fórmula). Ola 1: rápido y alto valor; 2: medio; 3: estructural.
A6: Sindicatos — 47 fichas: calidad informativa del sitio (1-5), app/portal detectado, mutual/instituto, cantidad de servicios.
A7: Servicios — 715 servicios relevados con modalidad (online / semi-online / presencial), categoría, descripción, URL y propuestas de Colm3na vinculadas.
A8: Cobertura — por sindicato, cuántos servicios cubre Colm3na hoy, a corto plazo (ola 1), con desarrollo mayor o no aplica; y cuántas vacancias digitales (semi-online/presencial) son cubribles a corto plazo.
A9: Matriz — qué sindicatos aportan evidencia a cada propuesta.
A11: Tipo de propuesta: NUEVA = módulo o función inexistente en Colm3na; VARIANTE = mejora de algo existente o ya planificado; EXTENSION = amplía un módulo existente.
A12: Notas: UPCN, UOCRA, FATSA/ATSA, SUTNA y AOT no pudieron relevarse y se reemplazaron por UPJET, FGB, Pasteleros, STIHMPRA y SETIA. AEDGI hoy se llama AEFIP (una sola ficha). Aceiteros = Federación + SOEA San Lorenzo. Montos citados son los publicados por cada sitio a la fecha del relevamiento.

Sheet Propuestas
A1: ID | B1: Título | C1: Tipo | D1: Módulo Colm3na | E1: Sindicatos fuente | F1: Idea original observada | G1: Funcionalidad propuesta en Colm3na | H1: Resumen (4 líneas) | I1: Impacto (1-5) | J1: Esfuerzo (1-5) | K1: Prioridad | L1: Ola | M1: Evidencia (servicios)
A2: P01 | B2: Motor de subsidios por evento vital con elegibilidad automática | C2: VARIANTE | D2: Trámites + Beneficios + Trabajadores | E2: SUPARA, CAMIONEROS, FOETRA, ACEITEROS, UF, STPCHPYA, UPSRA, SOEME, UPJET, APOC, ALEARA, SUTPA, SOESGyPE, SSRA, STVyARA, SGBATOS, SETIA, UOMA | F2: Es el servicio más repetido después del turismo: 38 de los 47 gremios publican subsidios por casamiento, nacimiento, adopción, fallecimiento, cumpleaños de 15/18 de hijos, jubilación o cumpleaños del afiliado, con reglas explícitas: antigüedad mínima (3 a 12 meses), plazo desde el evento (30 días a 6 meses), documentación, monto vigente con fecha y pago por CBU. SUPARA los resolvió con un micrositio por subsidio con carga de documentos y firma dibujada; Camioneros lo inició en su Sede Digital; APOC usa Google Forms + CBU; SSRA los pide desde la app; SOEA publica montos escalonados por categoría del CCT; SUTPA y la mutual de SOESGyPE expresan los montos en múltiplos de la cuota social (20 cuotas nacimiento, 100 fallecimiento), lo que los indexa solos. | G2: Plantilla 'Subsidio' en el constructor de trámites: evento, antigüedad mínima, plazo desde el evento, monto (fijo con vigencia, por categoría, o en múltiplos de cuota/porcentaje de escala), documentación y CBU. La app precalcula la elegibilidad antes de dejar iniciar el trámite, lee la partida o acta con el extractor para prellenar fechas y pasa el expediente por los estados existentes hasta 'pagado'. | H2: Convierte el catálogo de subsidios en trámites autoevaluados: el trabajador ve a qué tiene derecho y pide con dos fotos. El sindicato deja de recibir mails y papel, y tiene tablero de subsidios pagados por seccional y período. Reutiliza el motor de trámites, el extractor y el padrón; solo agrega reglas de elegibilidad y montos con vigencia. Es el segundo servicio más repetido en los 47 sitios relevados: alto valor percibido y rápido de mostrar. | I2: 5 | J2: 2 | K2: =I2*2-J2 -> 8 | L2: 1 | M2: SUPARA-8, SUPARA-9, SUPARA-10, CAMIONEROS-3, FOETRA-2, FOETRA-3, ACEITEROS-9, ACEITEROS-10, UF-5, UF-6, STPCHPYA-8, UPSRA-6, UPJET-5, APOC-2, ALEARA-4, ALEARA-5, SUTPA-3, SOESGyPE-6, SSRA-2, STVyARA-3, SGBATOS-13, SETIA-10, UOMA-7
A3: P02 | B3: Vouchers digitales por hitos de vida y fechas recurrentes | C3: NUEVA | D3: Beneficios + Credencial | E3: AEFIP, FGB, UF, UPSRA, UATRE, STIA, SUPARA, UTA, SADOP, AAA, SETIA, SGBATOS, UECARA, SPT, UPJET, ALEARA | F3: Veinte gremios regalan 7 a 10 noches en hoteles propios por casamiento, bodas de plata u oro, jubilación o 30/50 años de afiliación, a veces canjeables por dinero (UPSRA, UF) y con validez de un año en temporada baja. Aparecen además regalos recurrentes con elección de opción: cumpleaños del afiliado (AAA: gift card, 2 noches de hotel o anteojos según perfil; ALEARA: subsidio), kit de nacimiento o entradas a un parque (SADOP), gift card multimarca por hijo en el Día del Niño (UPJET), caja de Navidad (SETIA), noche de bodas (SADOP, UECARA). STIA PBA da días gratis según antigüedad. Todo se gestiona por mail y papel, y nadie sabe cuántos se canjean. | G3: Beneficio de tipo 'voucher': se emite automáticamente al aprobarse un evento (P01) o al cumplirse un hito calculado desde el padrón (aniversario de afiliación, cumpleaños, antigüedad), con QR, vigencia, condiciones y, si el sindicato lo define, opciones a elegir (estadía / monto / producto). El prestador lo valida y canjea con la misma verificación de QR de la credencial. | H3: Regalos por hitos que hoy se pierden en mails pasan a ser cupones en la app con vencimiento y canje controlado. El sindicato monetiza temporada baja de sus hoteles y ve cuántos vouchers emitió y canjeó. Se apoya en la validación de QR ya construida para la credencial. Diferencia a Colm3na en un punto muy emocional para el afiliado (casamiento, nacimiento, jubilación, cumpleaños). | I3: 4 | J3: 2 | K3: =I3*2-J3 -> 6 | L3: 1 | M3: AEFIP-6, AEFIP-7, AEFIP-9, FGB-10, UF-7, UPSRA-6, UATRE-7, STIA-12, SUPARA-15, UTA-5, SADOP-10, SADOP-11, SADOP-13, AAA-6, SETIA-11, SGBATOS-14, UECARA-7, SPT-12, UPJET-7, ALEARA-5, SETIA-13
A4: P03 | B4: Elegibilidad por nivel de vínculo: afiliado, adherente, jubilado, monotributista, no afiliado del rubro | C4: VARIANTE | D4: Beneficios + Plataforma (no afiliados) + Trabajadores | E4: FOETRA, FGB, SUPARA, UTHGRA, STIA, SIPREBA, UECARA, UTEDYC, UOMA, SOMU, COMERCIO | F4: FOETRA otorga préstamos y subsidios también a 'convencionados no afiliados' con montos menores ($350k vs $450k; $55k vs $70k); FGB cobra tarifas escalonadas según pertenencia sindicato/obra social/mutual; UECARA da ingreso gratis al afiliado y arancel a invitados y a beneficiarios de obra social no afiliados; SUPARA tiene 'socio adherente' para jubilados; UTHGRA y SiPreBA admiten monotributistas y freelance con cuota calculada sobre un salario de referencia y débito por CBU; UOMA acepta consultas legales de no afiliados; SOMU da camping gratis al afiliado más un invitado; el SEC tiene cuota reducida para jubilados. | G4: Cada beneficio, subsidio, tarifa, voucher o servicio admite valores por 'nivel de vínculo' (afiliado pleno, afiliado + entidad vinculada, adherente/jubilado, monotributista/freelance, registrado no afiliado, invitado). El nivel se deriva del padrón y de la estrategia de no afiliados ya decidida. La app muestra al no afiliado 'esto recibirías si te afiliás' con la diferencia concreta. | H4: Modela lo que FOETRA y UECARA hacen a mano: el beneficio como argumento de afiliación con montos visibles. Encaja directo en la etapa de no afiliados sin inventar un módulo nuevo y suma monotributistas y jubilados. Un solo catálogo, varios niveles; menos duplicación para el admin del sindicato. Habilita cuota diferenciada de jubilados y adherentes, pedido frecuente de los gremios. | I4: 4 | J4: 2 | K4: =I4*2-J4 -> 6 | L4: 1 | M4: FOETRA-1, FOETRA-16, FGB-9, SUPARA-2, SUPARA-11, UTHGRA-12, SIPREBA-1, UECARA-9, UTEDYC-4, UOMA-3, SOMU-5, COMERCIO-18
A5: P04 | B5: Campañas con ventana: kits escolares, Día de la Niñez, colonias, torneos, cajas navideñas | C5: NUEVA | D5: Nuevo módulo 'Campañas e inscripciones' (sobre Trámites y Notificaciones) | E5: CAMIONEROS, STIA, SUPARA, ACEITEROS, UATRE, FGB, UPJET, FOETRA, SUTEBA, PETROLEROS_PRIVADOS, UECARA, SGBATOS, SIPREBA, SETIA, AAA, STVyARA, SADOP, UOMA, SOESGyPE, STIHMPRA, SUTPA, ALEARA | F5: El kit escolar está en 30 de los 47 gremios y es el contenido más visitado en Camioneros (~30.000 visitas); STIA lo inscribe por web con login DNI + nro. de afiliado en una ventana fija (7/9 al 7/12); UECARA exige 'inscripción previa en la web' entre el 2/2 y el 13/3; SUPARA abre y cierra un micrositio anual; Camioneros ofrece 'consulta de estado de útiles'; SGBATOS asigna 550 becas secundarias; FOETRA inscribe talleres con Google Forms; hay colonias, torneos, Día de la Niñez, cajas de Navidad y Día del Textil con sorteos, casi todo con planillas en papel o en delegación. | G5: Campaña = formulario + ventana de fechas + elegibilidad (antigüedad, hijos en padrón por edad/nivel) + cupo + puntos de retiro por seccional. Estados por solicitud: solicitada → aprobada → lista para retirar (con QR) → entregada. Notificación automática al abrir la ventana y cuando está listo el retiro. Tablero de campaña con solicitudes, entregas y faltantes por seccional. | H5: Reemplaza Google Forms, planillas y mails con un flujo que el trabajador sigue desde la app hasta el retiro. El sindicato controla cupos, stock por seccional y evita duplicados por hijo. Sirve igual para kits, colonias, torneos, becas, talleres, cajas navideñas y sorteos. Es el servicio de mayor tráfico anual en los sitios relevados: buen imán de uso de la app. | I5: 5 | J5: 3 | K5: =I5*2-J5 -> 7 | L5: 1 | M5: CAMIONEROS-5, STIA-8, SUPARA-12, ACEITEROS-11, UATRE-9, FGB-13, UPJET-7, FOETRA-9, SUTEBA-11, STIA-13, PETROLEROS_PRIVADOS-9, UECARA-5, SGBATOS-8, SGBATOS-15, SGBATOS-16, SIPREBA-12, SETIA-13, SETIA-14, AAA-4, AAA-5, STVyARA-6, SADOP-12, UOMA-9, SOESGyPE-9, STIHMPRA-1, SUTPA-5, ALEARA-10
A6: P05 | B6: Grupo familiar en el padrón, con documentación y vencimientos | C6: EXTENSION | D6: Trabajadores (ABM) + Afiliación | E6: SUTEBA, SMATA, STPCHPYA, SUTERH, STIA, ACEITEROS, SGBATOS, SSRA, UECARA, STIHMPRA, SOESGyPE | F6: La afiliación online de SUTEBA carga el grupo familiar con parentesco y DNI; SMATA usa un 'formulario 311' para agregar familiares; STIA exige que los hijos estén en el padrón para el kit; SOEA paga subsidios por 15 años de hija y 18 de hijo; SUTERH incorpora hijos mayores de 21 que estudian con negativa de ANSES; SGBATOS y SSRA emiten credencial también para familiares; UECARA limita invitados por grupo familiar; SOESGyPE recomienda verificar el grupo en ANSES. | G6: Alta y edición de familiares (cónyuge/conviviente, hijos con fecha de nacimiento, documentación y vencimientos como el certificado de alumno regular) desde la app del trabajador con aprobación del sindicato. Alimenta elegibilidad de subsidios, campañas, vouchers y reservas y dispara hitos automáticos. Nunca se usa en el motor de recibos. | H6: Sin grupo familiar no hay kits, subsidios por hijo ni invitados en hoteles: es la base de la mitad de los beneficios relevados. El trabajador mantiene sus datos; el sindicato aprueba con la documentación adjunta. Genera eventos automáticos (cumpleaños, edad escolar) que hoy nadie avisa. Queda separado del motor de recibos, respetando la decisión de no sumar datos personales ahí. | I6: 4 | J6: 2 | K6: =I6*2-J6 -> 6 | L6: 1 | M6: SUTEBA-1, SMATA-1, STPCHPYA-2, SUTERH-3, STIA-8, ACEITEROS-10, SGBATOS-1, SSRA-1, UECARA-9, STIHMPRA-4, SOESGyPE-1
A7: P06 | B7: Crédito, anticipo de sueldo y ayuda financiera con simulador y conciliación en el recibo | C7: VARIANTE | D7: Trámites + Motor de recibos + Beneficios | E7: SUPARA, FOETRA, UF, SOEME, UTA, LYF, STPCHPYA, PETROLEROS_PRIVADOS, APOC, SSRA, ALEARA | F7: SUPARA otorga créditos de hasta $3,5M y anticipos de sueldo 100% online (formulario, recibo, certificado de retención, firma en pantalla, cuota informada); FOETRA deja que el afiliado proponga las cuotas y renueva al 50% pagado; APOC presta a tasa Banco Nación; SSRA suma crédito hipotecario vía FIDEC; UF, UTA, SOEME y Luz y Fuerza prestan con descuento por recibo o fondos propios; ALEARA financia bautismos, fiestas de 15 y ortodoncia; SUPARA financia turismo con débito en el recibo. | G7: Trámite 'Solicitud de crédito/anticipo' con simulador de cuota, planes definidos por el sindicato, carga de documentación, firma en pantalla y estado. Al aprobarse se registra el plan de cuotas y el motor de recibos verifica cada mes que el descuento 'préstamo sindical/mutual' coincida con la cuota prevista. Aviso al sindicato cuando la empresa no retuvo. | H7: Une un producto financiero muy común en los gremios con lo que Colm3na hace único: leer el recibo. El trabajador simula, pide y firma desde el celular; el sindicato aprueba con la documentación ya cargada. Cada recibo posterior confirma que la cuota se descontó bien: control automático de la cartera. Encaja con la idea propia de 'crédito de bienvenida' para no afiliados. | I7: 5 | J7: 3 | K7: =I7*2-J7 -> 7 | L7: 2 | M7: SUPARA-4, SUPARA-5, SUPARA-6, SUPARA-7, FOETRA-1, UF-10, SOEME-3, UTA-9, LYF-6, STPCHPYA-12, PETROLEROS_PRIVADOS-2, APOC-3, SSRA-6, SSRA-7, ALEARA-7
A8: P07 | B8: Reintegros con lectura automática de la factura, puntuales y recurrentes | C8: VARIANTE | D8: Trámites + Extractor IA | E8: ACEITEROS, STPCHPYA, SOEME, UF, UTHGRA, APOC, SGBATOS, ALEARA, SSRA | F8: SOEA reintegra hasta $100.000 en anteojos y 50-100% en ortopedia con receta y factura; la Mutual 12 de Enero reintegra óptica, ortopedia y útiles; APOC reintegra la guardería todos los meses con factura y CBU (acumulable hasta 3 meses); SGBATOS reintegra jardín maternal a quien no usa los propios; ALEARA reintegra mudanza, plantillas y colonia; SSRA reintegra colonia; UTHGRA reintegra sepelios privados contra factura dentro del año. | G8: Tipo de trámite 'Reintegro' con rubros, topes por período y modalidad puntual o mensual recurrente. El trabajador fotografía la factura; el extractor lee CUIT del comercio, fecha, importe y detalle, valida contra tope y plazo y prellena la solicitud. El sindicato aprueba y registra el pago; el tablero muestra reintegros por rubro y seccional. | H8: Reutiliza el extractor de documentos para un trámite que hoy es 100% papel en los gremios que lo ofrecen. El trabajador sabe al instante si la factura entra en tope y plazo antes de presentarla. Suma el reintegro mensual recurrente (guardería) con acumulación, como hace APOC. Es una vitrina barata de la IA de Colm3na fuera del recibo. | I8: 3 | J8: 2 | K8: =I8*2-J8 -> 4 | L8: 2 | M8: ACEITEROS-14, STPCHPYA-14, SOEME-8, UF-9, UTHGRA-5, APOC-2, SGBATOS-11, ALEARA-6, SSRA-4
A9: P08 | B9: Afiliación online con prellenado desde el recibo, chequeo de padrón y afiliación provisoria | C9: VARIANTE | D9: Plataforma (no afiliados) + Trámites + Credencial | E9: SUTEBA, SUTERH, UEJN, SUPARA, BANCARIA, UTHGRA, UTA, UTEDYC, ALEARA, SIPREBA, SADOP, FGB | F9: SUTEBA afilia 100% online con carga de DNI y recibo; UTEDYC afilia por CUIL con reanudación del trámite y observaciones; SUTERH inicia por WhatsApp/mail y entrega una 'afiliación provisoria' en PDF mientras valida; ALEARA y FGB ofrecen consulta de padrón por CUIL sin login como pre-chequeo; SiPreBA acepta freelance con prueba de trabajo; Bancaria, UTA y SADOP usan un lead form que termina en sede; UTHGRA centraliza todo en un Departamento Unificado de Afiliaciones. | G9: Flujo 'Quiero afiliarme' para el registrado no afiliado: chequeo público '¿estoy en el padrón?' por CUIL; sube su recibo (el extractor completa CUIL, empresa, CUIT, categoría, seccional por domicilio), DNI y firma en pantalla; el sindicato recibe el trámite con verificación previa y puede emitir una credencial provisoria con vigencia corta. Al aprobar se emite la credencial definitiva. | H9: Cierra el embudo de la estrategia de no afiliados: del validador gratuito a la afiliación en el mismo lugar. El recibo ya leído evita tipear datos y da al sindicato una preverificación del empleador y la categoría. La afiliación provisoria (idea de SUTERH) da un beneficio inmediato sin esperar la comisión directiva. Trazabilidad de altas por seccional y por canal de origen para medir la campaña. | I9: 5 | J9: 3 | K9: =I9*2-J9 -> 7 | L9: 1 | M9: SUTEBA-1, SUTERH-2, UEJN-1, SUPARA-1, BANCARIA-1, UTHGRA-1, UTA-1, UTEDYC-2, ALEARA-1, SIPREBA-1, SADOP-1, FGB-1
A10: P09 | B10: Constancias autogeneradas con QR verificable (afiliado, alumno, empleador, familiar) | C10: EXTENSION | D10: Credencial + Trámites | E10: AEFIP, FGB, SUPARA, UPJET, SIPREBA, SADOP, UECARA, ADEF | F10: AEFIP exige pedir por mail un 'certificado de afiliado' para usar más de 30 convenios universitarios; FGB tiene consulta de padrón online para que empleadores verifiquen la condición; SUPARA, UPJET, SiPreBA, SADOP (becas UMET), UECARA (UTN 25%) y ADEF (UMET) también activan convenios educativos acreditando afiliación ante la institución. | G10: Botón 'Generar constancia' en la app: PDF con datos del afiliado, fecha, antigüedad y QR que lleva a la página pública de verificación ya usada por la credencial. Tipos configurables. Registro de constancias emitidas y de verificaciones. | H10: Elimina uno de los mails más repetidos hacia el sindicato con una función de un día de trabajo. Los convenios con universidades e institutos pasan a activarse al instante desde la app. La verificación por QR reutiliza lo construido para la credencial. Da un uso concreto y frecuente a la credencial fuera del comercio adherido. | I10: 3 | J10: 1 | K10: =I10*2-J10 -> 5 | L10: 1 | M10: AEFIP-3, AEFIP-12, FGB-1, SUPARA-19, UPJET-10, SIPREBA-9, SADOP-15, UECARA-13, ADEF-12
A11: P10 | B11: Reclamo laboral tipificado con evidencia, un clic desde la discrepancia del recibo | C11: VARIANTE | D11: Trámites + Motor de recibos + Empleadores | E11: COMERCIO, SMATA, STIA, ACEITEROS, CAMIONEROS, UPSRA, SSRA, SPT, UOMA, SETIA | F11: El SEC ofrece formularios web tipificados: trabajo no registrado, horas extra impagas, adicional cajero, encuadramiento y falta de EPP; SMATA tiene canal anticorrupción anónimo; SSRA una casilla de violencia laboral; STIA publica protocolo; SETIA enruta la asesoría virtual por área con FAQ previo; UOMA acepta consultas legales de no afiliados; SPT tiene cuerpo de inspectores; Camioneros da una planilla de km para controlar el adicional. | G11: Catálogo de reclamos tipificados por convenio. Desde una discrepancia detectada en el recibo, el trabajador abre el reclamo con el recibo y el cálculo ya adjuntos; el sindicato agrupa reclamos por empresa y concepto y abre un trámite con el empleador desde el módulo Empleadores. Tipos no salariales (EPP, violencia laboral) con confidencialidad. Registro de horas/km como evidencia mensual. | H11: Es el 'para qué' del validador: la diferencia detectada se transforma en un reclamo formal sin volver a explicar nada. El sindicato ve reclamos agrupados por empresa y concepto, y actúa colectivamente. Suma tipos de reclamo no salariales (EPP, violencia laboral) con confidencialidad. Usa trámites, empleadores y el motor existentes: es configuración y flujo, no un módulo nuevo. | I11: 5 | J11: 2 | K11: =I11*2-J11 -> 8 | L11: 1 | M11: COMERCIO-9, COMERCIO-10, SMATA-11, STIA-6, ACEITEROS-3, CAMIONEROS-11, UPSRA-4, SSRA-14, SPT-4, UOMA-3, SETIA-4
A12: P11 | B12: Mi delegado: directorio, asignación, mensajería y validaciones | C12: NUEVA | D12: Trabajadores + Notificaciones + Seguridad/perfiles | E12: SUTERH, ATE, UEJN, SGBATOS, ADEF, APOC, SUPARA | F12: La app de SUTERH permite mensajes a delegados y autoridades y tiene buscador de delegados por zona; SGBATOS envía consultas a cada Secretaría desde la app; ADEF publica delegados por comuna; ATE explica el rol del delegado en su FAQ; UEJN tiene canal de consultas en la app; SUPARA exige firma del delegado en los subsidios; APOC tiene una 'Red de Trabajadores' entre organismos. | G12: Rol 'Delegado' en perfiles con alcance por empresa/establecimiento; el trabajador ve quién es su delegado y le escribe por el hilo tipo WhatsApp; el delegado ve a sus representados, sus reclamos y campañas, y puede validar pasos de trámites. Directorio público de delegados y de áreas/secretarías con enrutamiento de consultas. | H12: Lleva a la app la relación más importante del sindicato: la del trabajador con su delegado de planta. El delegado deja de ser un teléfono y pasa a ser un rol con bandeja, alcance y métricas. Reusa la seguridad granular por áreas y seccionales ya construida. Habilita el paso 'visto del delegado' que varios gremios exigen en subsidios. | I12: 4 | J12: 3 | K12: =I12*2-J12 -> 5 | L12: 2 | M12: SUTERH-1, SUTERH-9, ATE-6, UEJN-8, SGBATOS-2, ADEF-18, APOC-16, SUPARA-8
A13: P12 | B13: Turnos para asesoría jurídica, previsional, contable, médico legista y servicios en sede | C13: NUEVA | D13: Nuevo módulo 'Turnos' (ligado a Seccionales) | E13: STIA, UPSRA, FGB, ACEITEROS, COMERCIO, CAMIONEROS, SUTERH, APOC, SPT, AAA, UPJET, SOESGyPE | F13: Los abogados atienden en horarios fijos (STIA lunes 9:30-11:30, UPSRA martes y jueves, FGB 16 a 18:30, SOEA miércoles y viernes) con turno por WhatsApp o teléfono; APOC pide entrevista previa por teléfono; el SEC tramita DNI/pasaporte en sede y Camioneros tiene oficina ANSES adentro del gremio; UPJET y AAA asesoran sobre Ganancias; SOESGyPE ofrece peluquería y podología en sede; SUTERH muestra y cancela turnos desde su app. | G13: Agendas por servicio y sede con franjas, cupos y requisitos. Reserva y cancelación en la app, recordatorio, check-in con QR de la credencial y estadísticas de demanda por tema y seccional. Sirve también para servicios de terceros en sede (ANSES, RENAPER, ópticas). | H13: Los servicios presenciales más valorados (asesoría legal, previsional, contable) hoy dependen de un teléfono que suena. Con turnos, el trabajador llega con la documentación correcta y el sindicato dimensiona la demanda. Sirve también para servicios de terceros en sede (ANSES, DNI) que varios gremios ofrecen. Módulo acotado y conocido; se integra con seccionales, credencial y notificaciones. | I13: 4 | J13: 3 | K13: =I13*2-J13 -> 5 | L13: 2 | M13: STIA-5, UPSRA-10, FGB-4, ACEITEROS-15, COMERCIO-16, CAMIONEROS-14, SUTERH-1, APOC-4, SPT-4, AAA-7, UPJET-8, SOESGyPE-11
... A35: P34 | B35: Entidades vinculadas: mutual, caja complementaria, fundación e instituto como capas del mismo sindicato | C35: NUEVA | D35: Plataforma + Seguridad/perfiles + Beneficios + Credencial | E35: STPCHPYA, UTA, UF, SMATA, SSRA, SGBATOS, SUPARA, LYF, PETROLEROS_PRIVADOS, ALEARA, SUTPA, SOESGyPE, UOMA, AAA, ADEF, UATRE, APOC, SIPREBA, UECARA | F35: En 25 de los 47 gremios los beneficios de peso (subsidios, préstamos, seguros, tiendas, hoteles, formación) los presta una entidad vinculada: mutuales (12 de Enero, UTA, AMUF, Mecánica, AMTRAS, AMTIMA, AMUPEJA, 27 de Agosto, SUTPA, AMDTA, AMDEF), cajas complementarias (SUPARA, SGBATOS), fundaciones (FUNDATRE, FAECE, IAF) e institutos (IDETEL, IFP-UPSRA, ESDU, La Piedad, Centro 26). Suelen tener padrón propio (afiliación separada con antigüedad), credencial propia y cuota propia; Petroleros afilia a sindicato y mutual en un solo acto; SSRA muestra las tres credenciales en una app. | G35: Concepto de 'entidad vinculada' dentro del inquilino sindicato: padrón de asociados (subconjunto o superconjunto del padrón sindical), cuota y antigüedad propias, catálogo de beneficios y trámites propios, credencial propia en la misma wallet, perfiles de administración separados y tablero propio. La afiliación conjunta (sindicato + mutual) en un solo trámite. | H35: La mitad de los beneficios relevados los presta una mutual, caja, fundación o instituto del gremio, con padrón y credencial propios. Sin modelarlas, Colm3na no puede decir con precisión quién es elegible ni quién paga. Se implementa como capa de pertenencia sobre el padrón, no como otro inquilino. Habilita afiliación conjunta y credencial múltiple como hacen Petroleros y SSRA. | I35: 4 | J35: 4 | K35: =I35*2-J35 -> 4 | L35: 3 | M35: STPCHPYA-7, UTA-9, UF-10, SMATA-6, SSRA-1, SGBATOS-19, SUPARA-17, LYF-6, PETROLEROS_PRIVADOS-1, ALEARA-2, SUTPA-2, SOESGyPE-6, UOMA-9, AAA-9, ADEF-15, UATRE-5, APOC-14, SIPREBA-2, UECARA-12

Sheet Sindicatos
A1: Sigla | B1: Sindicato | C1: Rubro | D1: Alcance | E1: URL | F1: Calidad web (1-5) | G1: App / portal detectado | H1: Mutual / instituto | I1: Cant. servicios | J1: Online | K1: Semi-online | L1: Presencial | M1: Observaciones | N1: Páginas leídas
A2: ADEF | B2: Asociación de Empleados de Farmacia | C2: Empleados de farmacia (CABA y provincia de Buenos Aires) | D2: nacional (sede central CABA; delegados comunales y de PBA) | E2: https://www.adef.org.ar/ | F2: 4 | G2: Subdominio app.adef.org.ar con herramientas web: Simulador de liquidación de haberes (app.adef.org.ar/simulador), Simulador de vacaciones (app.adef.org.ar/simulador/holiday), 'ADEF Responde' (app.adef.org.ar/responde, atención 24hs por web/0800/WhatsApp), Sistema de Aportes en Línea (para empleadores, login con CUIT). Pre-afiliación online a la obra social (afiliacion.osadef.org.ar). No se detectó app móvil nativa ni credencial digital sindical. | H2: Mutual AMDEF (mutual.adef.org.ar): funciona como tienda online (e-commerce con 'Mi cuenta' y carrito) de útiles escolares, alimentos y artículos de limpieza para asociados; contacto WhatsApp +54 9 11 2369-3316. Centro de Formación Profesional N°26 (centro26.com.ar) y Laboratorio Escuela 'Jorge Di Pascuale' para formación de auxiliares de farmacia. Convenio con UMET para Licenciatura en Farmacia y Centro de Idiomas. | I2: 18 | J2: 9 | K2: 5 | L2: 4 | M2: Sindicato chico con web muy por encima de su tamaño. Diferenciales: (1) DOS calculadoras propias (liquidación de haberes y vacaciones) bajo un subdominio 'app'; (2) 'FarmaTrivia', una plataforma gamificada de capacitación con premios mensuales, idea muy original para retención/engagement; (3) mutual convertida en tienda online (útiles, alimentos, limpieza) en vez de solo subsidios; (4) turismo social con circuito claro (consultar web -> WhatsApp/mail -> seña 48hs -> cuotas -> voucher por mail) y FAQ bien redactada; (5) canal 24hs unificado 'ADEF Responde'; (6) plan de viviendas propio nacido de un censo habitacional de afiliados. Excluido: portal OSADEF, validador de prestadores, pre-afiliación obra social (salud). | N2: https://www.adef.org.ar/ https://www.adef.org.ar/simulador https://www.adef.org.ar/simulador-vacaciones https://www.adef.org.ar/sistema-de-aportes-en-linea https://www.adef.org.ar/turismo-social/preguntas-frecuentes https://www.adef.org.ar/institucional/plan-viviendas https://www.adef.org.ar/adef-responde https://mutual.adef.org.ar/ https://farmatrivia.ar/
A3: CAMIONEROS | B3: Sindicato de Choferes de Camiones, Obreros y Empleados del Transporte Automotor de Cargas de CABA y Provincia de Buenos Aires (con referencias a la Federación Nacional de Trabajadores Camioneros - FEDCAM) | C3: transporte automotor de cargas y logística (CCT 40/89) | D3: seccional CABA y Provincia de Buenos Aires (sindicato de base) + federación nacional para escalas y sistemas | E3: https://www.camioneros-ba.org.ar/ | F3: 4 | G3: App móvil 'CamionerosBA' (Android e iOS) promocionada como 'toda la información al alcance de tu mano' (funciones no detalladas en la web). 'Sede Digital' (sededigital.camioneros-ba.org.ar): portal de autogestión del afiliado con login por CUIL y clave, registro de nuevo usuario, donde se inician trámites como el beneficio por nacimiento. Credencial digital de OSCHOCA (obra social) y mención a credencial sindical digital. Portales para empresas: impresión de boletas, acuerdos por empresa con login (convenios.camioneros.org.ar / acuerdos.spdps.com.ar), psicofísico. Escalas salariales online; sin calculadora. sindicatocamioneros.org.ar no resuelve DNS. | H3: Mutual Camioneros (mutualcamioneros.org.ar, enlazada desde la home, contenido no relevado); Club Camioneros (deportivo); programa 'Camioneros Solidarios' (asistencia); revista 'Los Camioneros' y Biblioteca Sindical (FEDCAM). | I3: 22 | J3: 7 | K3: 5 | L3: 10 | M3: El sitio más completo del grupo (calidad 4): es el único con app móvil en ambas tiendas y un portal de autogestión (Sede Digital, login por CUIL) donde ya se inician beneficios sociales online. Ideas fuertes: catálogo de subsidios con reglas claras (6 meses de antigüedad, plazo de 3 meses, documentación) fácilmente digitalizables; consulta online del estado de entrega de útiles escolares; planilla de km como herramienta de control del recibo; oficina ANSES dentro del gremio; alojamiento para estudiantes y pacientes del interior; sistemas específicos del oficio (psicofísico/LiNTI). El lado empresa está muy digitalizado (boletas, libre deuda, acuerdos por empresa, aportes por CBU). Debilidades: la web no explica qué hace la app ni qué trámites hay en Sede Digital; turismo sin reserva online; URLs de Joomla frágiles (varias dan 404). Nota: sindicatocamioneros.org.ar no resuelve; se usó camioneros-ba.org.ar (sindicato de base más grande) y fedcam.org.ar. | N3: https://www.camioneros-ba.org.ar/ https://www.fedcam.org.ar/ http://camioneros-ba.org.ar/index.php/sindicato/novedades/537-nueva-app-camionerosba https://www.camioneros-ba.org.ar/index.php/turismo https://www.camioneros-ba.org.ar/index.php/secretarias https://www.camioneros-ba.org.ar/index.php/2015-04-16-17-59-12/secretaria-de-accion-social https://www.camioneros-ba.org.ar/index.php/nacimientos https://sededigital.camioneros-ba.org.ar/
A4: SETIA | B4: Sindicato de Empleados Textiles de la Industria y Afines de la República Argentina (reemplaza a AOT, cuyo sitio aot.org.ar / aotra.org.ar no respondió) | C4: empleados (administrativos, técnicos, supervisión) de la industria textil y afines | D4: nacional (con seccionales) | E4: https://setia.org.ar/ | F4: 4 | G4: Sí: (1) 'SETIA Online' (portal con acceso a sistema AMETIA Online, afiliaciones y padrones, boletas sindicales online para empresas y credencial digital móvil en wcaup.com/setiaonline/mobile/); (2) app propia 'Setia App' (app.setia.ar, web app con landing; contenido dinámico no legible sin JS); (3) portal de reservas de turismo turismo.setia.ar (web app). Además formulario web de Asesoría Virtual. | H4: AMETIA (ametia.com.ar) — entidad vinculada (mutual/asociación) con sistema 'AMETIA Online' integrado en SETIA Online; su oferta concreta no está descrita en el sitio. Hotelería propia: Hotel Yana (San Clemente), Hotel Bareko (Bariloche), Hotel Juan D. Perón (Mar del Plata), Colonia Eva Perón (Córdoba) y Centro Recreativo Ezeiza. | I4: 16 | J4: 8 | K4: 2 | L4: 6 | M4: Sindicato mediano con una capa digital sorprendentemente completa: credencial digital móvil, app propia, portal 'SETIA Online' que integra sistema de la mutual AMETIA, padrones y boletas online para empresas, portal de reservas hoteleras y asesoría virtual con N° de afiliado. Idea original: página pública de 'verificación de inspectores' con listado de inspectores habilitados y formulario para que la empresa solicite inspección (transparencia frente a inspectores falsos y canal formal de cobranza). También el enrutamiento de consultas por área y el FAQ previo a la asesoría. Beneficios clásicos bien definidos (luna de miel y bodas de oro en hoteles propios, caja de Navidad, útiles, subsidio nacimiento, Día del Textil con sorteo de vehículos). Falta: afiliación online (sigue en PDF). | N4: https://setia.org.ar/ https://setia.org.ar/?cat=4 https://setia.org.ar/?page_id=25 https://setia.org.ar/?page_id=13 https://setia.org.ar/?page_id=29 https://setia.org.ar/?page_id=34 https://setia.org.ar/?page_id=15 https://app.setia.ar/#/landing
A5: SGBATOS | B5: Sindicato Gran Buenos Aires de Trabajadores de Obras Sanitarias | C5: trabajadores de obras sanitarias / agua y saneamiento (AySA y afines) | D5: seccional Gran Buenos Aires (sindicato de primer grado, adherido a FeNTOS) | E5: https://sgbatos.org.ar/ | F5: 4 | G5: App móvil propia 'SGBATOS' (iOS y Android, desarrollada por OYS Group, paquete 'GestionAfiliados'). Registro con DNI + mail + contraseña validado contra padrón del sindicato y de la obra social OSOSS. Funciones: credencial digital del sindicato y de OSOSS (también para familiares), noticias/comunicados, info de turismo, torneos y beneficios, envío de consultas a las distintas Secretarías del sindicato y a la obra social, y botones de emergencia 'SOS' y 'Guardián' conectados a una sala de monitoreo. No se detectó portal web de autogestión con login aparte de la app. | H5: Farmacia Mutual 15 de Mayo (descuento adicional 10% sobre el 40% de cartilla; prestación farmacéutica, se menciona solo como referencia); Instituto Tecnológico Leopoldo Marechal (ITLM, itlm.org.ar) e Instituto Universitario del Agua y Saneamiento (IUAS, iuas.edu.ar) como instituciones educativas vinculadas; jardines maternales propios 'La Gotita de Agua' (lagotitadeagua.edu.ar); Caja Complementaria propia para jubilados. | I5: 23 | J5: 5 | K5: 3 | L5: 15 | M5: Lo más original es la app: además de credencial digital (sindicato + obra social, también para familiares) y mensajería hacia las Secretarías, integra un botón SOS georreferenciado y un modo 'Guardián' (alerta temporizada tipo 'llegué bien') con sala de monitoreo 24h y contactos de emergencia; es una función de seguridad personal poco habitual en apps sindicales. También destacan la Caja Complementaria previsional propia (haber complementario a jubilados financiado por activos), los jardines maternales propios con reintegro para quienes usan otros, el programa de lactancia hasta 2 años y la oferta educativa propia (instituto tecnológico + instituto universitario del agua). El sitio es prolijo en catálogo de beneficios pero casi ningún beneficio explica el trámite (formulario, canal, requisitos): oportunidad clara para digitalizar solicitudes de kit escolar, becas, nacimiento, casamiento y reservas hoteleras. | N5: https://sgbatos.org.ar/ https://sgbatos.org.ar/app/ https://sgbatos.org.ar/beneficios/ https://sgbatos.org.ar/turismo/
A6: STPCHPYA | B6: Sindicato de Trabajadores Pasteleros, Confiteros, Heladeros, Pizzeros y Alfajoreros - Buenos Aires (reemplazo de FATSA/ATSA: fatsa.org.ar, sanidad.org.ar y atsa.org.ar no respondieron en ningún intento) | C6: pasteleros, confiteros, heladeros, pizzeros y alfajoreros | D6: seccional Buenos Aires (CABA y GBA) | E6: https://pasteleros.org/ | F6: 4 | G6: App móvil 'ELEVAR' (Android/iOS, compartida con la obra social) con carnet digital de afiliado; registro con el mail declarado en la afiliación; manual de usuario en PDF. WhatsApp de mutual y de turismo. Escuela con sitio propio y cursos online. | H6: Asociación Mutual 12 de Enero: subsidios (ajuar por nacimiento, plan materno infantil, casamiento, fallecimiento, hijo con discapacidad), FOCOM fondo compensatorio, créditos personales, electrodomésticos, reintegros en óptica/ortopedia/útiles, descuentos en farmacia. Escuela de Pastelería Profesional (escueladepasteleria.com.ar). | I6: 30 | J6: 4 | K6: 6 | L6: 20 | M6: El sitio más completo del grupo en cuanto a detalle de prestaciones: cada subsidio de la mutual tiene monto, requisitos y plazos publicados (transparencia útil como modelo de 'catálogo de beneficios'). Diferenciales: carnet digital en app compartida sindicato+obra social (ELEVAR) con registro por mail declarado y manual de usuario; escuela de pastelería propia con cursos online; WhatsApp segmentado por área. Casi todos los trámites siguen siendo presenciales; oportunidad clara para digitalizar solicitud de subsidios con carga de documentación. | N6: https://pasteleros.org/ https://pasteleros.org/carnet-digital/ https://pasteleros.org/categoria/mutual/servicios/ https://pasteleros.org/categoria/turismo/ https://pasteleros.org/categoria/turismo/alojamientos-propios/ https://pasteleros.org/escuela/ https://pasteleros.org/prestaciones-gratuitas/ https://pasteleros.org/subsidios-y-beneficios/ https://pasteleros.org/trabajadores/
A7: SUPARA | B7: Sindicato Único del Personal Aduanero de la República Argentina | C7: Empleados públicos de la Dirección General de Aduanas (ARCA/AFIP) | D7: nacional | E7: https://supara.org.ar/ | F7: 4 | G7: No hay app móvil detectada, pero sí un ecosistema de micrositios de autogestión por trámite: credencial digital web-app (micredencial.supara.org.ar, React), formularios 100% online con carga de documentos y firma digital dibujada para crédito personal/jubilados (prestamopersonal.supara.org.ar), anticipo de sueldo (anticiposueldo.supara.org.ar), subsidios por matrimonio/nacimiento/fallecimiento (matrimonio./nacimiento./fallecimiento.supara.org.ar), apoyo escolar (apoyoescolar.supara.org.ar) y afiliación online (supara.org.ar/afiliacion-supara-online). WhatsApp de consultas 5491131543269. | H7: FAECE - Fundación de Altos Estudios en Comercio Exterior (faece.com.ar): fundación del sindicato con descuentos importantes y cursos gratuitos en comercio exterior para afiliados y grupo familiar. Caja Complementaria de Previsión para el Personal Aduanero (cajacomplementariadeaduana.org.ar): entidad separada que paga complemento jubilatorio y otorga préstamos a jubilados. Farmacia Sindical SUPARA (Azopardo 350) con descuentos 15-20% (excluida por ser salud, se menciona como referencia). | I7: 25 | J7: 7 | K7: 12 | L7: 6 | M7: Es el caso más avanzado del grupo en autogestión: en lugar de una app monolítica, SUPARA construyó un micrositio por trámite (prestamopersonal., anticiposueldo., matrimonio., nacimiento., fallecimiento., apoyoescolar., micredencial.supara.org.ar) con formularios 100% online que incluyen carga de documentos (DNI, recibo S.A.R.H.A., certificado de retención ARCA), selección de plan con cuota informada y firma dibujada en pantalla, además de afiliación online. Publica montos y fechas de vigencia de subsidios (actualizados a abril 2026) y plazos (6 meses), algo poco común. Ideas destacables: anticipo de sueldo como producto financiero gremial; premio de jubilación combinando dinero + 7 noches; socio adherente para jubilados con paquete propio (4x3 en hoteles, crédito jubilados, farmacia); campaña anual de apoyo escolar con ventana de inscripción online; fundación de formación profesional específica del oficio (FAECE) y descuento en Tarifar (herramienta de trabajo). Débil: sin app de tienda, sin motor de reservas hotelero centralizado, deporte y previsión siguen por mail/teléfono, y los subsidios exigen firma del delegado (paso presencial oculto dentro de un trámite 'online'). | N7: https://supara.org.ar/ https://supara.org.ar/prestamos https://supara.org.ar/subsidios https://supara.org.ar/afiliaciones/ https://supara.org.ar/hoteles-supara https://supara.org.ar/deporte-y-recreacion https://supara.org.ar/pre-jubilaciones https://supara.org.ar/beneficios-jubilaciones-2 https://supara.org.ar/capacitacion-y-cultura https://micredencial.supara.org.ar/ https://prestamopersonal.supara.org.ar/ https://apoyoescolar.supara.org.ar/beneficio/utiles
A8: SUTEBA | B8: Sindicato Unificado de Trabajadores de la Educación de Buenos Aires | C8: docentes (educación pública, privada y municipal de la Provincia de Buenos Aires) | D8: provincial (Buenos Aires), con seccionales por distrito | E8: https://www.suteba.org.ar/ | F8: 4 | G8: No hay app móvil ni credencial digital detectadas, pero sí un conjunto de aplicaciones web propias: Cálculo de Haberes (haberes.suteba.org.ar), portal de turismo con reservas (turismo.suteba.org.ar), consulta de precios de medicamentos, sistema de trámites ante IOMA (tioma.suteba.org.ar), cuenta recaudadora DIPREGEP, seguimiento de equipamiento y reserva de recursos (apps.suteba.org.ar). Afiliación 100% online con carga de documentos. | H8: No detectado como mutual. Tiene estructuras propias: Recreo del SUTEBA en Tigre, Escuela de Montaña, campings, Escuela de Formación Político Sindical, revista digital y espacios 'RUTEvte' y 'Utopías en Movimiento'. | I8: 18 | J8: 7 | K8: 6 | L8: 5 | M8: El sitio más completo del grupo en autogestión: afiliación online con carga de documentos y grupo familiar, calculadora de haberes propia, portal de reservas de turismo, sistema de trámites ante la obra social, consulta de precios de medicamentos y sistemas internos de reservas de recursos. Bien resuelto: un 'hub de aplicaciones' con todas las herramientas web listadas en una página. Ideas originales: asignaciones solidarias con reglas claras de antigüedad (6 meses), ferias de emprendedores afiliados, Escuela de Montaña, torneo provincial entre seccionales. Falta: app móvil y credencial digital. | N8: https://www.suteba.org.ar/ https://www.suteba.org.ar/beneficios-sociales-requisitos_435.html https://www.suteba.org.ar/promocion-social_6.html https://www.suteba.org.ar/enlaces-de-aplicaciones_407.html https://www.suteba.org.ar/afiliacion
A9: SUTERH | B9: Sindicato Único de Trabajadores de Edificios de Renta y Horizontal | C9: encargados y trabajadores de edificios (propiedad horizontal) | D9: CABA y Gran Buenos Aires (federación nacional FATERYH; hoteles abiertos también a afiliados del interior) | E9: https://suterh.org.ar/ | F9: 4 | G9: App móvil propia 'SUTERH Móvil' (iOS/Android) con credencial digital (carnet de beneficiario OSPERyH), turnos, consulta de aportes, estado de trámites, mensajes a delegados y autoridades, teléfonos útiles y novedades. Además: chat online en la web (10 a 18 hs), WhatsApp con menú de opciones (+54 9 11 3724-6682), reservas hoteleras online (motor b-tech DOTIA), 'Sistema de Control' de aportes (cc.fateryh.org.ar), directorio de delegados (servicios.suterh.org.ar/delegados) y afiliación iniciada por WhatsApp/mail. | H9: UMET – Universidad Metropolitana para la Educación y el Trabajo (universidad propia del sindicato, Sarmiento 2037), escuelas y programas de formación y capacitación; no se detectó mutual. | I9: 14 | J9: 6 | K9: 6 | L9: 2 | M9: El sindicato más digitalizado del grupo: app propia con credencial digital, mensajería a delegados y consulta de aportes; afiliación remota por WhatsApp/mail con 'afiliación provisoria' enviada como PDF; motor de reservas hoteleras online con reglas de pago y cancelación explícitas; chat web, WhatsApp con menú por área y directorio de delegados. Ideas rescatables: (1) afiliación provisoria digital inmediata mientras se valida la documentación, (2) reglas de hotelería claras (invitados máx. 2, pago 30 días antes, no show = una noche) que se pueden codificar, (3) consulta de aportes del empleador como control del trabajador, (4) mensajería directa afiliado→delegado. La app mezcla obra social y sindicato en una sola identidad, lo que simplifica la credencial. | N9: https://suterh.org.ar/ https://suterh.org.ar/nuevos-tramites-de-afiliacion-sin-salir-de-tu-casa/ https://apps.apple.com/ar/app/suterh-m%C3%B3vil/id1239631941 https://suterh.org.ar/preguntas-frecuentes/ https://suterh.org.ar/nuestros-hoteles/
A10: UEJN | B10: Unión de Empleados de la Justicia de la Nación | C10: empleados judiciales (Poder Judicial de la Nación) | D10: nacional | E10: https://www.uejn.org.ar/ | F10: 4 | G10: App móvil propia 'UEJN' (iOS y Android, +10.000 descargas, actualizada 11/09/2026) con credencial virtual, catálogo de beneficios/descuentos, noticias y canal de consultas sindicales. Web-app app.uejn.org.ar (afiliación online, catálogo de beneficios, pedido de credencial) y portal de autogestión afigestion.uejn.org.ar (módulo 'pases'). Además campus.uejn.org.ar y turismo.uejn.org.ar como subportales. | H10: no detectado (obra social OSPJN es estatal; se excluye) | I10: 9 | J10: 8 | K10: 1 | L10: 0 | M10: El sindicato más digitalizado del grupo: afiliación online, credencial virtual en app, catálogo de beneficios como web-app, portal de autogestión (afigestion), campus virtual y portal de turismo, todos en subdominios propios. Modelo de referencia para la arquitectura 'app del afiliado + subportales'. Puntos débiles: la información sobre subsidios/ayudas económicas no aparece en el sitio público (probablemente detrás del login), y la reserva turística no se ve como 100% online. No se pudo leer /por-que-afiliarme (bloqueo de proveniencia). | N10: https://www.uejn.org.ar/ https://www.uejn.org.ar/beneficios https://www.uejn.org.ar/afiliate https://www.uejn.org.ar/afiliate-completando-el-formulario-4504 https://www.uejn.org.ar/articulos/%C2%A1record%C3%A1-pedir-tu-credencial-de-afiliado-la-uejn-349 https://app.uejn.org.ar/beneficios https://play.google.com/store/apps/details?id=uejn.org.ar&hl=en_US https://turismo.uejn.org.ar/
A11: UTEDYC | B11: Unión Trabajadores de Entidades Deportivas y Civiles | C11: Trabajadores de clubes, entidades deportivas, civiles, mutuales, ONG, countries, guardavidas y profesores | D11: nacional | E11: https://www.utedyc.org.ar/ | F11: 4 | G11: App 'Mi UTEDYC' (iOS y Android) con carnet sindical digital, consulta y solicitud de beneficios, turismo con reserva, reserva y pago del lugar en los parques recreativos, inscripción al Campus Virtual, actualización de datos de contacto, descarga de formularios, convenios y biblioteca digital; soporte notificacionesapp@utedyc.org.ar. Además: portal de afiliación online por CUIL (Utedyc2.0/Afiliaciones), sistema 'UTEDYC NEO' de autogestión para empresas (DDJJ, login, guía) y un sistema de tickets (WebApiUtedyc/apiddjj/tickets). | H11: OSPEDYC (obra social, excluida). Centro de Formación Profesional UTEDYC / Campus Virtual (capacitacionutedyc.org.ar) y Escuela de Guardavidas propia. Departamento de Previsión Social con abogados previsionales. | I11: 14 | J11: 11 | K11: 2 | L11: 1 | M11: De los sindicatos medianos, el más avanzado en autogestión: afiliación online por CUIL con reanudación del trámite, app con carnet digital, solicitud de beneficios, reserva y pago de parques y turismo, inscripción a campus e incluso biblioteca digital. Ideas destacables: parques recreativos con ingreso gratuito para afiliados y pago de invitados desde la app; asesoría previsional proactiva ('contactanos 3 años antes de jubilarte'); escuela de guardavidas como formación específica del rubro; secretaría de digitalización. Debilidad: el sitio web tiene muchas páginas rotas (404 en /turismo y /convenios) y el 'beneficios' web es una página en construcción; la app concentra la funcionalidad. | N11: https://www.utedyc.org.ar/ https://www.utedyc.org.ar/miutedyc_app/index.html https://www.utedyc.org.ar/Utedyc2.0/Aplicaciones/Afiliaciones/Forms/Frm_Afiliaciones_Inicio.html https://www.utedyc.org.ar/Utedyc2.0/Aplicaciones/Login/Forms/Login.html https://www.utedyc.org.ar/nw35_02.html https://www.utedyc.org.ar/502/numero36/departamento-de-prevision-social.html
A12: ACEITEROS | B12: Federación de Trabajadores del Complejo Industrial Oleaginoso, Desmotadores de Algodón y Afines de la República Argentina (FTCIODyARA) + Sindicato de Obreros y Empleados Aceiteros de San Lorenzo (SOEA) | C12: Industria aceitera / oleaginosa y desmotadores de algodón | D12: nacional (federación) + seccional San Lorenzo (SOEA, sindicato de base más relevante, usado porque la federación no publica servicios al afiliado) | E12: https://federacionaceitera.com.ar/ | F12: 3 | G12: Federación: no tiene portal de afiliados; sí un 'Portal de Empresas' (gestion.federacionaceitera.com.ar/loginempresas.aspx) para las empleadoras. SOEA San Lorenzo: portal de autogestión de afiliados con login (secwebafiliados.soeasl.org.ar) para 'trámites a distancia' como libros y útiles escolares; no se pudo leer su interior (robots). | H12: Mutual AMPIAVA (vinculada a SOEA, Puerto General San Martín): farmacia mutual con descuentos, alquiler de salones de eventos, canal del fondo voluntario de medicamentos y de la leche maternizada. Centro Médico 29 de Octubre (SOEA, excluido por ser salud, salvo el apto físico para el camping). Nota: aceiteros.org.ar y soea.org.ar del brief no responden; los dominios reales son federacionaceitera.com.ar y soea.com.ar. | I12: 21 | J12: 5 | K12: 4 | L12: 12 | M12: La federación es puramente institucional/gremial (escalas, leyes, comunicados, salud laboral) y solo digitaliza el vínculo con empresas. El sindicato de base SOEA San Lorenzo, en cambio, tiene la lista de beneficios más completa y transparente del grupo: montos exactos indexados por categoría del CCT, documentación por beneficio y un portal de autogestión donde los beneficios simples (libros, útiles) se piden a distancia. Ideas valiosas: subsidios por hitos familiares (15 años, 18 años, bautismo), 'guarda de puesto' como subsidio por enfermedad prolongada, préstamo de mobiliario para fiestas, fondo voluntario de medicamentos vía mutual, y la tabla de montos por categoría que podría convertirse en una calculadora de beneficios en la app. | N12: https://federacionaceitera.com.ar/ https://federacionaceitera.com.ar/convenios-y-leyes/ https://federacionaceitera.com.ar/salud-laboral/ https://federacionaceitera.com.ar/category/formacion-sindical/ https://www.soea.com.ar/
A13: AEFIP | B13: Asociación de Empleados Fiscales e Ingresos Públicos (ex AEDGI) | C13: Empleados públicos de ARCA/AFIP (ex DGI, impositivos) | D13: nacional (Mesa Directiva Nacional, 18 seccionales) | E13: https://www.aefip.org.ar/ | F13: 3 | G13: App móvil propia 'AEFIP Credencial Digital' (Android, Google Play, id ar.org.aefip.aefipdigital.credencial; +1.000 descargas, 4,4 estrellas, última actualización marzo 2024): credencial digital con QR, login de afiliado, acceso a beneficios y notificaciones de eventos/noticias. La web es informativa (Joomla) sin portal de autogestión con login; los trámites se canalizan por mail/WhatsApp. Nota: la organización se renombró AEFIP; el dominio aedgi no se detectó como oficial (aefipcordoba.org.ar aún conserva la marca 'A.E.D.G.I. Seccional Córdoba'). | H13: no detectado (no hay mutual ni fundación propia visible; posee hoteles propios gestionados por Secretaría de Asuntos Sociales/Turismo Gremial y una 'Aula Virtual' de seminarios) | I13: 25 | J13: 5 | K13: 17 | L13: 3 | M13: Lo más destacable es la app 'AEFIP Credencial Digital' con QR y login, que actúa como llave de todo el ecosistema de convenios comerciales (los comercios exigen credencial física o digital). La política de 'regalos de estadía' (7 noches para dos por matrimonio, bodas de plata y jubilación) usando la red de 5 hoteles propios es una idea original para monetizar activos hoteleros en temporada baja y fidelizar hitos de vida; conviene replicarla como 'beneficios por evento vital' automatizables desde la app (la partida/acta se sube y se genera el voucher). El certificado de afiliado a demanda por mail es un candidato claro a constancia autogenerada desde la app. Débil: la afiliación es ficha PDF, sin formulario online, y ningún trámite (reservas, kits, certificados) tiene formulario web; todo pasa por mail/WhatsApp/delegado. Sitio Joomla desactualizado en algunas secciones; el dominio histórico aedgi no es el oficial. | N13: https://play.google.com/store/apps/details?id=ar.org.aefip.aefipdigital.credencial https://play.google.com/store/apps/details?id=ar.org.aefip.aefipdigital.credencial&hl=en_US https://www.aefip.org.ar/ https://www.aefip.org.ar/beneficios https://www.aefip.org.ar/beneficios/comercios https://www.aefip.org.ar/beneficios/culturales https://www.aefip.org.ar/beneficios/educativos https://www.aefip.org.ar/beneficios/gremiales https://www.aefip.org.ar/beneficios/turismo-conveniado https://www.aefip.org.ar/beneficios/turismo-gremial https://www.aefip.org.ar/institucional/afiliaciones https://www.aefipcapital.org.ar/beneficios
... A48: UTA | B48: Unión Tranviarios Automotor | C48: transporte automotor de pasajeros (choferes de colectivos y transporte urbano/larga distancia) | D48: nacional (sitio institucional con foco en CABA/AMBA; el dominio uta.org.ar no respondió y el sitio activo es utaargentina.com) | E48: https://www.utaargentina.com/ | F48: 2 | G48: El sindicato no tiene app ni portal de autogestión. La Mutual UTA (entidad vinculada) sí tiene un portal de socios con 'Credencial Online' en http://servicios.mutualuta.com.ar/Socio/Credencial y ofrece 'Bonos Virtuales' y Médico/Psicología online. | H48: Mutual UTA (mutualuta.com.ar): préstamos con retención de haberes, bonos virtuales, subsidios, sepelios, becas escolares, descuentos en comercios y en pasajes de larga distancia, asesoramiento legal, credencial online; además servicios de salud (odontología, medicamentos, médico online, enfermería) que se excluyen por ser prestaciones tipo obra social. | I48: 13 | J48: 3 | K48: 4 | L48: 6 | M48: El sitio del sindicato es básicamente institucional: turismo con tarifas publicadas pero reserva solo telefónica/presencial, y afiliación que arranca en un formulario web genérico y termina en la sede. Lo digital está tercerizado en la Mutual UTA: credencial online, bonos virtuales, préstamos por WhatsApp, médico y psicología online. Ideas rescatables: acceso gratuito a predios recreativos con solo mostrar la credencial (candidato obvio a credencial digital con QR), beneficio de luna de miel ligado a antigüedad sindical (regla automatizable), y mutual como capa de servicios financieros/descuentos separada del gremio. Muchas líneas telefónicas distintas por servicio: un caso claro para unificar en un chatbot/app. | N48: https://www.utaargentina.com/servicios/ https://www.utaargentina.com/turismo/ https://www.utaargentina.com/afiliate-a-uta/ https://www.mutualuta.com.ar/site/

Sheet Servicios
A1: ID | B1: Sindicato | C1: Servicio | D1: Modalidad | E1: Categoría | F1: Descripción | G1: URL fuente | H1: Propuestas Colm3na | I1: Cobertura Colm3na | J1: Cómo lo cubre
A2: ADEF-1 | B2: ADEF | C2: Simulador de liquidación de haberes | D2: online | E2: tramites | F2: Calculadora web (app.adef.org.ar/simulador) donde el empleado de farmacia estima su recibo de sueldo según la escala vigente del CCT. Vinculado desde la sección de escalas salariales. Abierto sin login (no se pudo verificar el detalle de campos porque la app carga por JS). | G2: https://www.adef.org.ar/simulador | H2: P14, P16 | I2: Corto plazo | J2: Simulador de haberes (P14).
A3: ADEF-2 | B3: ADEF | C3: Simulador de vacaciones | D3: online | E3: tramites | F3: Segunda calculadora web (app.adef.org.ar/simulador/holiday) que liquida el plus vacacional / días de vacaciones que corresponden al trabajador. Herramienta abierta desde el sitio. | G3: https://www.adef.org.ar/simulador-vacaciones | H3: P14 | I3: Corto plazo | J3: Simulador de vacaciones (P14).
A4: ADEF-3 | B4: ADEF | C4: Escalas salariales históricas 2003-2026 | D4: online | E4: tramites | F4: Archivo completo de escalas salariales por año desde 2003 hasta la vigente (mayo 2026), publicadas como páginas web navegables, más sección de legislación laboral y normativas. | G4: https://www.adef.org.ar/escala-salarial | I4: Hoy | J4: Escalas históricas: Fórmulas con vigencia + Novedades.
A5: ADEF-4 | B5: ADEF | C5: ADEF Responde (atención 24 hs) | D5: semi-online | E5: comunicacion | F5: Canal de consultas 24 horas vía 0800-345-0299, WhatsApp +54 9 11 2322-3662 y plataforma web app.adef.org.ar/responde. Orientado principalmente a consultas sobre la cartilla de prestadores de OSADEF, pero es el canal de atención unificado del sindicato. [Reclasificado a semi-online: atención por 0800/WhatsApp.] | G5: https://www.adef.org.ar/adef-responde | H5: P17 | I5: Desarrollo mayor | J5: Canal 24 hs unificado: bot omnicanal (P17, ola 2).
A6: ADEF-5 | B6: ADEF | C6: Sistema de Aportes en Línea (empleadores) | D6: online | E6: tramites | F6: Plataforma 24x7 donde las farmacias empleadoras cargan la planilla de retención de afiliados y generan boletas bancarias con código de barras (Banco Nación / Banco Provincia). Alta con CUIT y contraseña; incluye manual de usuario y soporte 9-17 hs por WhatsApp, teléfono y mail. Elimina el envío de documentación mensual. | G6: https://www.adef.org.ar/sistema-de-aportes-en-linea | H6: P15 | I6: Desarrollo mayor | J6: Aportes en línea: P15.
A7: ADEF-6 | B7: ADEF | C7: Turismo social: complejos hoteleros propios | D7: semi-online | E7: recreacion | F7: Hoteles/complejos propios en Mar del Plata, Mendoza, Cosquín y otros, solo alojamiento, para afiliado y grupo familiar primario (otros familiares con tarifa diferenciada). Se consultan precios en la web, se reserva por mail o WhatsApp de la Secretaría de Turismo con número de afiliado, pasajeros, fechas y régimen; seña en 48 hs, saldo en cuotas por depósito bancario, y se recibe voucher por correo. | G7: https://www.adef.org.ar/turismo-social/preguntas-frecuentes | H7: P20 | I7: Hoy | J7: Reserva con formularios encadenados (solicitud → confirmación de disponibilidad por el sindicato → registro), semi-automática hoy; automatizable con carga de recursos y vacantes (P20, bajo esfuerzo).
A8: ADEF-7 | B8: ADEF | C8: Miniturismo (paquetes con traslado y excursiones) | D8: semi-online | E8: recreacion | F8: Paquetes cortos que incluyen traslados + hotelería + excursiones, publicados por temporada (precios de invierno desde mediados de abril; verano desde fin de octubre). Mismo circuito de reserva por mail/WhatsApp con 15-30 días de anticipación. | G8: https://www.adef.org.ar/turismo-social/miniturismo | I8: Hoy | J8: Reserva con formularios encadenados (solicitud → confirmación de disponibilidad por el sindicato → registro), semi-automática hoy; automatizable con carga de recursos y vacantes (P20, bajo esfuerzo).
A9: ADEF-8 | B9: ADEF | C9: Campos recreativos | D9: presencial | E9: recreacion | F9: Predios recreativos 'Eva Perón' y 'Jorge Di Pascuale' abiertos todo el año y otros abiertos del 15/12 al 15/3, para afiliados y familia. Acceso presentando credencial. | G9: https://www.adef.org.ar/turismo-social/campos-recreativos | I9: Hoy | J9: Campos recreativos con credencial: acceso hoy; registro en P19.
A10: ADEF-9 | B10: ADEF | C10: Salón de fiestas 'Don Alfredo' | D10: presencial | E10: recreacion | F10: Salón de fiestas propio del sindicato para eventos de afiliados; se consulta disponibilidad por contacto. | G10: https://www.adef.org.ar/salon-de-fiestas/ | I10: Hoy | J10: Reserva con formularios encadenados (solicitud → confirmación de disponibilidad por el sindicato → registro), semi-automática hoy; automatizable con carga de recursos y vacantes (P20, bajo esfuerzo).
A11: ADEF-10 | B11: ADEF | C11: Plan de Viviendas 'Parque Los Nogales' | D11: presencial | E11: beneficios | F11: Barrio de 180 viviendas unifamiliares (2-3 dormitorios, lotes de 250 m2) en Tristán Suárez, Ezeiza, surgido de un censo habitacional de afiliados. La web describe el proyecto pero no el proceso de inscripción; consultas por 0800/WhatsApp. | G11: https://www.adef.org.ar/institucional/plan-viviendas | I11: No aplica | J11: Infraestructura física o programa de vivienda: fuera del alcance de la plataforma (se puede difundir como Novedad).
A12: ADEF-11 | B12: ADEF | C12: Centro de Formación Profesional N°26 (auxiliar de farmacia) | D12: semi-online | E12: formacion | F12: Centro de formación propio (centro26.com.ar) con cursos de Auxiliar de Farmacia, Farmacología, Farmacotecnia y Cosmética, más Laboratorio Escuela 'Jorge Di Pascuale'; entrega de diplomas anual. Inscripción a través del centro. | G12: https://www.centro26.com.ar/ | H12: P21, P22 | I12: Desarrollo mayor | J12: Centro de formación: Capacitación (P22).
A13: ADEF-12 | B13: ADEF | C13: Licenciatura en Farmacia y Centro de Idiomas (UMET) | D13: semi-online | E13: formacion | F13: Convenio con la UMET para que afiliados cursen la Licenciatura en Farmacia y accedan a un Centro de Idiomas; la inscripción se hace en la universidad. | G13: https://www.adef.org.ar/novedades/2335-tu-futuro-empieza-hoy | H13: P09, P26 | I13: Corto plazo | J13: Licenciatura UMET: constancia (P09).
A14: ADEF-13 | B14: ADEF | C14: Videos de capacitación y publicaciones técnicas | D14: online | E14: no-afiliados | F14: Biblioteca online de videos de capacitación y manuales (Farmacología, Farmacotecnia, Cosmética) descargables desde la web, abiertos a cualquier trabajador del sector. | G14: https://www.adef.org.ar/capacitacion/videos-de-capacitacion | H14: P18 | I14: Corto plazo | J14: Biblioteca abierta de videos y manuales (P18, ola 1).
A15: ADEF-14 | B15: ADEF | C15: FarmaTrivia (gamificación de capacitación) | D15: online | E15: formacion | F15: Plataforma web (farmatrivia.ar) con registro de usuario donde empleados de farmacia responden trivias mensuales sobre productos/laboratorios y ganan premios; tiene secciones 'Premios' y 'Ganadores'. Exclusiva para empleados de farmacias. | G15: https://farmatrivia.ar/ | H15: P31 | I15: Desarrollo mayor | J15: Trivia con premios (P31, ola 2).
A16: ADEF-15 | B16: ADEF | C16: Tienda online de la Mutual AMDEF | D16: online | E16: beneficios | F16: E-commerce de la mutual con útiles escolares, alimentos y artículos de limpieza para asociados, con cuenta de usuario y carrito; consultas por WhatsApp. No se detallan créditos ni subsidios en la web. | G16: https://mutual.adef.org.ar/ | H16: P24, P34 | I16: Desarrollo mayor | J16: Tienda de la mutual (P24/P34).
A17: ADEF-16 | B17: ADEF | C17: Descuento SportClub | D17: presencial | E17: beneficios | F17: Convenio de descuento en la cadena de gimnasios SportClub para afiliados, publicado como novedad. | G17: https://www.adef.org.ar/novedades/537-beneficios-sportclub | I17: Hoy | J17: SportClub: Beneficios.
A18: ADEF-17 | B18: ADEF | C18: Publicaciones, podcast y revista | D18: online | E18: comunicacion | F18: Sección de publicaciones con libros, revistas, podcast, anuario 2024/2025 y canales de YouTube/Vimeo con programas propios; comunicación institucional y cultural. | G18: https://www.adef.org.ar/publicaciones/historia/ | I18: No aplica | J18: Publicaciones y podcast: contenido editorial (enlace desde Novedades).
A19: ADEF-18 | B19: ADEF | C19: Delegados comunales y de PBA (mapa) | D19: online | E19: comunicacion | F19: Listado de delegados por comuna de CABA y por zona de provincia de Buenos Aires para que el trabajador ubique a su referente gremial. | G19: https://www.adef.org.ar/institucional/delegados-comunales | H19: P11, P28 | I19: Desarrollo mayor | J19: Directorio de delegados (P11, ola 2).
A20: CAMIONEROS-1 | B20: CAMIONEROS | C20: Sede Digital - autogestión del afiliado | D20: online | E20: tramites | F20: Portal web donde el afiliado crea usuario con CUIL y clave y gestiona trámites online (confirmado: solicitud del beneficio por nacimiento para CABA/GBA). La web no lista el catálogo completo de trámites disponibles tras el login. | G20: https://sededigital.camioneros-ba.org.ar/ | I20: Hoy | J20: Portal de autogestión: app del trabajador.
A21: CAMIONEROS-2 | B21: CAMIONEROS | C21: App CamionerosBA | D21: online | E21: comunicacion | F21: Aplicación móvil oficial en Google Play y App Store con información del sindicato para el afiliado. La nota de lanzamiento no detalla funciones (credencial, turnos, escalas); consultas a Secretaría de Comunicación 4378-1412. | G21: http://camioneros-ba.org.ar/index.php/sindicato/novedades/537-nueva-app-camionerosba | I21: Hoy | J21: App: app del trabajador (PWA).
A22: CAMIONEROS-3 | B22: CAMIONEROS | C22: Beneficio por nacimiento | D22: online | E22: beneficios | F22: Ayuda económica única para afiliados que fueron padres/madres, con mínimo 6 meses de aportes y solicitud dentro de los 3 meses del nacimiento. Documentación: credencial de obra social, último recibo, DNI del bebé y partida. Se tramita online en Sede Digital (CABA/GBA), en sede central/delegación, o vía seccional en provincia. | G22: https://www.camioneros-ba.org.ar/index.php/nacimientos | H22: P01 | I22: Corto plazo | J22: Subsidio por nacimiento online (P01, ola 1).
A23: CAMIONEROS-4 | B23: CAMIONEROS | C23: Becas universitarias y becas de Enfermería | D23: semi-online | E23: beneficios | F23: Becas para hijos de afiliados que cursan estudios universitarios, y programa específico de becas de Enfermería Profesional. Se solicitan online, en sede central o delegación. | G23: https://www.camioneros-ba.org.ar/index.php/2013-03-01-07-42-21 | I23: Corto plazo | J23: Becas como campaña con cupo (P04).
A24: CAMIONEROS-5 | B24: CAMIONEROS | C24: Guardapolvos y útiles escolares + consulta online | D24: semi-online | E24: beneficios | F24: Entrega anual de kit de útiles y guardapolvos para hijos de afiliados (el contenido más visitado del sitio, ~30.000 visitas). Existe una 'Consulta de útiles' en Servicios en Línea para que el afiliado verifique su solicitud/entrega (la URL exacta devolvió 404 al momento del relevamiento). | G24: https://www.camioneros-ba.org.ar/index.php/secretarias | H24: P04 | I24: Corto plazo | J24: Campaña de útiles con consulta de estado (P04, ola 1).
A25: CAMIONEROS-6 | B25: CAMIONEROS | C25: Subsidio por fallecimiento y sepelio | D25: presencial | E25: beneficios | F25: Ayuda económica por fallecimiento del afiliado o familiar y servicio de sepelio gestionados por Acción Social. Trámite presencial en sede/delegación con documentación (Tel. 4378-1011). | G25: https://www.camioneros-ba.org.ar/index.php/2015-04-16-17-59-12/secretaria-de-accion-social | I25: Corto plazo | J25: Subsidio por fallecimiento (P01) y ficha de emergencias (P29).
A26: CAMIONEROS-7 | B26: CAMIONEROS | C26: Alojamiento para estudiantes y para pacientes del interior | D26: presencial | E26: beneficios | F26: Hospedaje en CABA para hijos de afiliados del interior bonaerense que estudian (requiere credencial vigente, certificado de alumno regular y recibo del titular) y para afiliados en tratamiento médico con autorización de su seccional. | G26: https://www.camioneros-ba.org.ar/index.php/2015-04-16-17-59-12/secretaria-de-accion-social | I26: Hoy | J26: Reserva con formularios encadenados (solicitud → confirmación de disponibilidad por el sindicato → registro), semi-automática hoy; automatizable con carga de recursos y vacantes (P20, bajo esfuerzo).
A27: CAMIONEROS-8 | B27: CAMIONEROS | C27: Área Discapacidad y ambulancias programadas | D27: presencial | E27: beneficios | F27: Atención a afiliados con familiares con discapacidad (presupuesto y requisitos 2026 publicados; línea 4378-1003) y coordinación de ambulancias programadas. Parte se canaliza por obra social OSCHOCA. | G27: https://www.camioneros-ba.org.ar/index.php/2015-04-16-17-59-12/secretaria-de-accion-social | I27: Hoy | J27: Área de discapacidad: consulta por trámite; la parte de ambulancias es de obra social.
A28: CAMIONEROS-9 | B28: CAMIONEROS | C28: Escalas salariales online e histórico desde 1969 | D28: online | E28: tramites | F28: Escala vigente (agosto 2026) consultable en la web, histórico de escalas desde 1969, acuerdos y homologaciones. FEDCAM publica planillas de sueldos desde 1978. Formato de lectura/descarga, sin calculadora. | G28: https://www.camioneros-ba.org.ar/index.php/gremiales/salarios/escalas-salariales | H28: P14 | I28: Hoy | J28: Escalas e histórico en Novedades y Fórmulas; buscador en P14.
A29: CAMIONEROS-10 | B29: CAMIONEROS | C29: Acuerdos por empresa (portal con login) | D29: online | E29: tramites | F29: Sistema con usuario y contraseña (convenios.camioneros.org.ar / acuerdos.spdps.com.ar) para consultar acuerdos salariales específicos de cada empresa. Público objetivo no explicitado (delegados/empresas). | G29: http://convenios.camioneros.org.ar/ | I29: Hoy | J29: Acuerdos por empresa: Fórmulas por empleador + Novedades segmentadas.
A30: CAMIONEROS-11 | B30: CAMIONEROS | C30: Planilla de kilometraje | D30: online | E30: tramites | F30: Planilla descargable para que el chofer registre kilómetros recorridos y calcule el adicional por km del CCT 40/89. Herramienta práctica para control del recibo. | G30: https://www.camioneros-ba.org.ar/index.php/gremiales/salarios/planilla-km | H30: P10, P14 | I30: Corto plazo | J30: Registro de km como evidencia y cálculo del adicional (P10/P14).
A31: CAMIONEROS-12 | B31: CAMIONEROS | C31: Asesoramiento salarial y por accidentes de trabajo | D31: presencial | E31: legal-previsional | F31: Asesoramiento sobre liquidación de haberes y sobre accidentes/enfermedades laborales (Secretaría de Accidentes de Trabajo en FEDCAM). Contacto por ramas de actividad, teléfono o presencial. | G31: https://www.camioneros-ba.org.ar/ | I31: Hoy | J31: Asesoramiento salarial: validador de recibos + consulta por trámite; accidentes por trámite.
A32: CAMIONEROS-13 | B32: CAMIONEROS | C32: Psicofísico (examen para licencia) | D32: semi-online | E32: tramites | F32: Información y sistema de arancel/turno para el examen psicofísico requerido por la Licencia Nacional de Transporte Interjurisdiccional (LiNTI), con enlace al trámite en argentina.gob.ar y sistema psicofisico.impresiondeboletas.com.ar. | G32: https://www.camioneros-ba.org.ar/index.php/gremiales/otros/psicofisico | H32: P23 | I32: Desarrollo mayor | J32: Habilitantes con vencimiento y turno (P23/P12, ola 2).
A33: CAMIONEROS-14 | B33: CAMIONEROS | C33: Atención ANSES (ULAT) | D33: presencial | E33: legal-previsional | F33: Unidad de Atención ANSES dentro del sindicato para trámites previsionales (jubilación, asignaciones) de afiliados sin ir a una oficina de ANSES. | G33: https://www.camioneros-ba.org.ar/ | H33: P12, P13 | I33: Desarrollo mayor | J33: Turnos para servicios de terceros en sede (P12, ola 2).
A34: CAMIONEROS-15 | B34: CAMIONEROS | C34: Hoteles, cabañas, campings y recreos | D34: semi-online | E34: beneficios | F34: 4 hoteles/cabañas y 6 campings/recreos propios para afiliados y familias. Información en web; reserva por teléfono (Secretaría de Turismo 4378-1050) o formulario de contacto. Tarifas no publicadas. | G34: https://www.camioneros-ba.org.ar/index.php/turismo | H34: P20 | I34: Hoy | J34: Reserva con formularios encadenados (solicitud → confirmación de disponibilidad por el sindicato → registro), semi-automática hoy; automatizable con carga de recursos y vacantes (P20, bajo esfuerzo).
A35: CAMIONEROS-16 | B35: CAMIONEROS | C35: Viaje de bodas | D35: presencial | E35: beneficios | F35: Programa de viaje de luna de miel para afiliados recién casados gestionado por Turismo. Solicitud con acta de matrimonio, presencial/telefónica. | G35: https://www.camioneros-ba.org.ar/index.php/turismo | I35: Corto plazo | J35: Viaje de bodas: voucher (P02).
A36: CAMIONEROS-17 | B36: CAMIONEROS | C36: Camioneritos (colonia/recreación infantil) | D36: presencial | E36: recreacion | F36: Programa recreativo para hijos de afiliados (colonia de vacaciones/actividades) dentro de la sección Turismo. Inscripción presencial. | G36: https://www.camioneros-ba.org.ar/index.php/turismo | I36: Corto plazo | J36: Camioneritos: inscripción (P04).
A37: CAMIONEROS-18 | B37: CAMIONEROS | C37: Club Camioneros y deportes | D37: presencial | E37: recreacion | F37: Club deportivo del sindicato y Secretaría de Deportes con torneos y actividades para afiliados y familias. | G37: https://www.camioneros-ba.org.ar/ | I37: Corto plazo | J37: Club y deportes: inscripciones (P04).
A38: CAMIONEROS-19 | B38: CAMIONEROS | C38: Vivienda | D38: presencial | E38: beneficios | F38: Secretaría de Vivienda (sindicato y federación) con programas de acceso a la vivienda para afiliados; sin detalle de mecanismo en web. | G38: https://www.camioneros-ba.org.ar/index.php/2015-04-16-17-59-12/secretaria-de-la-vivienda | I38: No aplica | J38: Vivienda.
A39: CAMIONEROS-20 | B39: CAMIONEROS | C39: Prevención de adicciones y campañas de seguridad vial/fatiga | D39: presencial | E39: otro | F39: Programas de prevención (adicciones, fatiga al volante, seguridad vial) con materiales y galerías de prevención; enfoque en la salud ocupacional del chofer. | G39: https://www.fedcam.org.ar/ | H39: P30 | I39: Corto plazo | J39: Campañas de prevención: Novedades segmentadas y encuestas (P30).
A40: CAMIONEROS-21 | B40: CAMIONEROS | C40: Formación política-sindical y Biblioteca Sindical | D40: semi-online | E40: formacion | F40: Secretaría de Formación con cursos para delegados y afiliados; FEDCAM mantiene una biblioteca sindical digital y revista 'Los Camioneros'. | G40: https://www.fedcam.org.ar/index.php/nuestra-federacion/publicaciones/biblioteca-sindical | I40: Desarrollo mayor | J40: Formación sindical y biblioteca: P22; biblioteca en P18 (corto).
A41: CAMIONEROS-22 | B41: CAMIONEROS | C41: Libre deuda y conflicto (empresas) | D41: online | E41: otro | F41: Consulta online de certificado de libre deuda sindical y de conflicto para empresas de transporte; junto con inscripción/reempadronamiento, contribución solidaria, impresión de boletas y pago de aportes por CBU forman el módulo de autogestión de empleadores. | G41: https://www.camioneros-ba.org.ar/index.php/gremiales/otros/libre-deuda | H41: P15 | I41: Desarrollo mayor | J41: Libre deuda y autogestión de empleadores: P15.
A42: SETIA-1 | B42: SETIA | C42: Credencial digital móvil | D42: online | E42: tramites | F42: Credencial digital del afiliado accesible desde una web app móvil (setiaonline/mobile) enlazada desde SETIA Online, que reemplaza el carnet físico para identificarse en hoteles, sede y beneficios. El detalle del alta de usuario no está publicado. | G42: https://setia.org.ar/?page_id=25 | H42: P19 | I42: Hoy | J42: Credencial digital con QR.
A43: SETIA-2 | B43: SETIA | C43: App móvil 'Setia App' | D43: online | E43: comunicacion | F43: Aplicación propia promocionada en la home ('Bajate la App de Setia') publicada como web app en app.setia.ar. La landing no expone funciones sin JavaScript; por contexto integra credencial, novedades y beneficios (no verificado). | G43: https://app.setia.ar/#/landing | I43: Hoy | J43: App propia: app del trabajador.
A44: SETIA-3 | B44: SETIA | C44: Portal de reservas de turismo online | D44: online | E44: recreacion | F44: Web app turismo.setia.ar para reservar en los hoteles propios (San Clemente, Bariloche, Mar del Plata, Córdoba) y el camping de Ezeiza, con tarifario. También se puede reservar por teléfono en cada hotel o con el formulario '06 – Solicitud Turismo' descargable. Dirigido a afiliados y familia. | G44: https://setia.org.ar/?page_id=34 | H44: P20 | I44: Hoy | J44: Reserva con formularios encadenados (solicitud → confirmación de disponibilidad por el sindicato → registro), semi-automática hoy; automatizable con carga de recursos y vacantes (P20, bajo esfuerzo).
A45: SETIA-4 | B45: SETIA | C45: Asesoría Virtual (consultas gremiales online) | D45: online | E45: legal-previsional | F45: Formulario web donde el afiliado ingresa nombre, N° de afiliado, DNI, mail y su consulta (con captcha), que se deriva al área correspondiente. Antes se lo invita a revisar la sección de Preguntas Frecuentes. Es el canal digital de consulta laboral/gremial. | G45: https://setia.org.ar/?page_id=13 | H45: P10, P17 | I45: Hoy | J45: Asesoría virtual con nro. de afiliado: trámites/consultas.
A46: SETIA-5 | B46: SETIA | C46: Preguntas frecuentes de afiliados | D46: online | E46: comunicacion | F46: Sección de FAQ orientada a resolver dudas comunes (afiliación, aportes, beneficios) antes de usar la asesoría virtual. | G46: https://setia.org.ar/?page_id=23 | H46: P17, P18 | I46: Corto plazo | J46: FAQ (P18, ola 1).
A47: SETIA-6 | B47: SETIA | C47: Asesoramiento gremial y legal laboral presencial | D47: presencial | E47: legal-previsional | F47: Representación en negociaciones y conflictos bajo el CCT y asesoría personalizada sobre el aspecto laboral en las dependencias del sindicato/seccionales. | G47: https://setia.org.ar/?cat=4 | I47: Hoy | J47: Asesoría presencial: consulta por trámite; turnos en P12.
A48: SETIA-7 | B48: SETIA | C48: Afiliación con formulario descargable | D48: semi-online | E48: tramites | F48: Formulario PDF '02 – Sindicato y Obra Social' (afiliación conjunta) y '05 – Cuota Sindical' que se descargan, completan y presentan en la seccional más cercana. No hay alta online. | G48: https://setia.org.ar/?page_id=15 | I48: Corto plazo | J48: Afiliación online (P08).
A49: SETIA-8 | B49: SETIA | C49: Trámites para empresas: empadronamiento, planilla de aportes y boletas online | D49: online | E49: otro | F49: Formularios de empadronamiento de empresas y planilla de aportes/contribuciones, más 'Boletas Sindicales Online' dentro de SETIA Online para que los empleadores generen y paguen boletas de cuota sindical. Servicio a empresas, no a afiliados. | G49: https://setia.org.ar/?page_id=25 | H49: P15 | I49: Desarrollo mayor | J49: Boletas online para empresas: P15.
A50: SETIA-9 | B50: SETIA | C50: Solicitud y verificación de inspectores | D50: online | E50: otro | F50: Listado público de 18 inspectores habilitados (con mail y teléfono) para que las empresas verifiquen la identidad de quien las inspecciona, más formulario web (razón social, CUIT, mail, teléfono, responsable) para solicitar inspección/auditoría/determinación de deuda vía 'Servicios de Gestión Técnica Integral'. Función de transparencia y anti-fraude. | G50: https://setia.org.ar/?page_id=29 | H50: P15 | I50: Desarrollo mayor | J50: Verificación de inspectores y solicitud de inspección (P15).
A51: SETIA-10 | B51: SETIA | C51: Subsidio por nacimiento | D51: presencial | E51: beneficios | F51: Asignación económica del sindicato al nacer un hijo de afiliado; se gestiona en seccional con la documentación del nacimiento. | G51: https://setia.org.ar/?cat=4 | H51: P01 | I51: Corto plazo | J51: Subsidio por nacimiento (P01).
A52: SETIA-11 | B52: SETIA | C52: Luna de miel y Bodas de Oro en hotelería propia | D52: presencial | E52: beneficios | F52: Siete días de hospedaje sin cargo con desayuno en hoteles propios para afiliados recién casados y para parejas que cumplen 50 años de matrimonio. | G52: https://setia.org.ar/?cat=4 | H52: P02 | I52: Corto plazo | J52: Luna de miel y bodas de oro: voucher (P02).
A53: SETIA-12 | B53: SETIA | C53: Útiles escolares | D53: presencial | E53: beneficios | F53: Entrega anual de útiles escolares para hijos de afiliados desde preescolar hasta secundario. | G53: https://setia.org.ar/?cat=4 | I53: Corto plazo | J53: Útiles: campaña (P04).
A54: SETIA-13 | B54: SETIA | C54: Caja de Navidad | D54: presencial | E54: beneficios | F54: Caja navideña con productos de marcas reconocidas entregada a los afiliados en las fiestas. | G54: https://setia.org.ar/?cat=4 | H54: P02, P04 | I54: Corto plazo | J54: Caja de Navidad: campaña con retiro (P04).
A55: SETIA-14 | B55: SETIA | C55: Día del Textil | D55: presencial | E55: recreacion | F55: Evento anual con torneos deportivos, espectáculos musicales y sorteos de autos y motos entre afiliados. | G55: https://setia.org.ar/?cat=4 | H55: P04, P31 | I55: Corto plazo | J55: Día del Textil: inscripciones (P04); sorteo en P31.
A56: SETIA-15 | B56: SETIA | C56: Capacitación | D56: semi-online | E56: formacion | F56: Sección de capacitación con programas de formación para afiliados (categoría de noticias/cursos); el formulario de contacto tiene una opción específica 'Capacitación'. | G56: https://setia.org.ar/?cat=5 | I56: Desarrollo mayor | J56: Capacitación (P22).
A57: SETIA-16 | B57: SETIA | C57: Formulario de contacto segmentado por área | D57: online | E57: comunicacion | F57: Formulario web con selector de destinatario (informes, gremiales, capacitación, turismo, recursos humanos), que enruta la consulta al área correspondiente. | G57: https://setia.org.ar/ | I57: Hoy | J57: Formulario segmentado por área: trámites enrutados por área.
A58: SGBATOS-1 | B58: SGBATOS | C58: App móvil con credencial digital | D58: online | E58: tramites | F58: App para afiliados y su grupo familiar que emite la credencial electrónica del sindicato y de la obra social OSOSS, válida como identificación. El afiliado se registra con DNI y mail; el sistema valida contra el padrón y habilita las funciones según sea afiliado sindical y/o beneficiario de OSOSS. | G58: https://sgbatos.org.ar/app/ | H58: P05, P19 | I58: Hoy | J58: Credencial digital; credencial familiar y de obra social en P19/P05.
A59: SGBATOS-2 | B59: SGBATOS | C59: Consultas a Secretarías desde la app | D59: online | E59: comunicacion | F59: Desde la app el afiliado envía consultas dirigidas a las distintas Secretarías del sindicato (gremial, acción social, etc.) y consultas a la obra social. Funciona como canal de mensajería/ticket interno; la web no detalla tiempos de respuesta ni seguimiento. | G59: https://sgbatos.org.ar/app/ | H59: P11, P17 | I59: Hoy | J59: Consultas a áreas por trámite con conversación.
A60: SGBATOS-3 | B60: SGBATOS | C60: Botón SOS y modo Guardián (emergencias) | D60: online | E60: otro | F60: La app incluye un botón SOS que dispara una alerta con ubicación GPS a una sala de monitoreo para urgencias médicas o de seguridad, y un modo 'Guardián' que programa una alerta temporizada que el usuario debe desactivar cuando pasó el riesgo; si no la desactiva, los operadores llaman a los contactos de emergencia cargados y pueden despachar servicios de emergencia. Requiere GPS y conexión. | G60: https://sgbatos.org.ar/app/ | H60: P29 | I60: Corto plazo | J60: Botón SOS y modo "llegué bien" sobre la georreferenciación existente (P29, ola 1).
A61: SGBATOS-4 | B61: SGBATOS | C61: Noticias, comunicados y beneficios en la app | D61: online | E61: comunicacion | F61: La app distribuye noticias y comunicados del sindicato y de OSOSS, e información sobre turismo, campeonatos de fútbol y beneficios vigentes. Complementa la web, la revista institucional y el canal de YouTube. | G61: https://sgbatos.org.ar/app/ | I61: Hoy | J61: Noticias y beneficios en la app: Novedades y Beneficios.
A62: SGBATOS-5 | B62: SGBATOS | C62: Hoteles 15 de Mayo (Mar del Plata y Villa Carlos Paz) | D62: presencial | E62: recreacion | F62: Hoteles propios con pileta climatizada, spa, gimnasio, cochera y desayuno buffet, disponibles todo el año para afiliados y familia. La web no explica el proceso de reserva (no hay portal de reservas online detectado); se accede vía la sección Turismo y contacto con el sindicato. | G62: https://sgbatos.org.ar/hoteles-turisticos/ | H62: P20 | I62: Hoy | J62: Reserva con formularios encadenados (solicitud → confirmación de disponibilidad por el sindicato → registro), semi-automática hoy; automatizable con carga de recursos y vacantes (P20, bajo esfuerzo).
A63: SGBATOS-6 | B63: SGBATOS | C63: Turismo: convenios de transporte y hotel spa | D63: semi-online | E63: beneficios | F63: Descuentos en pasajes terrestres con las empresas Pulqui y Ruta Atlántica y convenio con Hotel & Spa 'La Chacra' en San Pedro. Se difunden en la web con enlaces 'Conocé más'; la gestión concreta no está detallada. | G63: https://sgbatos.org.ar/turismo/ | I63: Hoy | J63: Convenios de transporte y hotel: Beneficios.
A64: SGBATOS-7 | B64: SGBATOS | C64: Camping 17 de Octubre | D64: presencial | E64: recreacion | F64: Campo recreativo propio en Gregorio de Laferrere con parrillas, quincho, juegos infantiles, canchas de fútbol, pádel, vóley, tenis y básquet, dos piletas, buffet y gimnasio, para uso de afiliados y familia. | G64: https://sgbatos.org.ar/camping-17-de-octubre/ | I64: Hoy | J64: Reserva con formularios encadenados (solicitud → confirmación de disponibilidad por el sindicato → registro), semi-automática hoy; automatizable con carga de recursos y vacantes (P20, bajo esfuerzo).
A65: SGBATOS-8 | B65: SGBATOS | C65: Colonia de vacaciones | D65: presencial | E65: recreacion | F65: Colonia de verano en enero y febrero para hijos de afiliados de 6 a 11 años. Inscripción a través del sindicato; la web no indica formulario online. | G65: https://sgbatos.org.ar/colonia-de-vacaciones/ | H65: P04 | I65: Corto plazo | J65: Colonia: inscripción (P04).
A66: SGBATOS-9 | B66: SGBATOS | C66: Deportes y Copa SGBATOS | D66: presencial | E66: recreacion | F66: Torneos internos de fútbol (Copa SGBATOS) y disciplinas como vóley femenino, fútbol femenino, ajedrez, rugby y básquet. La información de fixtures se distribuye también por la app. | G66: https://sgbatos.org.ar/deportes/ | I66: Corto plazo | J66: Torneos: inscripciones (P04) y Novedades.
A67: SGBATOS-10 | B67: SGBATOS | C67: Convenio SportClub | D67: semi-online | E67: beneficios | F67: Beneficio para acceder a la red de gimnasios SportClub con condiciones para afiliados. Se anuncia como 'nuevo beneficio'; el detalle de adhesión no está en la home. | G67: https://sgbatos.org.ar/nuevo-beneficio-sgbatos-sportclub/ | I67: Hoy | J67: Convenio SportClub: Beneficios.
A68: SGBATOS-11 | B68: SGBATOS | C68: Jardines materno-infantiles 'La Gotita de Agua' | D68: presencial | E68: beneficios | F68: Dos sedes de jardín maternal propio para hijos de afiliados, con sitio web propio (lagotitadeagua.edu.ar). Además existe un reintegro por jardín materno-infantil para quienes usan otros jardines, que fue ampliado. | G68: https://sgbatos.org.ar/jardines-materno-infantil/ | H68: P07 | I68: No aplica | J68: Jardines propios: infraestructura; el reintegro alternativo en P07.
A69: SGBATOS-12 | B69: SGBATOS | C69: Programa de lactancia 'Nutriendo el Futuro' | D69: presencial | E69: beneficios | F69: Programa con beneficios exclusivos para madres y padres afiliados con bebés de hasta 2 años (apoyo a la lactancia). La web no detalla si incluye insumos, reintegros o talleres. | G69: https://sgbatos.org.ar/lactancia/ | H69: P32 | I69: Desarrollo mayor | J69: Programa de lactancia disparado desde el recibo (P32); como beneficio informativo, hoy.
A70: SGBATOS-13 | B70: SGBATOS | C70: Regalo por nacimiento | D70: presencial | E70: beneficios | F70: Al nacer un hijo, el afiliado elige entre un cochecito con huevito o una practicuna. Se tramita ante el sindicato presentando la documentación del nacimiento. | G70: https://sgbatos.org.ar/nacimientos/ | H70: P01, P24 | I70: Corto plazo | J70: Regalo por nacimiento con elección (P01/P24).
A71: SGBATOS-14 | B71: SGBATOS | C71: Beneficio por casamiento | D71: presencial | E71: beneficios | F71: Estadía de 7 días con desayuno en los Hoteles 15 de Mayo para afiliados que contraen matrimonio. | G71: https://sgbatos.org.ar/casamiento/ | H71: P02 | I71: Corto plazo | J71: Estadía por casamiento: voucher (P02).
A72: SGBATOS-15 | B72: SGBATOS | C72: Día del Niño | D72: presencial | E72: beneficios | F72: Entrega de un juguete a cada hijo de afiliado en el Día del Niño. | G72: https://sgbatos.org.ar/dia-del-nino/ | H72: P04 | I72: Corto plazo | J72: Día del Niño: campaña (P04).
A73: SGBATOS-16 | B73: SGBATOS | C73: Becas secundarias | D73: presencial | E73: formacion | F73: 550 becas anuales para hijos de afiliados que cursan la enseñanza secundaria. La web no publica el formulario ni el criterio de asignación. | G73: https://sgbatos.org.ar/becas/ | H73: P04 | I73: Corto plazo | J73: Becas como campaña con cupo (P04).
A74: SGBATOS-17 | B74: SGBATOS | C74: Kit escolar (guardapolvo, mochila y útiles) | D74: presencial | E74: beneficios | F74: Kit escolar con mochila, útiles y guardapolvo para hijos de afiliados que concurren a escuela pública. Entrega anual presencial. | G74: https://sgbatos.org.ar/guardapolvos-y-utiles/ | I74: Corto plazo | J74: Kit escolar: campaña (P04).
A75: SGBATOS-18 | B75: SGBATOS | C75: Institutos educativos propios (ITLM e IUAS) | D75: semi-online | E75: formacion | F75: Instituto Tecnológico Leopoldo Marechal (formación técnica) e Instituto Universitario del Agua y Saneamiento (formación universitaria vinculada al rubro), con sitios propios; orientados a afiliados, familia y en principio abiertos al público. | G75: https://www.iuas.edu.ar/ | I75: Desarrollo mayor | J75: Institutos propios: Capacitación (P22) y semillero (P21).
A76: SGBATOS-19 | B76: SGBATOS | C76: Caja Complementaria para jubilados | D76: presencial | E76: legal-previsional | F76: Haber complementario mensual que el sindicato paga a jubilados y pensionados de la actividad, financiado con un aporte mensual de los trabajadores activos. Es una caja propia de complemento previsional (la página de detalle no respondió). | G76: https://sgbatos.org.ar/caja-complementaria/ | H76: P13, P34 | I76: Desarrollo mayor | J76: Caja complementaria como entidad vinculada (P34) y ruta jubilatoria (P13).
A77: SGBATOS-20 | B77: SGBATOS | C77: Centro Sanitarista de la Tercera Edad | D77: presencial | E77: recreacion | F77: Espacio con talleres y actividades de encuentro para afiliados mayores y jubilados. | G77: https://sgbatos.org.ar/centro-sanitarista-de-la-tercera-edad/ | I77: Corto plazo | J77: Centro de tercera edad: agenda e inscripciones (P04); nivel jubilado (P03).
A78: SGBATOS-21 | B78: SGBATOS | C78: Servicio de cochería fúnebre | D78: presencial | E78: beneficios | F78: Convenio con Cochería Caramuto que cubre traslado en ambulancia, sala velatoria, ataúd, coche fúnebre y de acompañamiento, para afiliados activos y jubilados. | G78: https://sgbatos.org.ar/cocheria-funebre/ | H78: P29 | I78: Corto plazo | J78: Cochería: ficha de emergencias (P29).
A79: SGBATOS-22 | B79: SGBATOS | C79: Secretaría de Género e Igualdad | D79: presencial | E79: otro | F79: Área específica con página propia de iniciativas de género e igualdad; funciona como punto de contacto/acompañamiento para afiliadas. | G79: https://sgbatos.org.ar/genero | I79: Hoy | J79: Secretaría de género: área con perfil y trámite confidencial.
A80: SGBATOS-23 | B80: SGBATOS | C80: Revista y contenido institucional | D80: online | E80: comunicacion | F80: Revistas institucionales digitalizadas, sección 'En Clave Sanitarista' de noticias y canal de YouTube, además de redes sociales. | G80: https://sgbatos.org.ar/revista | I80: Hoy | J80: Revista y contenido: Novedades.
A81: STPCHPYA-1 | B81: STPCHPYA | C81: Carnet digital en app ELEVAR | D81: online | E81: tramites | F81: El afiliado descarga la app ELEVAR, se registra con el mail declarado al afiliarse y obtiene el carnet digital con la misma validez que el físico, que presenta junto a DNI y recibo. Si no tiene mail registrado debe actualizar datos en una sede. Incluye advertencia antifraude. | G81: https://pasteleros.org/carnet-digital/ | H81: P19 | I81: Hoy | J81: Credencial digital con QR.
A82: STPCHPYA-2 | B82: STPCHPYA | C82: Afiliación presencial con requisitos publicados | D82: presencial | E82: tramites | F82: Cualquier trabajador con recibo de sueldo se afilia en una sede con recibo y DNI; con menos de 3 meses de antigüedad presenta F.931 y nómina AFIP. Se detalla la documentación del grupo familiar (certificación ANSES, cónyuge, hijos, estudios para mayores de 21). | G82: https://pasteleros.org/trabajadores/ | H82: P05, P18 | I82: Corto plazo | J82: Afiliación online con grupo familiar (P08/P05).
A83: STPCHPYA-3 | B83: STPCHPYA | C83: Asesoramiento laboral y abogados laborales | D83: presencial | E83: legal-previsional | F83: Servicio sindical de asesoramiento laboral con abogados para afiliados, en sede. Sin canal online publicado. | G83: https://pasteleros.org/trabajadores/ | I83: Hoy | J83: Asesoramiento laboral: consulta por trámite; turnos en P12.
A84: STPCHPYA-4 | B84: STPCHPYA | C84: Gestoría previsional (jubilación) | D84: presencial | E84: legal-previsional | F84: Gestoría para tramitar la jubilación de los afiliados, incluida en los servicios del sindicato. | G84: https://pasteleros.org/trabajadores/ | I84: Hoy | J84: Gestoría previsional: consulta por trámite; P13 después.
A85: STPCHPYA-5 | B85: STPCHPYA | C85: Convenios y revisión salarial por rama | D85: online | E85: tramites | F85: Sección de convenios (CCT 739/16 y otros por rama) y actas de revisión salarial para consulta de trabajadores y empresas. | G85: https://pasteleros.org/convenios/ | I85: Hoy | J85: Convenios por rama: Fórmulas + Novedades.
A86: STPCHPYA-6 | B86: STPCHPYA | C86: Ajuar por nacimiento (mutual) | D86: presencial | E86: beneficios | F86: Kit de ajuar para asociadas embarazadas, retirable desde la semana 30 hasta el tercer mes del bebé, con certificado médico. Requiere 1 año de antigüedad y estar al día. Retiro presencial en sedes. | G86: https://pasteleros.org/subsidios-y-beneficios/ | I86: Corto plazo | J86: Ajuar de la mutual: subsidio en especie (P01); entidad en P34.
A87: STPCHPYA-7 | B87: STPCHPYA | C87: Plan Materno Infantil (mutual) | D87: presencial | E87: beneficios | F87: Subsidio mensual de $37.000 hasta los 2 años del hijo para trabajadoras activas en relación de dependencia, con partida de nacimiento y recibo con descuento mutual. Trámite presencial. | G87: https://pasteleros.org/subsidios-y-beneficios/ | H87: P34 | I87: Desarrollo mayor | J87: Plan materno infantil mensual: reintegro/subsidio recurrente (P07/P32).
A88: STPCHPYA-8 | B88: STPCHPYA | C88: Subsidio por casamiento (mutual) | D88: presencial | E88: beneficios | F88: Pago único de $79.000 a socios activos o adherentes que se casan, con certificado de matrimonio y DNI de ambos. Presencial. | G88: https://pasteleros.org/subsidios-y-beneficios/ | H88: P01 | I88: Corto plazo | J88: Subsidio por casamiento (P01).
A89: STPCHPYA-9 | B89: STPCHPYA | C89: Prestación por fallecimiento (mutual) | D89: presencial | E89: beneficios | F89: Ayuda de $660.000 a los beneficiarios designados del asociado fallecido, con certificado de defunción, carnet, último recibo y libreta de casamiento si corresponde. | G89: https://pasteleros.org/subsidios-y-beneficios/ | I89: Corto plazo | J89: Prestación por fallecimiento (P01/P29).
A90: STPCHPYA-10 | B90: STPCHPYA | C90: Subsidio por hijo con discapacidad (mutual) | D90: presencial | E90: beneficios | F90: $40.000 mensuales a socios activos con hijos con discapacidad a cargo, con certificado ANSES y recibo con asignación; incluye evaluación médica de la institución. | G90: https://pasteleros.org/subsidios-y-beneficios/ | I90: Desarrollo mayor | J90: Subsidio mensual por hijo con discapacidad: recurrente (P07/P32) con CUD en padrón (P05).
A91: STPCHPYA-11 | B91: STPCHPYA | C91: FOCOM - Fondo Compensatorio Mutual | D91: presencial | E91: beneficios | F91: Fondo de previsión para 'asegurar el futuro familiar' de los asociados; se consulta telefónicamente (opción 3) y tiene página propia. | G91: https://pasteleros.org/caba/focom/ | I91: Desarrollo mayor | J91: Fondo compensatorio de la mutual (P34).
A92: STPCHPYA-12 | B92: STPCHPYA | C92: Ayudas económicas / créditos personales (mutual) | D92: presencial | E92: beneficios | F92: Créditos personales para asociados de la mutual; la web los enuncia con página propia sin tasas ni plazos, consulta por teléfono o WhatsApp de la mutual. | G92: https://pasteleros.org/creditos-personales/ | H92: P06 | I92: Desarrollo mayor | J92: Créditos de la mutual (P06/P34).
A93: STPCHPYA-13 | B93: STPCHPYA | C93: Electrodomésticos 'Hogar' (mutual) | D93: presencial | E93: beneficios | F93: Programa de venta de electrodomésticos para asociados con financiación mutual; detalle de planes no publicado. | G93: https://pasteleros.org/hogar/ | H93: P24 | I93: Desarrollo mayor | J93: Electrodomésticos financiados (P24/P06).
A94: STPCHPYA-14 | B94: STPCHPYA | C94: Reintegros y descuentos (óptica, ortopedia, útiles, farmacia) | D94: presencial | E94: beneficios | F94: La mutual reintegra gastos de óptica, ortopedia y útiles escolares y otorga descuentos farmacéuticos a asociados; sección 'Reintegros' y 'Prestaciones gratuitas' en la web. Trámite presencial con comprobantes. | G94: https://pasteleros.org/reintegros/ | H94: P07 | I94: Desarrollo mayor | J94: Reintegros con lectura de factura (P07, ola 2).
A95: STPCHPYA-15 | B95: STPCHPYA | C95: Hoteles y cabañas propias | D95: semi-online | E95: beneficios | F95: Siete alojamientos propios (Majestic Córdoba, Saint Honoré Mar del Plata, Konke El Calafate y Konke Buenos Aires, apart en City Bell, cabañas en E. Echeverría, hostal en San Miguel) más destinos en convenio (Mendoza). Reserva por mail, WhatsApp, teléfono o presencial en el Departamento de Turismo; tarifas no publicadas. | G95: https://pasteleros.org/categoria/turismo/alojamientos-propios/ | H95: P20 | I95: Hoy | J95: Reserva con formularios encadenados (solicitud → confirmación de disponibilidad por el sindicato → registro), semi-automática hoy; automatizable con carga de recursos y vacantes (P20, bajo esfuerzo).
A96: STPCHPYA-16 | B96: STPCHPYA | C96: Descuentos en pasajes y espacios deportivos | D96: presencial | E96: recreacion | F96: Recreación: descuentos en pasajes y acceso a espacios deportivos propios para afiliados, enunciados en la sección trabajadores. | G96: https://pasteleros.org/trabajadores/ | I96: Hoy | J96: Descuentos en pasajes y espacios: Beneficios.
A97: STPCHPYA-17 | B97: STPCHPYA | C97: Escuela de Pastelería Profesional | D97: semi-online | E97: formacion | F97: Escuela propia con formación profesional presencial y cursos online (sitio escueladepasteleria.com.ar) orientada a la inserción laboral; contacto por mail/teléfono. Ambiguo si es solo para afiliados o abierta al público (la escuela se promociona como institución educativa general). | G97: https://www.escueladepasteleria.com.ar/cursos-online/ | H97: P22 | I97: Desarrollo mayor | J97: Escuela de pastelería: P22.
A98: STPCHPYA-18 | B98: STPCHPYA | C98: Sección Empresas | D98: online | E98: no-afiliados | F98: Información para empleadores del rubro (convenios, aportes, contacto). Servicio a no afiliados del lado empleador. | G98: https://pasteleros.org/empresas/ | I98: Desarrollo mayor | J98: Sección empresas: módulo Empleadores hoy (notificaciones y trámites); boletas en P15.
A99: STPCHPYA-19 | B99: STPCHPYA | C99: WhatsApp de mutual y turismo | D99: semi-online | E99: comunicacion | F99: Líneas de WhatsApp dedicadas para consultas de la mutual (+54 9 11 2411 3879) y reservas de turismo (11 2411-3882), además de teléfonos con horarios publicados. | G99: https://pasteleros.org/subsidios-y-beneficios/ | H99: P17, P27 | I99: Hoy | J99: Consultas por área vía trámites; WhatsApp como canal en P17/P27.
A100: STPCHPYA-20 | B100: STPCHPYA | C100: Carnet digital (app ELEVAR) | D100: semi-online | E100: tramites | F100: El afiliado descarga la app ELEVAR, se registra con el mail declarado en su afiliación y accede a su carnet sindical digital, con igual validez que el físico. Requiere que el mail esté cargado; si no, actualización presencial de datos en una sede. | G100: https://pasteleros.org/carnet-digital/ | I100: Hoy | J100: Credencial digital con QR.
...

Sheet Cobertura
A1: Sigla | B1: Servicios | C1: Hoy | D1: Corto plazo | E1: Desarrollo mayor | F1: No aplica | G1: Cubrible hoy + corto | H1: % cubrible | I1: Vacancias digitales | J1: Vacancias cubribles a corto plazo | K1: % vacancias cubribles
A2: ADEF | B2: =COUNTIF(Servicios!B:B,A2) -> 18 | C2: =COUNTIFS(Servicios!B:B,A2,Servicios!I:I,"Hoy") -> 6 | D2: =COUNTIFS(Servicios!B:B,A2,Servicios!I:I,"Corto plazo") -> 4 | E2: =COUNTIFS(Servicios!B:B,A2,Servicios!I:I,"Desarrollo mayor") -> 6 | F2: =COUNTIFS(Servicios!B:B,A2,Servicios!I:I,"No aplica") -> 2 | G2: =C2+D2 -> 10 | H2: =IF(B2=0,0,G2/B2) -> 0.55555556 | I2: =COUNTIFS(Servicios!B:B,A2,Servicios!D:D,"<>online") -> 9 | J2: =COUNTIFS(Servicios!B:B,A2,Servicios!D:D,"<>online",Servicios!I:I,"Hoy")+COUNTIFS(Servicios!B:B,A2,Servicios!D:D,"<>online",Servicios!I:I,"Corto plazo") -> 6 | K2: =IF(I2=0,0,J2/I2) -> 0.66666667
A3: CAMIONEROS | B3: =COUNTIF(Servicios!B:B,A3) -> 22 | C3: =COUNTIFS(Servicios!B:B,A3,Servicios!I:I,"Hoy") -> 8 | D3: =COUNTIFS(Servicios!B:B,A3,Servicios!I:I,"Corto plazo") -> 9 | E3: =COUNTIFS(Servicios!B:B,A3,Servicios!I:I,"Desarrollo mayor") -> 4 | F3: =COUNTIFS(Servicios!B:B,A3,Servicios!I:I,"No aplica") -> 1 | G3: =C3+D3 -> 17 | H3: =IF(B3=0,0,G3/B3) -> 0.77272727 | I3: =COUNTIFS(Servicios!B:B,A3,Servicios!D:D,"<>online") -> 15 | J3: =COUNTIFS(Servicios!B:B,A3,Servicios!D:D,"<>online",Servicios!I:I,"Hoy")+COUNTIFS(Servicios!B:B,A3,Servicios!D:D,"<>online",Servicios!I:I,"Corto plazo") -> 11 | K3: =IF(I3=0,0,J3/I3) -> 0.73333333
A4: SETIA | B4: =COUNTIF(Servicios!B:B,A4) -> 16 | C4: =COUNTIFS(Servicios!B:B,A4,Servicios!I:I,"Hoy") -> 6 | D4: =COUNTIFS(Servicios!B:B,A4,Servicios!I:I,"Corto plazo") -> 7 | E4: =COUNTIFS(Servicios!B:B,A4,Servicios!I:I,"Desarrollo mayor") -> 3 | F4: =COUNTIFS(Servicios!B:B,A4,Servicios!I:I,"No aplica") -> 0 | G4: =C4+D4 -> 13 | H4: =IF(B4=0,0,G4/B4) -> 0.8125 | I4: =COUNTIFS(Servicios!B:B,A4,Servicios!D:D,"<>online") -> 8 | J4: =COUNTIFS(Servicios!B:B,A4,Servicios!D:D,"<>online",Servicios!I:I,"Hoy")+COUNTIFS(Servicios!B:B,A4,Servicios!D:D,"<>online",Servicios!I:I,"Corto plazo") -> 7 | K4: =IF(I4=0,0,J4/I4) -> 0.875
A5: SGBATOS | B5: =COUNTIF(Servicios!B:B,A5) -> 23 | C5: =COUNTIFS(Servicios!B:B,A5,Servicios!I:I,"Hoy") -> 9 | D5: =COUNTIFS(Servicios!B:B,A5,Servicios!I:I,"Corto plazo") -> 10 | E5: =COUNTIFS(Servicios!B:B,A5,Servicios!I:I,"Desarrollo mayor") -> 3 | F5: =COUNTIFS(Servicios!B:B,A5,Servicios!I:I,"No aplica") -> 1 | G5: =C5+D5 -> 19 | H5: =IF(B5=0,0,G5/B5) -> 0.82608696 | I5: =COUNTIFS(Servicios!B:B,A5,Servicios!D:D,"<>online") -> 18 | J5: =COUNTIFS(Servicios!B:B,A5,Servicios!D:D,"<>online",Servicios!I:I,"Hoy")+COUNTIFS(Servicios!B:B,A5,Servicios!D:D,"<>online",Servicios!I:I,"Corto plazo") -> 14 | K5: =IF(I5=0,0,J5/I5) -> 0.77777778
A6: STPCHPYA | B6: =COUNTIF(Servicios!B:B,A6) -> 30 | C6: =COUNTIFS(Servicios!B:B,A6,Servicios!I:I,"Hoy") -> 11 | D6: =COUNTIFS(Servicios!B:B,A6,Servicios!I:I,"Corto plazo") -> 7 | E6: =COUNTIFS(Servicios!B:B,A6,Servicios!I:I,"Desarrollo mayor") -> 11 | F6: =COUNTIFS(Servicios!B:B,A6,Servicios!I:I,"No aplica") -> 1 | G6: =C6+D6 -> 18 | H6: =IF(B6=0,0,G6/B6) -> 0.6 | I6: =COUNTIFS(Servicios!B:B,A6,Servicios!D:D,"<>online") -> 26 | J6: =COUNTIFS(Servicios!B:B,A6,Servicios!D:D,"<>online",Servicios!I:I,"Hoy")+COUNTIFS(Servicios!B:B,A6,Servicios!D:D,"<>online",Servicios!I:I,"Corto plazo") -> 15 | K6: =IF(I6=0,0,J6/I6) -> 0.57692308
A7: SUPARA | B7: =COUNTIF(Servicios!B:B,A7) -> 25 | C7: =COUNTIFS(Servicios!B:B,A7,Servicios!I:I,"Hoy") -> 9 | D7: =COUNTIFS(Servicios!B:B,A7,Servicios!I:I,"Corto plazo") -> 10 | E7: =COUNTIFS(Servicios!B:B,A7,Servicios!I:I,"Desarrollo mayor") -> 5 | F7: =COUNTIFS(Servicios!B:B,A7,Servicios!I:I,"No aplica") -> 1 | G7: =C7+D7 -> 19 | H7: =IF(B7=0,0,G7/B7) -> 0.76 | I7: =COUNTIFS(Servicios!B:B,A7,Servicios!D:D,"<>online") -> 18 | J7: =COUNTIFS(Servicios!B:B,A7,Servicios!D:D,"<>online",Servicios!I:I,"Hoy")+COUNTIFS(Servicios!B:B,A7,Servicios!D:D,"<>online",Servicios!I:I,"Corto plazo") -> 15 | K7: =IF(I7=0,0,J7/I7) -> 0.83333333
A8: SUTEBA | B8: =COUNTIF(Servicios!B:B,A8) -> 18 | C8: =COUNTIFS(Servicios!B:B,A8,Servicios!I:I,"Hoy") -> 8 | D8: =COUNTIFS(Servicios!B:B,A8,Servicios!I:I,"Corto plazo") -> 6 | E8: =COUNTIFS(Servicios!B:B,A8,Servicios!I:I,"Desarrollo mayor") -> 2 | F8: =COUNTIFS(Servicios!B:B,A8,Servicios!I:I,"No aplica") -> 2 | G8: =C8+D8 -> 14 | H8: =IF(B8=0,0,G8/B8) -> 0.77777778 | I8: =COUNTIFS(Servicios!B:B,A8,Servicios!D:D,"<>online") -> 11 | J8: =COUNTIFS(Servicios!B:B,A8,Servicios!D:D,"<>online",Servicios!I:I,"Hoy")+COUNTIFS(Servicios!B:B,A8,Servicios!D:D,"<>online",Servicios!I:I,"Corto plazo") -> 8 | K8: =IF(I8=0,0,J8/I8) -> 0.72727273
A9: SUTERH | B9: =COUNTIF(Servicios!B:B,A9) -> 14 | C9: =COUNTIFS(Servicios!B:B,A9,Servicios!I:I,"Hoy") -> 6 | D9: =COUNTIFS(Servicios!B:B,A9,Servicios!I:I,"Corto plazo") -> 4 | E9: =COUNTIFS(Servicios!B:B,A9,Servicios!I:I,"Desarrollo mayor") -> 4 | F9: =COUNTIFS(Servicios!B:B,A9,Servicios!I:I,"No aplica") -> 0 | G9: =C9+D9 -> 10 | H9: =IF(B9=0,0,G9/B9) -> 0.71428571 | I9: =COUNTIFS(Servicios!B:B,A9,Servicios!D:D,"<>online") -> 8 | J9: =COUNTIFS(Servicios!B:B,A9,Servicios!D:D,"<>online",Servicios!I:I,"Hoy")+COUNTIFS(Servicios!B:B,A9,Servicios!D:D,"<>online",Servicios!I:I,"Corto plazo") -> 6 | K9: =IF(I9=0,0,J9/I9) -> 0.75
A10: UEJN | B10: =COUNTIF(Servicios!B:B,A10) -> 9 | C10: =COUNTIFS(Servicios!B:B,A10,Servicios!I:I,"Hoy") -> 7 | D10: =COUNTIFS(Servicios!B:B,A10,Servicios!I:I,"Corto plazo") -> 1 | E10: =COUNTIFS(Servicios!B:B,A10,Servicios!I:I,"Desarrollo mayor") -> 1 | F10: =COUNTIFS(Servicios!B:B,A10,Servicios!I:I,"No aplica") -> 0 | G10: =C10+D10 -> 8 | H10: =IF(B10=0,0,G10/B10) -> 0.88888889 | I10: =COUNTIFS(Servicios!B:B,A10,Servicios!D:D,"<>online") -> 1 | J10: =COUNTIFS(Servicios!B:B,A10,Servicios!D:D,"<>online",Servicios!I:I,"Hoy")+COUNTIFS(Servicios!B:B,A10,Servicios!D:D,"<>online",Servicios!I:I,"Corto plazo") -> 1 | K10: =IF(I10=0,0,J10/I10) -> 1
A11: UTEDYC | B11: =COUNTIF(Servicios!B:B,A11) -> 14 | C11: =COUNTIFS(Servicios!B:B,A11,Servicios!I:I,"Hoy") -> 6 | D11: =COUNTIFS(Servicios!B:B,A11,Servicios!I:I,"Corto plazo") -> 4 | E11: =COUNTIFS(Servicios!B:B,A11,Servicios!I:I,"Desarrollo mayor") -> 4 | F11: =COUNTIFS(Servicios!B:B,A11,Servicios!I:I,"No aplica") -> 0 | G11: =C11+D11 -> 10 | H11: =IF(B11=0,0,G11/B11) -> 0.71428571 | I11: =COUNTIFS(Servicios!B:B,A11,Servicios!D:D,"<>online") -> 3 | J11: =COUNTIFS(Servicios!B:B,A11,Servicios!D:D,"<>online",Servicios!I:I,"Hoy")+COUNTIFS(Servicios!B:B,A11,Servicios!D:D,"<>online",Servicios!I:I,"Corto plazo") -> 1 | K11: =IF(I11=0,0,J11/I11) -> 0.33333333
A12: ACEITEROS | B12: =COUNTIF(Servicios!B:B,A12) -> 21 | C12: =COUNTIFS(Servicios!B:B,A12,Servicios!I:I,"Hoy") -> 6 | D12: =COUNTIFS(Servicios!B:B,A12,Servicios!I:I,"Corto plazo") -> 8 | E12: =COUNTIFS(Servicios!B:B,A12,Servicios!I:I,"Desarrollo mayor") -> 4 | F12: =COUNTIFS(Servicios!B:B,A12,Servicios!I:I,"No aplica") -> 3 | G12: =C12+D12 -> 14 | H12: =IF(B12=0,0,G12/B12) -> 0.66666667 | I12: =COUNTIFS(Servicios!B:B,A12,Servicios!D:D,"<>online") -> 16 | J12: =COUNTIFS(Servicios!B:B,A12,Servicios!D:D,"<>online",Servicios!I:I,"Hoy")+COUNTIFS(Servicios!B:B,A12,Servicios!D:D,"<>online",Servicios!I:I,"Corto plazo") -> 11 | K12: =IF(I12=0,0,J12/I12) -> 0.6875
A13: AEFIP | B13: =COUNTIF(Servicios!B:B,A13) -> 25 | C13: =COUNTIFS(Servicios!B:B,A13,Servicios!I:I,"Hoy") -> 10 | D13: =COUNTIFS(Servicios!B:B,A13,Servicios!I:I,"Corto plazo") -> 13 | E13: =COUNTIFS(Servicios!B:B,A13,Servicios!I:I,"Desarrollo mayor") -> 2 | F13: =COUNTIFS(Servicios!B:B,A13,Servicios!I:I,"No aplica") -> 0 | G13: =C13+D13 -> 23 | H13: =IF(B13=0,0,G13/B13) -> 0.92 | I13: =COUNTIFS(Servicios!B:B,A13,Servicios!D:D,"<>online") -> 20 | J13: =COUNTIFS(Servicios!B:B,A13,Servicios!D:D,"<>online",Servicios!I:I,"Hoy")+COUNTIFS(Servicios!B:B,A13,Servicios!D:D,"<>online",Servicios!I:I,"Corto plazo") -> 20 | K13: =IF(I13=0,0,J13/I13) -> 1
... A48: UTA | B48: =COUNTIF(Servicios!B:B,A48) -> 13 | C48: =COUNTIFS(Servicios!B:B,A48,Servicios!I:I,"Hoy") -> 7 | D48: =COUNTIFS(Servicios!B:B,A48,Servicios!I:I,"Corto plazo") -> 4 | E48: =COUNTIFS(Servicios!B:B,A48,Servicios!I:I,"Desarrollo mayor") -> 2 | F48: =COUNTIFS(Servicios!B:B,A48,Servicios!I:I,"No aplica") -> 0 | G48: =C48+D48 -> 11 | H48: =IF(B48=0,0,G48/B48) -> 0.84615385 | I48: =COUNTIFS(Servicios!B:B,A48,Servicios!D:D,"<>online") -> 10 | J48: =COUNTIFS(Servicios!B:B,A48,Servicios!D:D,"<>online",Servicios!I:I,"Hoy")+COUNTIFS(Servicios!B:B,A48,Servicios!D:D,"<>online",Servicios!I:I,"Corto plazo") -> 9 | K48: =IF(I48=0,0,J48/I48) -> 0.9
A49: TOTAL | B49: =SUM(B2:B48) -> 715 | C49: =SUM(C2:C48) -> 292 | D49: =SUM(D2:D48) -> 242 | E49: =SUM(E2:E48) -> 137 | F49: =SUM(F2:F48) -> 44 | G49: =SUM(G2:G48) -> 534 | H49: =G49/B49 -> 0.74685315 | I49: =SUM(I2:I48) -> 510 | J49: =SUM(J2:J48) -> 396 | K49: =J49/I49 -> 0.77647059
A51: Niveles: Hoy = la versión actual de Colm3na resuelve el servicio o su parte digitalizable (incluye reservas con formularios encadenados y confirmación semiautomática); Corto plazo = con propuestas de ola 1; Desarrollo mayor = olas 2 y 3; No aplica = infraestructura física, salud, medios, vivienda. Vacancia digital = servicio semi-online o presencial. Clasificación por reglas + revisión manual (ver hoja Servicios).

Sheet Matriz
A1: Sindicato | B1: Calidad | C1: P01 | D1: P02 | E1: P03 | F1: P04 | G1: P05 | H1: P06 | I1: P07 | J1: P08 | K1: P09 | L1: P10 | M1: P11 | N1: P12 | O1: P13 | P1: P14 | Q1: P15 | R1: P16 | S1: P17 | T1: P18 | U1: P19 | V1: P20 | W1: P21 | X1: P22 | Y1: P23 | Z1: P24 | AA1: P25 | AB1: P26 | AC1: P27 | AD1: P28 | AE1: P29 | AF1: P30 | AG1: P31 | AH1: P32 | AI1: P33 | AJ1: P34 | AK1: Total
A2: ADEF | B2: =INDEX(Sindicatos!F:F,MATCH(A2,Sindicatos!A:A,0)) -> 4 | C2: =IF(ISNUMBER(SEARCH(","&$A2&",",","&SUBSTITUTE(INDEX(Propuestas!$E$2:$E$35,1),", ",",")&",")),"●","") | D2: =IF(ISNUMBER(SEARCH(","&$A2&",",","&SUBSTITUTE(INDEX(Propuestas!$E$2:$E$35,2),", ",",")&",")),"●","") | E2: =IF(ISNUMBER(SEARCH(","&$A2&",",","&SUBSTITUTE(INDEX(Propuestas!$E$2:$E$35,3),", ",",")&",")),"●","") | F2: =IF(ISNUMBER(SEARCH(","&$A2&",",","&SUBSTITUTE(INDEX(Propuestas!$E$2:$E$35,4),", ",",")&",")),"●","") | G2: =IF(ISNUMBER(SEARCH(","&$A2&",",","&SUBSTITUTE(INDEX(Propuestas!$E$2:$E$35,5),", ",",")&",")),"●","") | H2: =IF(ISNUMBER(SEARCH(","&$A2&",",","&SUBSTITUTE(INDEX(Propuestas!$E$2:$E$35,6),", ",",")&",")),"●","") | I2: =IF(ISNUMBER(SEARCH(","&$A2&",",","&SUBSTITUTE(INDEX(Propuestas!$E$2:$E$35,7),", ",",")&",")),"●","") | J2: =IF(ISNUMBER(SEARCH(","&$A2&",",","&SUBSTITUTE(INDEX(Propuestas!$E$2:$E$35,8),", ",",")&",")),"●","") | K2: =IF(ISNUMBER(SEARCH(","&$A2&",",","&SUBSTITUTE(INDEX(Propuestas!$E$2:$E$35,9),", ",",")&",")),"●","") -> ● | L2: =IF(ISNUMBER(SEARCH(","&$A2&",",","&SUBSTITUTE(INDEX(Propuestas!$E$2:$E$35,10),", ",",")&",")),"●","") | M2: =IF(ISNUMBER(SEARCH(","&$A2&",",","&SUBSTITUTE(INDEX(Propuestas!$E$2:$E$35,11),", ",",")&",")),"●","") -> ● | N2: =IF(ISNUMBER(SEARCH(","&$A2&",",","&SUBSTITUTE(INDEX(Propuestas!$E$2:$E$35,12),", ",",")&",")),"●","") | O2: =IF(ISNUMBER(SEARCH(","&$A2&",",","&SUBSTITUTE(INDEX(Propuestas!$E$2:$E$35,13),", ",",")&",")),"●","") | P2: =IF(ISNUMBER(SEARCH(","&$A2&",",","&SUBSTITUTE(INDEX(Propuestas!$E$2:$E$35,14),", ",",")&",")),"●","") -> ● | Q2: =IF(ISNUMBER(SEARCH(","&$A2&",",","&SUBSTITUTE(INDEX(Propuestas!$E$2:$E$35,15),", ",",")&",")),"●","") -> ● | R2: =IF(ISNUMBER(SEARCH(","&$A2&",",","&SUBSTITUTE(INDEX(Propuestas!$E$2:$E$35,16),", ",",")&",")),"●","") -> ● | S2: =IF(ISNUMBER(SEARCH(","&$A2&",",","&SUBSTITUTE(INDEX(Propuestas!$E$2:$E$35,17),", ",",")&",")),"●","") -> ● | T2: =IF(ISNUMBER(SEARCH(","&$A2&",",","&SUBSTITUTE(INDEX(Propuestas!$E$2:$E$35,18),", ",",")&",")),"●","") -> ● | U2: =IF(ISNUMBER(SEARCH(","&$A2&",",","&SUBSTITUTE(INDEX(Propuestas!$E$2:$E$35,19),", ",",")&",")),"●","") | V2: =IF(ISNUMBER(SEARCH(","&$A2&",",","&SUBSTITUTE(INDEX(Propuestas!$E$2:$E$35,20),", ",",")&",")),"●","") -> ● | W2: =IF(ISNUMBER(SEARCH(","&$A2&",",","&SUBSTITUTE(INDEX(Propuestas!$E$2:$E$35,21),", ",",")&",")),"●","") -> ● | X2: =IF(ISNUMBER(SEARCH(","&$A2&",",","&SUBSTITUTE(INDEX(Propuestas!$E$2:$E$35,22),", ",",")&",")),"●","") -> ● | Y2: =IF(ISNUMBER(SEARCH(","&$A2&",",","&SUBSTITUTE(INDEX(Propuestas!$E$2:$E$35,23),", ",",")&",")),"●","") | Z2: =IF(ISNUMBER(SEARCH(","&$A2&",",","&SUBSTITUTE(INDEX(Propuestas!$E$2:$E$35,24),", ",",")&",")),"●","") -> ● | AA2: =IF(ISNUMBER(SEARCH(","&$A2&",",","&SUBSTITUTE(INDEX(Propuestas!$E$2:$E$35,25),", ",",")&",")),"●","") | AB2: =IF(ISNUMBER(SEARCH(","&$A2&",",","&SUBSTITUTE(INDEX(Propuestas!$E$2:$E$35,26),", ",",")&",")),"●","") -> ● | AC2: =IF(ISNUMBER(SEARCH(","&$A2&",",","&SUBSTITUTE(INDEX(Propuestas!$E$2:$E$35,27),", ",",")&",")),"●","") | AD2: =IF(ISNUMBER(SEARCH(","&$A2&",",","&SUBSTITUTE(INDEX(Propuestas!$E$2:$E$35,28),", ",",")&",")),"●","") -> ● | AE2: =IF(ISNUMBER(SEARCH(","&$A2&",",","&SUBSTITUTE(INDEX(Propuestas!$E$2:$E$35,29),", ",",")&",")),"●","") | AF2: =IF(ISNUMBER(SEARCH(","&$A2&",",","&SUBSTITUTE(INDEX(Propuestas!$E$2:$E$35,30),", ",",")&",")),"●","") | AG2: =IF(ISNUMBER(SEARCH(","&$A2&",",","&SUBSTITUTE(INDEX(Propuestas!$E$2:$E$35,31),", ",",")&",")),"●","") -> ● | AH2: =IF(ISNUMBER(SEARCH(","&$A2&",",","&SUBSTITUTE(INDEX(Propuestas!$E$2:$E$35,32),", ",",")&",")),"●","") | AI2: =IF(ISNUMBER(SEARCH(","&$A2&",",","&SUBSTITUTE(INDEX(Propuestas!$E$2:$E$35,33),", ",",")&",")),"●","") | AJ2: =IF(ISNUMBER(SEARCH(","&$A2&",",","&SUBSTITUTE(INDEX(Propuestas!$E$2:$E$35,34),", ",",")&",")),"●","") -> ● | AK2: =COUNTIF(C2:AJ2,"●") -> 15
A3: CAMIONEROS | B3: =INDEX(Sindicatos!F:F,MATCH(A3,Sindicatos!A:A,0)) -> 4 | C3: =IF(ISNUMBER(SEARCH(","&$A3&",",","&SUBSTITUTE(INDEX(Propuestas!$E$2:$E$35,1),", ",",")&",")),"●","") -> ● | D3: =IF(ISNUMBER(SEARCH(","&$A3&",",","&SUBSTITUTE(INDEX(Propuestas!$E$2:$E$35,2),", ",",")&",")),"●","") | E3: =IF(ISNUMBER(SEARCH(","&$A3&",",","&SUBSTITUTE(INDEX(Propuestas!$E$2:$E$35,3),", ",",")&",")),"●","") | F3: =IF(ISNUMBER(SEARCH(","&$A3&",",","&SUBSTITUTE(INDEX(Propuestas!$E$2:$E$35,4),", ",",")&",")),"●","") -> ● | G3: =IF(ISNUMBER(SEARCH(","&$A3&",",","&SUBSTITUTE(INDEX(Propuestas!$E$2:$E$35,5),", ",",")&",")),"●","") | H3: =IF(ISNUMBER(SEARCH(","&$A3&",",","&SUBSTITUTE(INDEX(Propuestas!$E$2:$E$35,6),", ",",")&",")),"●","") | I3: =IF(ISNUMBER(SEARCH(","&$A3&",",","&SUBSTITUTE(INDEX(Propuestas!$E$2:$E$35,7),", ",",")&",")),"●","") | J3: =IF(ISNUMBER(SEARCH(","&$A3&",",","&SUBSTITUTE(INDEX(Propuestas!$E$2:$E$35,8),", ",",")&",")),"●","") | K3: =IF(ISNUMBER(SEARCH(","&$A3&",",","&SUBSTITUTE(INDEX(Propuestas!$E$2:$E$35,9),", ",",")&",")),"●","") | L3: =IF(ISNUMBER(SEARCH(","&$A3&",",","&SUBSTITUTE(INDEX(Propuestas!$E$2:$E$35,10),", ",",")&",")),"●","") -> ● | M3: =IF(ISNUMBER(SEARCH(","&$A3&",",","&SUBSTITUTE(INDEX(Propuestas!$E$2:$E$35,11),", ",",")&",")),"●","") | N3: =IF(ISNUMBER(SEARCH(","&$A3&",",","&SUBSTITUTE(INDEX(Propuestas!$E$2:$E$35,12),", ",",")&",")),"●","") -> ● | O3: =IF(ISNUMBER(SEARCH(","&$A3&",",","&SUBSTITUTE(INDEX(Propuestas!$E$2:$E$35,13),", ",",")&",")),"●","") -> ● | P3: =IF(ISNUMBER(SEARCH(","&$A3&",",","&SUBSTITUTE(INDEX(Propuestas!$E$2:$E$35,14),", ",",")&",")),"●","") -> ● | Q3: =IF(ISNUMBER(SEARCH(","&$A3&",",","&SUBSTITUTE(INDEX(Propuestas!$E$2:$E$35,15),", ",",")&",")),"●","") -> ● | R3: =IF(ISNUMBER(SEARCH(","&$A3&",",","&SUBSTITUTE(INDEX(Propuestas!$E$2:$E$35,16),", ",",")&",")),"●","") | S3: =IF(ISNUMBER(SEARCH(","&$A3&",",","&SUBSTITUTE(INDEX(Propuestas!$E$2:$E$35,17),", ",",")&",")),"●","") | T3: =IF(ISNUMBER(SEARCH(","&$A3&",",","&SUBSTITUTE(INDEX(Propuestas!$E$2:$E$35,18),", ",",")&",")),"●","") | U3: =IF(ISNUMBER(SEARCH(","&$A3&",",","&SUBSTITUTE(INDEX(Propuestas!$E$2:$E$35,19),", ",",")&",")),"●","") | V3: =IF(ISNUMBER(SEARCH(","&$A3&",",","&SUBSTITUTE(INDEX(Propuestas!$E$2:$E$35,20),", ",",")&",")),"●","") -> ● | W3: =IF(ISNUMBER(SEARCH(","&$A3&",",","&SUBSTITUTE(INDEX(Propuestas!$E$2:$E$35,21),", ",",")&",")),"●","") | X3: =IF(ISNUMBER(SEARCH(","&$A3&",",","&SUBSTITUTE(INDEX(Propuestas!$E$2:$E$35,22),", ",",")&",")),"●","") | Y3: =IF(ISNUMBER(SEARCH(","&$A3&",",","&SUBSTITUTE(INDEX(Propuestas!$E$2:$E$35,23),", ",",")&",")),"●","") -> ● | Z3: =IF(ISNUMBER(SEARCH(","&$A3&",",","&SUBSTITUTE(INDEX(Propuestas!$E$2:$E$35,24),", ",",")&",")),"●","") | AA3: =IF(ISNUMBER(SEARCH(","&$A3&",",","&SUBSTITUTE(INDEX(Propuestas!$E$2:$E$35,25),", ",",")&",")),"●","") | AB3: =IF(ISNUMBER(SEARCH(","&$A3&",",","&SUBSTITUTE(INDEX(Propuestas!$E$2:$E$35,26),", ",",")&",")),"●","") | AC3: =IF(ISNUMBER(SEARCH(","&$A3&",",","&SUBSTITUTE(INDEX(Propuestas!$E$2:$E$35,27),", ",",")&",")),"●","") | AD3: =IF(ISNUMBER(SEARCH(","&$A3&",",","&SUBSTITUTE(INDEX(Propuestas!$E$2:$E$35,28),", ",",")&",")),"●","") | AE3: =IF(ISNUMBER(SEARCH(","&$A3&",",","&SUBSTITUTE(INDEX(Propuestas!$E$2:$E$35,29),", ",",")&",")),"●","") | AF3: =IF(ISNUMBER(SEARCH(","&$A3&",",","&SUBSTITUTE(INDEX(Propuestas!$E$2:$E$35,30),", ",",")&",")),"●","") -> ● | AG3: =IF(ISNUMBER(SEARCH(","&$A3&",",","&SUBSTITUTE(INDEX(Propuestas!$E$2:$E$35,31),", ",",")&",")),"●","") | AH3: =IF(ISNUMBER(SEARCH(","&$A3&",",","&SUBSTITUTE(INDEX(Propuestas!$E$2:$E$35,32),", ",",")&",")),"●","") | AI3: =IF(ISNUMBER(SEARCH(","&$A3&",",","&SUBSTITUTE(INDEX(Propuestas!$E$2:$E$35,33),", ",",")&",")),"●","") | AJ3: =IF(ISNUMBER(SEARCH(","&$A3&",",","&SUBSTITUTE(INDEX(Propuestas!$E$2:$E$35,34),", ",",")&",")),"●","") | AK3: =COUNTIF(C3:AJ3,"●") -> 10
A4: SETIA | B4: =INDEX(Sindicatos!F:F,MATCH(A4,Sindicatos!A:A,0)) -> 4 | C4: =IF(ISNUMBER(SEARCH(","&$A4&",",","&SUBSTITUTE(INDEX(Propuestas!$E$2:$E$35,1),", ",",")&",")),"●","") -> ● | D4: =IF(ISNUMBER(SEARCH(","&$A4&",",","&SUBSTITUTE(INDEX(Propuestas!$E$2:$E$35,2),", ",",")&",")),"●","") -> ● | E4: =IF(ISNUMBER(SEARCH(","&$A4&",",","&SUBSTITUTE(INDEX(Propuestas!$E$2:$E$35,3),", ",",")&",")),"●","") | F4: =IF(ISNUMBER(SEARCH(","&$A4&",",","&SUBSTITUTE(INDEX(Propuestas!$E$2:$E$35,4),", ",",")&",")),"●","") -> ● | G4: =IF(ISNUMBER(SEARCH(","&$A4&",",","&SUBSTITUTE(INDEX(Propuestas!$E$2:$E$35,5),", ",",")&",")),"●","") | H4: =IF(ISNUMBER(SEARCH(","&$A4&",",","&SUBSTITUTE(INDEX(Propuestas!$E$2:$E$35,6),", ",",")&",")),"●","") | I4: =IF(ISNUMBER(SEARCH(","&$A4&",",","&SUBSTITUTE(INDEX(Propuestas!$E$2:$E$35,7),", ",",")&",")),"●","") | J4: =IF(ISNUMBER(SEARCH(","&$A4&",",","&SUBSTITUTE(INDEX(Propuestas!$E$2:$E$35,8),", ",",")&",")),"●","") | K4: =IF(ISNUMBER(SEARCH(","&$A4&",",","&SUBSTITUTE(INDEX(Propuestas!$E$2:$E$35,9),", ",",")&",")),"●","") | L4: =IF(ISNUMBER(SEARCH(","&$A4&",",","&SUBSTITUTE(INDEX(Propuestas!$E$2:$E$35,10),", ",",")&",")),"●","") -> ● | M4: =IF(ISNUMBER(SEARCH(","&$A4&",",","&SUBSTITUTE(INDEX(Propuestas!$E$2:$E$35,11),", ",",")&",")),"●","") | N4: =IF(ISNUMBER(SEARCH(","&$A4&",",","&SUBSTITUTE(INDEX(Propuestas!$E$2:$E$35,12),", ",",")&",")),"●","") | O4: =IF(ISNUMBER(SEARCH(","&$A4&",",","&SUBSTITUTE(INDEX(Propuestas!$E$2:$E$35,13),", ",",")&",")),"●","") | P4: =IF(ISNUMBER(SEARCH(","&$A4&",",","&SUBSTITUTE(INDEX(Propuestas!$E$2:$E$35,14),", ",",")&",")),"●","") | Q4: =IF(ISNUMBER(SEARCH(","&$A4&",",","&SUBSTITUTE(INDEX(Propuestas!$E$2:$E$35,15),", ",",")&",")),"●","") -> ● | R4: =IF(ISNUMBER(SEARCH(","&$A4&",",","&SUBSTITUTE(INDEX(Propuestas!$E$2:$E$35,16),", ",",")&",")),"●","") | S4: =IF(ISNUMBER(SEARCH(","&$A4&",",","&SUBSTITUTE(INDEX(Propuestas!$E$2:$E$35,17),", ",",")&",")),"●","") -> ● | T4: =IF(ISNUMBER(SEARCH(","&$A4&",",","&SUBSTITUTE(INDEX(Propuestas!$E$2:$E$35,18),", ",",")&",")),"●","") -> ● | U4: =IF(ISNUMBER(SEARCH(","&$A4&",",","&SUBSTITUTE(INDEX(Propuestas!$E$2:$E$35,19),", ",",")&",")),"●","") -> ● | V4: =IF(ISNUMBER(SEARCH(","&$A4&",",","&SUBSTITUTE(INDEX(Propuestas!$E$2:$E$35,20),", ",",")&",")),"●","") -> ● | W4: =IF(ISNUMBER(SEARCH(","&$A4&",",","&SUBSTITUTE(INDEX(Propuestas!$E$2:$E$35,21),", ",",")&",")),"●","") | X4: =IF(ISNUMBER(SEARCH(","&$A4&",",","&SUBSTITUTE(INDEX(Propuestas!$E$2:$E$35,22),", ",",")&",")),"●","") | Y4: =IF(ISNUMBER(SEARCH(","&$A4&",",","&SUBSTITUTE(INDEX(Propuestas!$E$2:$E$35,23),", ",",")&",")),"●","") | Z4: =IF(ISNUMBER(SEARCH(","&$A4&",",","&SUBSTITUTE(INDEX(Propuestas!$E$2:$E$35,24),", ",",")&",")),"●","") | AA4: =IF(ISNUMBER(SEARCH(","&$A4&",",","&SUBSTITUTE(INDEX(Propuestas!$E$2:$E$35,25),", ",",")&",")),"●","") | AB4: =IF(ISNUMBER(SEARCH(","&$A4&",",","&SUBSTITUTE(INDEX(Propuestas!$E$2:$E$35,26),", ",",")&",")),"●","") | AC4: =IF(ISNUMBER(SEARCH(","&$A4&",",","&SUBSTITUTE(INDEX(Propuestas!$E$2:$E$35,27),", ",",")&",")),"●","") | AD4: =IF(ISNUMBER(SEARCH(","&$A4&",",","&SUBSTITUTE(INDEX(Propuestas!$E$2:$E$35,28),", ",",")&",")),"●","") | AE4: =IF(ISNUMBER(SEARCH(","&$A4&",",","&SUBSTITUTE(INDEX(Propuestas!$E$2:$E$35,29),", ",",")&",")),"●","") | AF4: =IF(ISNUMBER(SEARCH(","&$A4&",",","&SUBSTITUTE(INDEX(Propuestas!$E$2:$E$35,30),", ",",")&",")),"●","") | AG4: =IF(ISNUMBER(SEARCH(","&$A4&",",","&SUBSTITUTE(INDEX(Propuestas!$E$2:$E$35,31),", ",",")&",")),"●","") -> ● | AH4: =IF(ISNUMBER(SEARCH(","&$A4&",",","&SUBSTITUTE(INDEX(Propuestas!$E$2:$E$35,32),", ",",")&",")),"●","") | AI4: =IF(ISNUMBER(SEARCH(","&$A4&",",","&SUBSTITUTE(INDEX(Propuestas!$E$2:$E$35,33),", ",",")&",")),"●","") | AJ4: =IF(ISNUMBER(SEARCH(","&$A4&",",","&SUBSTITUTE(INDEX(Propuestas!$E$2:$E$35,34),", ",",")&",")),"●","") | AK4: =COUNTIF(C4:AJ4,"●") -> 10
A5: SGBATOS | B5: =INDEX(Sindicatos!F:F,MATCH(A5,Sindicatos!A:A,0)) -> 4 | C5: =IF(ISNUMBER(SEARCH(","&$A5&",",","&SUBSTITUTE(INDEX(Propuestas!$E$2:$E$35,1),", ",",")&",")),"●","") -> ● | D5: =IF(ISNUMBER(SEARCH(","&$A5&",",","&SUBSTITUTE(INDEX(Propuestas!$E$2:$E$35,2),", ",",")&",")),"●","") -> ● | E5: =IF(ISNUMBER(SEARCH(","&$A5&",",","&SUBSTITUTE(INDEX(Propuestas!$E$2:$E$35,3),", ",",")&",")),"●","") | F5: =IF(ISNUMBER(SEARCH(","&$A5&",",","&SUBSTITUTE(INDEX(Propuestas!$E$2:$E$35,4),", ",",")&",")),"●","") -> ● | G5: =IF(ISNUMBER(SEARCH(","&$A5&",",","&SUBSTITUTE(INDEX(Propuestas!$E$2:$E$35,5),", ",",")&",")),"●","") -> ● | H5: =IF(ISNUMBER(SEARCH(","&$A5&",",","&SUBSTITUTE(INDEX(Propuestas!$E$2:$E$35,6),", ",",")&",")),"●","") | I5: =IF(ISNUMBER(SEARCH(","&$A5&",",","&SUBSTITUTE(INDEX(Propuestas!$E$2:$E$35,7),", ",",")&",")),"●","") -> ● | J5: =IF(ISNUMBER(SEARCH(","&$A5&",",","&SUBSTITUTE(INDEX(Propuestas!$E$2:$E$35,8),", ",",")&",")),"●","") | K5: =IF(ISNUMBER(SEARCH(","&$A5&",",","&SUBSTITUTE(INDEX(Propuestas!$E$2:$E$35,9),", ",",")&",")),"●","") | L5: =IF(ISNUMBER(SEARCH(","&$A5&",",","&SUBSTITUTE(INDEX(Propuestas!$E$2:$E$35,10),", ",",")&",")),"●","") | M5: =IF(ISNUMBER(SEARCH(","&$A5&",",","&SUBSTITUTE(INDEX(Propuestas!$E$2:$E$35,11),", ",",")&",")),"●","") -> ● | N5: =IF(ISNUMBER(SEARCH(","&$A5&",",","&SUBSTITUTE(INDEX(Propuestas!$E$2:$E$35,12),", ",",")&",")),"●","") | O5: =IF(ISNUMBER(SEARCH(","&$A5&",",","&SUBSTITUTE(INDEX(Propuestas!$E$2:$E$35,13),", ",",")&",")),"●","") -> ● | P5: =IF(ISNUMBER(SEARCH(","&$A5&",",","&SUBSTITUTE(INDEX(Propuestas!$E$2:$E$35,14),", ",",")&",")),"●","") | Q5: =IF(ISNUMBER(SEARCH(","&$A5&",",","&SUBSTITUTE(INDEX(Propuestas!$E$2:$E$35,15),", ",",")&",")),"●","") | R5: =IF(ISNUMBER(SEARCH(","&$A5&",",","&SUBSTITUTE(INDEX(Propuestas!$E$2:$E$35,16),", ",",")&",")),"●","") | S5: =IF(ISNUMBER(SEARCH(","&$A5&",",","&SUBSTITUTE(INDEX(Propuestas!$E$2:$E$35,17),", ",",")&",")),"●","") -> ● | T5: =IF(ISNUMBER(SEARCH(","&$A5&",",","&SUBSTITUTE(INDEX(Propuestas!$E$2:$E$35,18),", ",",")&",")),"●","") | U5: =IF(ISNUMBER(SEARCH(","&$A5&",",","&SUBSTITUTE(INDEX(Propuestas!$E$2:$E$35,19),", ",",")&",")),"●","") -> ● | V5: =IF(ISNUMBER(SEARCH(","&$A5&",",","&SUBSTITUTE(INDEX(Propuestas!$E$2:$E$35,20),", ",",")&",")),"●","") -> ● | W5: =IF(ISNUMBER(SEARCH(","&$A5&",",","&SUBSTITUTE(INDEX(Propuestas!$E$2:$E$35,21),", ",",")&",")),"●","") | X5: =IF(ISNUMBER(SEARCH(","&$A5&",",","&SUBSTITUTE(INDEX(Propuestas!$E$2:$E$35,22),", ",",")&",")),"●","") | Y5: =IF(ISNUMBER(SEARCH(","&$A5&",",","&SUBSTITUTE(INDEX(Propuestas!$E$2:$E$35,23),", ",",")&",")),"●","") | Z5: =IF(ISNUMBER(SEARCH(","&$A5&",",","&SUBSTITUTE(INDEX(Propuestas!$E$2:$E$35,24),", ",",")&",")),"●","") -> ● | AA5: =IF(ISNUMBER(SEARCH(","&$A5&",",","&SUBSTITUTE(INDEX(Propuestas!$E$2:$E$35,25),", ",",")&",")),"●","") | AB5: =IF(ISNUMBER(SEARCH(","&$A5&",",","&SUBSTITUTE(INDEX(Propuestas!$E$2:$E$35,26),", ",",")&",")),"●","") | AC5: =IF(ISNUMBER(SEARCH(","&$A5&",",","&SUBSTITUTE(INDEX(Propuestas!$E$2:$E$35,27),", ",",")&",")),"●","") | AD5: =IF(ISNUMBER(SEARCH(","&$A5&",",","&SUBSTITUTE(INDEX(Propuestas!$E$2:$E$35,28),", ",",")&",")),"●","") | AE5: =IF(ISNUMBER(SEARCH(","&$A5&",",","&SUBSTITUTE(INDEX(Propuestas!$E$2:$E$35,29),", ",",")&",")),"●","") -> ● | AF5: =IF(ISNUMBER(SEARCH(","&$A5&",",","&SUBSTITUTE(INDEX(Propuestas!$E$2:$E$35,30),", ",",")&",")),"●","") | AG5: =IF(ISNUMBER(SEARCH(","&$A5&",",","&SUBSTITUTE(INDEX(Propuestas!$E$2:$E$35,31),", ",",")&",")),"●","") | AH5: =IF(ISNUMBER(SEARCH(","&$A5&",",","&SUBSTITUTE(INDEX(Propuestas!$E$2:$E$35,32),", ",",")&",")),"●","") -> ● | AI5: =IF(ISNUMBER(SEARCH(","&$A5&",",","&SUBSTITUTE(INDEX(Propuestas!$E$2:$E$35,33),", ",",")&",")),"●","") | AJ5: =IF(ISNUMBER(SEARCH(","&$A5&",",","&SUBSTITUTE(INDEX(Propuestas!$E$2:$E$35,34),", ",",")&",")),"●","") -> ● | AK5: =COUNTIF(C5:AJ5,"●") -> 14
A6: STPCHPYA | B6: =INDEX(Sindicatos!F:F,MATCH(A6,Sindicatos!A:A,0)) -> 4 | C6: =IF(ISNUMBER(SEARCH(","&$A6&",",","&SUBSTITUTE(INDEX(Propuestas!$E$2:$E$35,1),", ",",")&",")),"●","") -> ● | D6: =IF(ISNUMBER(SEARCH(","&$A6&",",","&SUBSTITUTE(INDEX(Propuestas!$E$2:$E$35,2),", ",",")&",")),"●","") | E6: =IF(ISNUMBER(SEARCH(","&$A6&",",","&SUBSTITUTE(INDEX(Propuestas!$E$2:$E$35,3),", ",",")&",")),"●","") | F6: =IF(ISNUMBER(SEARCH(","&$A6&",",","&SUBSTITUTE(INDEX(Propuestas!$E$2:$E$35,4),", ",",")&",")),"●","") | G6: =IF(ISNUMBER(SEARCH(","&$A6&",",","&SUBSTITUTE(INDEX(Propuestas!$E$2:$E$35,5),", ",",")&",")),"●","") -> ● | H6: =IF(ISNUMBER(SEARCH(","&$A6&",",","&SUBSTITUTE(INDEX(Propuestas!$E$2:$E$35,6),", ",",")&",")),"●","") -> ● | I6: =IF(ISNUMBER(SEARCH(","&$A6&",",","&SUBSTITUTE(INDEX(Propuestas!$E$2:$E$35,7),", ",",")&",")),"●","") -> ● | J6: =IF(ISNUMBER(SEARCH(","&$A6&",",","&SUBSTITUTE(INDEX(Propuestas!$E$2:$E$35,8),", ",",")&",")),"●","") | K6: =IF(ISNUMBER(SEARCH(","&$A6&",",","&SUBSTITUTE(INDEX(Propuestas!$E$2:$E$35,9),", ",",")&",")),"●","") | L6: =IF(ISNUMBER(SEARCH(","&$A6&",",","&SUBSTITUTE(INDEX(Propuestas!$E$2:$E$35,10),", ",",")&",")),"●","") | M6: =IF(ISNUMBER(SEARCH(","&$A6&",",","&SUBSTITUTE(INDEX(Propuestas!$E$2:$E$35,11),", ",",")&",")),"●","") | N6: =IF(ISNUMBER(SEARCH(","&$A6&",",","&SUBSTITUTE(INDEX(Propuestas!$E$2:$E$35,12),", ",",")&",")),"●","") | O6: =IF(ISNUMBER(SEARCH(","&$A6&",",","&SUBSTITUTE(INDEX(Propuestas!$E$2:$E$35,13),", ",",")&",")),"●","") | P6: =IF(ISNUMBER(SEARCH(","&$A6&",",","&SUBSTITUTE(INDEX(Propuestas!$E$2:$E$35,14),", ",",")&",")),"●","") | Q6: =IF(ISNUMBER(SEARCH(","&$A6&",",","&SUBSTITUTE(INDEX(Propuestas!$E$2:$E$35,15),", ",",")&",")),"●","") | R6: =IF(ISNUMBER(SEARCH(","&$A6&",",","&SUBSTITUTE(INDEX(Propuestas!$E$2:$E$35,16),", ",",")&",")),"●","") | S6: =IF(ISNUMBER(SEARCH(","&$A6&",",","&SUBSTITUTE(INDEX(Propuestas!$E$2:$E$35,17),", ",",")&",")),"●","") -> ● | T6: =IF(ISNUMBER(SEARCH(","&$A6&",",","&SUBSTITUTE(INDEX(Propuestas!$E$2:$E$35,18),", ",",")&",")),"●","") -> ● | U6: =IF(ISNUMBER(SEARCH(","&$A6&",",","&SUBSTITUTE(INDEX(Propuestas!$E$2:$E$35,19),", ",",")&",")),"●","") -> ● | V6: =IF(ISNUMBER(SEARCH(","&$A6&",",","&SUBSTITUTE(INDEX(Propuestas!$E$2:$E$35,20),", ",",")&",")),"●","") -> ● | W6: =IF(ISNUMBER(SEARCH(","&$A6&",",","&SUBSTITUTE(INDEX(Propuestas!$E$2:$E$35,21),", ",",")&",")),"●","") | X6: =IF(ISNUMBER(SEARCH(","&$A6&",",","&SUBSTITUTE(INDEX(Propuestas!$E$2:$E$35,22),", ",",")&",")),"●","") -> ● | Y6: =IF(ISNUMBER(SEARCH(","&$A6&",",","&SUBSTITUTE(INDEX(Propuestas!$E$2:$E$35,23),", ",",")&",")),"●","") | Z6: =IF(ISNUMBER(SEARCH(","&$A6&",",","&SUBSTITUTE(INDEX(Propuestas!$E$2:$E$35,24),", ",",")&",")),"●","") -> ● | AA6: =IF(ISNUMBER(SEARCH(","&$A6&",",","&SUBSTITUTE(INDEX(Propuestas!$E$2:$E$35,25),", ",",")&",")),"●","") | AB6: =IF(ISNUMBER(SEARCH(","&$A6&",",","&SUBSTITUTE(INDEX(Propuestas!$E$2:$E$35,26),", ",",")&",")),"●","") | AC6: =IF(ISNUMBER(SEARCH(","&$A6&",",","&SUBSTITUTE(INDEX(Propuestas!$E$2:$E$35,27),", ",",")&",")),"●","") -> ● | AD6: =IF(ISNUMBER(SEARCH(","&$A6&",",","&SUBSTITUTE(INDEX(Propuestas!$E$2:$E$35,28),", ",",")&",")),"●","") | AE6: =IF(ISNUMBER(SEARCH(","&$A6&",",","&SUBSTITUTE(INDEX(Propuestas!$E$2:$E$35,29),", ",",")&",")),"●","") | AF6: =IF(ISNUMBER(SEARCH(","&$A6&",",","&SUBSTITUTE(INDEX(Propuestas!$E$2:$E$35,30),", ",",")&",")),"●","") | AG6: =IF(ISNUMBER(SEARCH(","&$A6&",",","&SUBSTITUTE(INDEX(Propuestas!$E$2:$E$35,31),", ",",")&",")),"●","") | AH6: =IF(ISNUMBER(SEARCH(","&$A6&",",","&SUBSTITUTE(INDEX(Propuestas!$E$2:$E$35,32),", ",",")&",")),"●","") | AI6: =IF(ISNUMBER(SEARCH(","&$A6&",",","&SUBSTITUTE(INDEX(Propuestas!$E$2:$E$35,33),", ",",")&",")),"●","") | AJ6: =IF(ISNUMBER(SEARCH(","&$A6&",",","&SUBSTITUTE(INDEX(Propuestas!$E$2:$E$35,34),", ",",")&",")),"●","") -> ● | AK6: =COUNTIF(C6:AJ6,"●") -> 12
A7: SUPARA | B7: =INDEX(Sindicatos!F:F,MATCH(A7,Sindicatos!A:A,0)) -> 4 | C7: =IF(ISNUMBER(SEARCH(","&$A7&",",","&SUBSTITUTE(INDEX(Propuestas!$E$2:$E$35,1),", ",",")&",")),"●","") -> ● | D7: =IF(ISNUMBER(SEARCH(","&$A7&",",","&SUBSTITUTE(INDEX(Propuestas!$E$2:$E$35,2),", ",",")&",")),"●","") -> ● | E7: =IF(ISNUMBER(SEARCH(","&$A7&",",","&SUBSTITUTE(INDEX(Propuestas!$E$2:$E$35,3),", ",",")&",")),"●","") -> ● | F7: =IF(ISNUMBER(SEARCH(","&$A7&",",","&SUBSTITUTE(INDEX(Propuestas!$E$2:$E$35,4),", ",",")&",")),"●","") -> ● | G7: =IF(ISNUMBER(SEARCH(","&$A7&",",","&SUBSTITUTE(INDEX(Propuestas!$E$2:$E$35,5),", ",",")&",")),"●","") | H7: =IF(ISNUMBER(SEARCH(","&$A7&",",","&SUBSTITUTE(INDEX(Propuestas!$E$2:$E$35,6),", ",",")&",")),"●","") -> ● | I7: =IF(ISNUMBER(SEARCH(","&$A7&",",","&SUBSTITUTE(INDEX(Propuestas!$E$2:$E$35,7),", ",",")&",")),"●","") | J7: =IF(ISNUMBER(SEARCH(","&$A7&",",","&SUBSTITUTE(INDEX(Propuestas!$E$2:$E$35,8),", ",",")&",")),"●","") -> ● | K7: =IF(ISNUMBER(SEARCH(","&$A7&",",","&SUBSTITUTE(INDEX(Propuestas!$E$2:$E$35,9),", ",",")&",")),"●","") -> ● | L7: =IF(ISNUMBER(SEARCH(","&$A7&",",","&SUBSTITUTE(INDEX(Propuestas!$E$2:$E$35,10),", ",",")&",")),"●","") | M7: =IF(ISNUMBER(SEARCH(","&$A7&",",","&SUBSTITUTE(INDEX(Propuestas!$E$2:$E$35,11),", ",",")&",")),"●","") -> ● | N7: =IF(ISNUMBER(SEARCH(","&$A7&",",","&SUBSTITUTE(INDEX(Propuestas!$E$2:$E$35,12),", ",",")&",")),"●","") | O7: =IF(ISNUMBER(SEARCH(","&$A7&",",","&SUBSTITUTE(INDEX(Propuestas!$E$2:$E$35,13),", ",",")&",")),"●","") -> ● | P7: =IF(ISNUMBER(SEARCH(","&$A7&",",","&SUBSTITUTE(INDEX(Propuestas!$E$2:$E$35,14),", ",",")&",")),"●","") | Q7: =IF(ISNUMBER(SEARCH(","&$A7&",",","&SUBSTITUTE(INDEX(Propuestas!$E$2:$E$35,15),", ",",")&",")),"●","") | R7: =IF(ISNUMBER(SEARCH(","&$A7&",",","&SUBSTITUTE(INDEX(Propuestas!$E$2:$E$35,16),", ",",")&",")),"●","") -> ● | S7: =IF(ISNUMBER(SEARCH(","&$A7&",",","&SUBSTITUTE(INDEX(Propuestas!$E$2:$E$35,17),", ",",")&",")),"●","") | T7: =IF(ISNUMBER(SEARCH(","&$A7&",",","&SUBSTITUTE(INDEX(Propuestas!$E$2:$E$35,18),", ",",")&",")),"●","") | U7: =IF(ISNUMBER(SEARCH(","&$A7&",",","&SUBSTITUTE(INDEX(Propuestas!$E$2:$E$35,19),", ",",")&",")),"●","") | V7: =IF(ISNUMBER(SEARCH(","&$A7&",",","&SUBSTITUTE(INDEX(Propuestas!$E$2:$E$35,20),", ",",")&",")),"●","") -> ● | W7: =IF(ISNUMBER(SEARCH(","&$A7&",",","&SUBSTITUTE(INDEX(Propuestas!$E$2:$E$35,21),", ",",")&",")),"●","") | X7: =IF(ISNUMBER(SEARCH(","&$A7&",",","&SUBSTITUTE(INDEX(Propuestas!$E$2:$E$35,22),", ",",")&",")),"●","") | Y7: =IF(ISNUMBER(SEARCH(","&$A7&",",","&SUBSTITUTE(INDEX(Propuestas!$E$2:$E$35,23),", ",",")&",")),"●","") | Z7: =IF(ISNUMBER(SEARCH(","&$A7&",",","&SUBSTITUTE(INDEX(Propuestas!$E$2:$E$35,24),", ",",")&",")),"●","") | AA7: =IF(ISNUMBER(SEARCH(","&$A7&",",","&SUBSTITUTE(INDEX(Propuestas!$E$2:$E$35,25),", ",",")&",")),"●","") | AB7: =IF(ISNUMBER(SEARCH(","&$A7&",",","&SUBSTITUTE(INDEX(Propuestas!$E$2:$E$35,26),", ",",")&",")),"●","") -> ● | AC7: =IF(ISNUMBER(SEARCH(","&$A7&",",","&SUBSTITUTE(INDEX(Propuestas!$E$2:$E$35,27),", ",",")&",")),"●","") | AD7: =IF(ISNUMBER(SEARCH(","&$A7&",",","&SUBSTITUTE(INDEX(Propuestas!$E$2:$E$35,28),", ",",")&",")),"●","") | AE7: =IF(ISNUMBER(SEARCH(","&$A7&",",","&SUBSTITUTE(INDEX(Propuestas!$E$2:$E$35,29),", ",",")&",")),"●","") | AF7: =IF(ISNUMBER(SEARCH(","&$A7&",",","&SUBSTITUTE(INDEX(Propuestas!$E$2:$E$35,30),", ",",")&",")),"●","") -> ● | AG7: =IF(ISNUMBER(SEARCH(","&$A7&",",","&SUBSTITUTE(INDEX(Propuestas!$E$2:$E$35,31),", ",",")&",")),"●","") | AH7: =IF(ISNUMBER(SEARCH(","&$A7&",",","&SUBSTITUTE(INDEX(Propuestas!$E$2:$E$35,32),", ",",")&",")),"●","") | AI7: =IF(ISNUMBER(SEARCH(","&$A7&",",","&SUBSTITUTE(INDEX(Propuestas!$E$2:$E$35,33),", ",",")&",")),"●","") | AJ7: =IF(ISNUMBER(SEARCH(","&$A7&",",","&SUBSTITUTE(INDEX(Propuestas!$E$2:$E$35,34),", ",",")&",")),"●","") -> ● | AK7: =COUNTIF(C7:AJ7,"●") -> 14
A8: SUTEBA | B8: =INDEX(Sindicatos!F:F,MATCH(A8,Sindicatos!A:A,0)) -> 4 | C8: =IF(ISNUMBER(SEARCH(","&$A8&",",","&SUBSTITUTE(INDEX(Propuestas!$E$2:$E$35,1),", ",",")&",")),"●","") | D8: =IF(ISNUMBER(SEARCH(","&$A8&",",","&SUBSTITUTE(INDEX(Propuestas!$E$2:$E$35,2),", ",",")&",")),"●","") | E8: =IF(ISNUMBER(SEARCH(","&$A8&",",","&SUBSTITUTE(INDEX(Propuestas!$E$2:$E$35,3),", ",",")&",")),"●","") | F8: =IF(ISNUMBER(SEARCH(","&$A8&",",","&SUBSTITUTE(INDEX(Propuestas!$E$2:$E$35,4),", ",",")&",")),"●","") -> ● | G8: =IF(ISNUMBER(SEARCH(","&$A8&",",","&SUBSTITUTE(INDEX(Propuestas!$E$2:$E$35,5),", ",",")&",")),"●","") -> ● | H8: =IF(ISNUMBER(SEARCH(","&$A8&",",","&SUBSTITUTE(INDEX(Propuestas!$E$2:$E$35,6),", ",",")&",")),"●","") | I8: =IF(ISNUMBER(SEARCH(","&$A8&",",","&SUBSTITUTE(INDEX(Propuestas!$E$2:$E$35,7),", ",",")&",")),"●","") | J8: =IF(ISNUMBER(SEARCH(","&$A8&",",","&SUBSTITUTE(INDEX(Propuestas!$E$2:$E$35,8),", ",",")&",")),"●","") -> ● | K8: =IF(ISNUMBER(SEARCH(","&$A8&",",","&SUBSTITUTE(INDEX(Propuestas!$E$2:$E$35,9),", ",",")&",")),"●","") | L8: =IF(ISNUMBER(SEARCH(","&$A8&",",","&SUBSTITUTE(INDEX(Propuestas!$E$2:$E$35,10),", ",",")&",")),"●","") | M8: =IF(ISNUMBER(SEARCH(","&$A8&",",","&SUBSTITUTE(INDEX(Propuestas!$E$2:$E$35,11),", ",",")&",")),"●","") | N8: =IF(ISNUMBER(SEARCH(","&$A8&",",","&SUBSTITUTE(INDEX(Propuestas!$E$2:$E$35,12),", ",",")&",")),"●","") | O8: =IF(ISNUMBER(SEARCH(","&$A8&",",","&SUBSTITUTE(INDEX(Propuestas!$E$2:$E$35,13),", ",",")&",")),"●","") | P8: =IF(ISNUMBER(SEARCH(","&$A8&",",","&SUBSTITUTE(INDEX(Propuestas!$E$2:$E$35,14),", ",",")&",")),"●","") -> ● | Q8: =IF(ISNUMBER(SEARCH(","&$A8&",",","&SUBSTITUTE(INDEX(Propuestas!$E$2:$E$35,15),", ",",")&",")),"●","") | R8: =IF(ISNUMBER(SEARCH(","&$A8&",",","&SUBSTITUTE(INDEX(Propuestas!$E$2:$E$35,16),", ",",")&",")),"●","") -> ● | S8: =IF(ISNUMBER(SEARCH(","&$A8&",",","&SUBSTITUTE(INDEX(Propuestas!$E$2:$E$35,17),", ",",")&",")),"●","") | T8: =IF(ISNUMBER(SEARCH(","&$A8&",",","&SUBSTITUTE(INDEX(Propuestas!$E$2:$E$35,18),", ",",")&",")),"●","") | U8: =IF(ISNUMBER(SEARCH(","&$A8&",",","&SUBSTITUTE(INDEX(Propuestas!$E$2:$E$35,19),", ",",")&",")),"●","") -> ● | V8: =IF(ISNUMBER(SEARCH(","&$A8&",",","&SUBSTITUTE(INDEX(Propuestas!$E$2:$E$35,20),", ",",")&",")),"●","") -> ● | W8: =IF(ISNUMBER(SEARCH(","&$A8&",",","&SUBSTITUTE(INDEX(Propuestas!$E$2:$E$35,21),", ",",")&",")),"●","") -> ● | X8: =IF(ISNUMBER(SEARCH(","&$A8&",",","&SUBSTITUTE(INDEX(Propuestas!$E$2:$E$35,22),", ",",")&",")),"●","") | Y8: =IF(ISNUMBER(SEARCH(","&$A8&",",","&SUBSTITUTE(INDEX(Propuestas!$E$2:$E$35,23),", ",",")&",")),"●","") | Z8: =IF(ISNUMBER(SEARCH(","&$A8&",",","&SUBSTITUTE(INDEX(Propuestas!$E$2:$E$35,24),", ",",")&",")),"●","") | AA8: =IF(ISNUMBER(SEARCH(","&$A8&",",","&SUBSTITUTE(INDEX(Propuestas!$E$2:$E$35,25),", ",",")&",")),"●","") | AB8: =IF(ISNUMBER(SEARCH(","&$A8&",",","&SUBSTITUTE(INDEX(Propuestas!$E$2:$E$35,26),", ",",")&",")),"●","") | AC8: =IF(ISNUMBER(SEARCH(","&$A8&",",","&SUBSTITUTE(INDEX(Propuestas!$E$2:$E$35,27),", ",",")&",")),"●","") | AD8: =IF(ISNUMBER(SEARCH(","&$A8&",",","&SUBSTITUTE(INDEX(Propuestas!$E$2:$E$35,28),", ",",")&",")),"●","") | AE8: =IF(ISNUMBER(SEARCH(","&$A8&",",","&SUBSTITUTE(INDEX(Propuestas!$E$2:$E$35,29),", ",",")&",")),"●","") | AF8: =IF(ISNUMBER(SEARCH(","&$A8&",",","&SUBSTITUTE(INDEX(Propuestas!$E$2:$E$35,30),", ",",")&",")),"●","") | AG8: =IF(ISNUMBER(SEARCH(","&$A8&",",","&SUBSTITUTE(INDEX(Propuestas!$E$2:$E$35,31),", ",",")&",")),"●","") -> ● | AH8: =IF(ISNUMBER(SEARCH(","&$A8&",",","&SUBSTITUTE(INDEX(Propuestas!$E$2:$E$35,32),", ",",")&",")),"●","") | AI8: =IF(ISNUMBER(SEARCH(","&$A8&",",","&SUBSTITUTE(INDEX(Propuestas!$E$2:$E$35,33),", ",",")&",")),"●","") | AJ8: =IF(ISNUMBER(SEARCH(","&$A8&",",","&SUBSTITUTE(INDEX(Propuestas!$E$2:$E$35,34),", ",",")&",")),"●","") | AK8: =COUNTIF(C8:AJ8,"●") -> 9
A9: SUTERH | B9: =INDEX(Sindicatos!F:F,MATCH(A9,Sindicatos!A:A,0)) -> 4 | C9: =IF(ISNUMBER(SEARCH(","&$A9&",",","&SUBSTITUTE(INDEX(Propuestas!$E$2:$E$35,1),", ",",")&",")),"●","") | D9: =IF(ISNUMBER(SEARCH(","&$A9&",",","&SUBSTITUTE(INDEX(Propuestas!$E$2:$E$35,2),", ",",")&",")),"●","") | E9: =IF(ISNUMBER(SEARCH(","&$A9&",",","&SUBSTITUTE(INDEX(Propuestas!$E$2:$E$35,3),", ",",")&",")),"●","") | F9: =IF(ISNUMBER(SEARCH(","&$A9&",",","&SUBSTITUTE(INDEX(Propuestas!$E$2:$E$35,4),", ",",")&",")),"●","") | G9: =IF(ISNUMBER(SEARCH(","&$A9&",",","&SUBSTITUTE(INDEX(Propuestas!$E$2:$E$35,5),", ",",")&",")),"●","") -> ● | H9: =IF(ISNUMBER(SEARCH(","&$A9&",",","&SUBSTITUTE(INDEX(Propuestas!$E$2:$E$35,6),", ",",")&",")),"●","") | I9: =IF(ISNUMBER(SEARCH(","&$A9&",",","&SUBSTITUTE(INDEX(Propuestas!$E$2:$E$35,7),", ",",")&",")),"●","") | J9: =IF(ISNUMBER(SEARCH(","&$A9&",",","&SUBSTITUTE(INDEX(Propuestas!$E$2:$E$35,8),", ",",")&",")),"●","") -> ● | K9: =IF(ISNUMBER(SEARCH(","&$A9&",",","&SUBSTITUTE(INDEX(Propuestas!$E$2:$E$35,9),", ",",")&",")),"●","") | L9: =IF(ISNUMBER(SEARCH(","&$A9&",",","&SUBSTITUTE(INDEX(Propuestas!$E$2:$E$35,10),", ",",")&",")),"●","") | M9: =IF(ISNUMBER(SEARCH(","&$A9&",",","&SUBSTITUTE(INDEX(Propuestas!$E$2:$E$35,11),", ",",")&",")),"●","") -> ● | N9: =IF(ISNUMBER(SEARCH(","&$A9&",",","&SUBSTITUTE(INDEX(Propuestas!$E$2:$E$35,12),", ",",")&",")),"●","") -> ● | O9: =IF(ISNUMBER(SEARCH(","&$A9&",",","&SUBSTITUTE(INDEX(Propuestas!$E$2:$E$35,13),", ",",")&",")),"●","") | P9: =IF(ISNUMBER(SEARCH(","&$A9&",",","&SUBSTITUTE(INDEX(Propuestas!$E$2:$E$35,14),", ",",")&",")),"●","") | Q9: =IF(ISNUMBER(SEARCH(","&$A9&",",","&SUBSTITUTE(INDEX(Propuestas!$E$2:$E$35,15),", ",",")&",")),"●","") -> ● | R9: =IF(ISNUMBER(SEARCH(","&$A9&",",","&SUBSTITUTE(INDEX(Propuestas!$E$2:$E$35,16),", ",",")&",")),"●","") | S9: =IF(ISNUMBER(SEARCH(","&$A9&",",","&SUBSTITUTE(INDEX(Propuestas!$E$2:$E$35,17),", ",",")&",")),"●","") -> ● | T9: =IF(ISNUMBER(SEARCH(","&$A9&",",","&SUBSTITUTE(INDEX(Propuestas!$E$2:$E$35,18),", ",",")&",")),"●","") -> ● | U9: =IF(ISNUMBER(SEARCH(","&$A9&",",","&SUBSTITUTE(INDEX(Propuestas!$E$2:$E$35,19),", ",",")&",")),"●","") | V9: =IF(ISNUMBER(SEARCH(","&$A9&",",","&SUBSTITUTE(INDEX(Propuestas!$E$2:$E$35,20),", ",",")&",")),"●","") -> ● | W9: =IF(ISNUMBER(SEARCH(","&$A9&",",","&SUBSTITUTE(INDEX(Propuestas!$E$2:$E$35,21),", ",",")&",")),"●","") -> ● | X9: =IF(ISNUMBER(SEARCH(","&$A9&",",","&SUBSTITUTE(INDEX(Propuestas!$E$2:$E$35,22),", ",",")&",")),"●","") | Y9: =IF(ISNUMBER(SEARCH(","&$A9&",",","&SUBSTITUTE(INDEX(Propuestas!$E$2:$E$35,23),", ",",")&",")),"●","") | Z9: =IF(ISNUMBER(SEARCH(","&$A9&",",","&SUBSTITUTE(INDEX(Propuestas!$E$2:$E$35,24),", ",",")&",")),"●","") | AA9: =IF(ISNUMBER(SEARCH(","&$A9&",",","&SUBSTITUTE(INDEX(Propuestas!$E$2:$E$35,25),", ",",")&",")),"●","") | AB9: =IF(ISNUMBER(SEARCH(","&$A9&",",","&SUBSTITUTE(INDEX(Propuestas!$E$2:$E$35,26),", ",",")&",")),"●","") | AC9: =IF(ISNUMBER(SEARCH(","&$A9&",",","&SUBSTITUTE(INDEX(Propuestas!$E$2:$E$35,27),", ",",")&",")),"●","") -> ● | AD9: =IF(ISNUMBER(SEARCH(","&$A9&",",","&SUBSTITUTE(INDEX(Propuestas!$E$2:$E$35,28),", ",",")&",")),"●","") | AE9: =IF(ISNUMBER(SEARCH(","&$A9&",",","&SUBSTITUTE(INDEX(Propuestas!$E$2:$E$35,29),", ",",")&",")),"●","") | AF9: =IF(ISNUMBER(SEARCH(","&$A9&",",","&SUBSTITUTE(INDEX(Propuestas!$E$2:$E$35,30),", ",",")&",")),"●","") | AG9: =IF(ISNUMBER(SEARCH(","&$A9&",",","&SUBSTITUTE(INDEX(Propuestas!$E$2:$E$35,31),", ",",")&",")),"●","") | AH9: =IF(ISNUMBER(SEARCH(","&$A9&",",","&SUBSTITUTE(INDEX(Propuestas!$E$2:$E$35,32),", ",",")&",")),"●","") | AI9: =IF(ISNUMBER(SEARCH(","&$A9&",",","&SUBSTITUTE(INDEX(Propuestas!$E$2:$E$35,33),", ",",")&",")),"●","") | AJ9: =IF(ISNUMBER(SEARCH(","&$A9&",",","&SUBSTITUTE(INDEX(Propuestas!$E$2:$E$35,34),", ",",")&",")),"●","") | AK9: =COUNTIF(C9:AJ9,"●") -> 10
A10: UEJN | B10: =INDEX(Sindicatos!F:F,MATCH(A10,Sindicatos!A:A,0)) -> 4 | C10: =IF(ISNUMBER(SEARCH(","&$A10&",",","&SUBSTITUTE(INDEX(Propuestas!$E$2:$E$35,1),", ",",")&",")),"●","") | D10: =IF(ISNUMBER(SEARCH(","&$A10&",",","&SUBSTITUTE(INDEX(Propuestas!$E$2:$E$35,2),", ",",")&",")),"●","") | E10: =IF(ISNUMBER(SEARCH(","&$A10&",",","&SUBSTITUTE(INDEX(Propuestas!$E$2:$E$35,3),", ",",")&",")),"●","") | F10: =IF(ISNUMBER(SEARCH(","&$A10&",",","&SUBSTITUTE(INDEX(Propuestas!$E$2:$E$35,4),", ",",")&",")),"●","") | G10: =IF(ISNUMBER(SEARCH(","&$A10&",",","&SUBSTITUTE(INDEX(Propuestas!$E$2:$E$35,5),", ",",")&",")),"●","") | H10: =IF(ISNUMBER(SEARCH(","&$A10&",",","&SUBSTITUTE(INDEX(Propuestas!$E$2:$E$35,6),", ",",")&",")),"●","") | I10: =IF(ISNUMBER(SEARCH(","&$A10&",",","&SUBSTITUTE(INDEX(Propuestas!$E$2:$E$35,7),", ",",")&",")),"●","") | J10: =IF(ISNUMBER(SEARCH(","&$A10&",",","&SUBSTITUTE(INDEX(Propuestas!$E$2:$E$35,8),", ",",")&",")),"●","") -> ● | K10: =IF(ISNUMBER(SEARCH(","&$A10&",",","&SUBSTITUTE(INDEX(Propuestas!$E$2:$E$35,9),", ",",")&",")),"●","") | L10: =IF(ISNUMBER(SEARCH(","&$A10&",",","&SUBSTITUTE(INDEX(Propuestas!$E$2:$E$35,10),", ",",")&",")),"●","") | M10: =IF(ISNUMBER(SEARCH(","&$A10&",",","&SUBSTITUTE(INDEX(Propuestas!$E$2:$E$35,11),", ",",")&",")),"●","") -> ● | N10: =IF(ISNUMBER(SEARCH(","&$A10&",",","&SUBSTITUTE(INDEX(Propuestas!$E$2:$E$35,12),", ",",")&",")),"●","") | O10: =IF(ISNUMBER(SEARCH(","&$A10&",",","&SUBSTITUTE(INDEX(Propuestas!$E$2:$E$35,13),", ",",")&",")),"●","") | P10: =IF(ISNUMBER(SEARCH(","&$A10&",",","&SUBSTITUTE(INDEX(Propuestas!$E$2:$E$35,14),", ",",")&",")),"●","") | Q10: =IF(ISNUMBER(SEARCH(","&$A10&",",","&SUBSTITUTE(INDEX(Propuestas!$E$2:$E$35,15),", ",",")&",")),"●","") | R10: =IF(ISNUMBER(SEARCH(","&$A10&",",","&SUBSTITUTE(INDEX(Propuestas!$E$2:$E$35,16),", ",",")&",")),"●","") | S10: =IF(ISNUMBER(SEARCH(","&$A10&",",","&SUBSTITUTE(INDEX(Propuestas!$E$2:$E$35,17),", ",",")&",")),"●","") | T10: =IF(ISNUMBER(SEARCH(","&$A10&",",","&SUBSTITUTE(INDEX(Propuestas!$E$2:$E$35,18),", ",",")&",")),"●","") | U10: =IF(ISNUMBER(SEARCH(","&$A10&",",","&SUBSTITUTE(INDEX(Propuestas!$E$2:$E$35,19),", ",",")&",")),"●","") -> ● | V10: =IF(ISNUMBER(SEARCH(","&$A10&",",","&SUBSTITUTE(INDEX(Propuestas!$E$2:$E$35,20),", ",",")&",")),"●","") -> ● | W10: =IF(ISNUMBER(SEARCH(","&$A10&",",","&SUBSTITUTE(INDEX(Propuestas!$E$2:$E$35,21),", ",",")&",")),"●","") | X10: =IF(ISNUMBER(SEARCH(","&$A10&",",","&SUBSTITUTE(INDEX(Propuestas!$E$2:$E$35,22),", ",",")&",")),"●","") -> ● | Y10: =IF(ISNUMBER(SEARCH(","&$A10&",",","&SUBSTITUTE(INDEX(Propuestas!$E$2:$E$35,23),", ",",")&",")),"●","") | Z10: =IF(ISNUMBER(SEARCH(","&$A10&",",","&SUBSTITUTE(INDEX(Propuestas!$E$2:$E$35,24),", ",",")&",")),"●","") | AA10: =IF(ISNUMBER(SEARCH(","&$A10&",",","&SUBSTITUTE(INDEX(Propuestas!$E$2:$E$35,25),", ",",")&",")),"●","") | AB10: =IF(ISNUMBER(SEARCH(","&$A10&",",","&SUBSTITUTE(INDEX(Propuestas!$E$2:$E$35,26),", ",",")&",")),"●","") | AC10: =IF(ISNUMBER(SEARCH(","&$A10&",",","&SUBSTITUTE(INDEX(Propuestas!$E$2:$E$35,27),", ",",")&",")),"●","") | AD10: =IF(ISNUMBER(SEARCH(","&$A10&",",","&SUBSTITUTE(INDEX(Propuestas!$E$2:$E$35,28),", ",",")&",")),"●","") | AE10: =IF(ISNUMBER(SEARCH(","&$A10&",",","&SUBSTITUTE(INDEX(Propuestas!$E$2:$E$35,29),", ",",")&",")),"●","") | AF10: =IF(ISNUMBER(SEARCH(","&$A10&",",","&SUBSTITUTE(INDEX(Propuestas!$E$2:$E$35,30),", ",",")&",")),"●","") | AG10: =IF(ISNUMBER(SEARCH(","&$A10&",",","&SUBSTITUTE(INDEX(Propuestas!$E$2:$E$35,31),", ",",")&",")),"●","") | AH10: =IF(ISNUMBER(SEARCH(","&$A10&",",","&SUBSTITUTE(INDEX(Propuestas!$E$2:$E$35,32),", ",",")&",")),"●","") | AI10: =IF(ISNUMBER(SEARCH(","&$A10&",",","&SUBSTITUTE(INDEX(Propuestas!$E$2:$E$35,33),", ",",")&",")),"●","") | AJ10: =IF(ISNUMBER(SEARCH(","&$A10&",",","&SUBSTITUTE(INDEX(Propuestas!$E$2:$E$35,34),", ",",")&",")),"●","") | AK10: =COUNTIF(C10:AJ10,"●") -> 5
A11: UTEDYC | B11: =INDEX(Sindicatos!F:F,MATCH(A11,Sindicatos!A:A,0)) -> 4 | C11: =IF(ISNUMBER(SEARCH(","&$A11&",",","&SUBSTITUTE(INDEX(Propuestas!$E$2:$E$35,1),", ",",")&",")),"●","") | D11: =IF(ISNUMBER(SEARCH(","&$A11&",",","&SUBSTITUTE(INDEX(Propuestas!$E$2:$E$35,2),", ",",")&",")),"●","") | E11: =IF(ISNUMBER(SEARCH(","&$A11&",",","&SUBSTITUTE(INDEX(Propuestas!$E$2:$E$35,3),", ",",")&",")),"●","") -> ● | F11: =IF(ISNUMBER(SEARCH(","&$A11&",",","&SUBSTITUTE(INDEX(Propuestas!$E$2:$E$35,4),", ",",")&",")),"●","") | G11: =IF(ISNUMBER(SEARCH(","&$A11&",",","&SUBSTITUTE(INDEX(Propuestas!$E$2:$E$35,5),", ",",")&",")),"●","") | H11: =IF(ISNUMBER(SEARCH(","&$A11&",",","&SUBSTITUTE(INDEX(Propuestas!$E$2:$E$35,6),", ",",")&",")),"●","") | I11: =IF(ISNUMBER(SEARCH(","&$A11&",",","&SUBSTITUTE(INDEX(Propuestas!$E$2:$E$35,7),", ",",")&",")),"●","") | J11: =IF(ISNUMBER(SEARCH(","&$A11&",",","&SUBSTITUTE(INDEX(Propuestas!$E$2:$E$35,8),", ",",")&",")),"●","") -> ● | K11: =IF(ISNUMBER(SEARCH(","&$A11&",",","&SUBSTITUTE(INDEX(Propuestas!$E$2:$E$35,9),", ",",")&",")),"●","") | L11: =IF(ISNUMBER(SEARCH(","&$A11&",",","&SUBSTITUTE(INDEX(Propuestas!$E$2:$E$35,10),", ",",")&",")),"●","") | M11: =IF(ISNUMBER(SEARCH(","&$A11&",",","&SUBSTITUTE(INDEX(Propuestas!$E$2:$E$35,11),", ",",")&",")),"●","") | N11: =IF(ISNUMBER(SEARCH(","&$A11&",",","&SUBSTITUTE(INDEX(Propuestas!$E$2:$E$35,12),", ",",")&",")),"●","") | O11: =IF(ISNUMBER(SEARCH(","&$A11&",",","&SUBSTITUTE(INDEX(Propuestas!$E$2:$E$35,13),", ",",")&",")),"●","") -> ● | P11: =IF(ISNUMBER(SEARCH(","&$A11&",",","&SUBSTITUTE(INDEX(Propuestas!$E$2:$E$35,14),", ",",")&",")),"●","") | Q11: =IF(ISNUMBER(SEARCH(","&$A11&",",","&SUBSTITUTE(INDEX(Propuestas!$E$2:$E$35,15),", ",",")&",")),"●","") -> ● | R11: =IF(ISNUMBER(SEARCH(","&$A11&",",","&SUBSTITUTE(INDEX(Propuestas!$E$2:$E$35,16),", ",",")&",")),"●","") | S11: =IF(ISNUMBER(SEARCH(","&$A11&",",","&SUBSTITUTE(INDEX(Propuestas!$E$2:$E$35,17),", ",",")&",")),"●","") -> ● | T11: =IF(ISNUMBER(SEARCH(","&$A11&",",","&SUBSTITUTE(INDEX(Propuestas!$E$2:$E$35,18),", ",",")&",")),"●","") -> ● | U11: =IF(ISNUMBER(SEARCH(","&$A11&",",","&SUBSTITUTE(INDEX(Propuestas!$E$2:$E$35,19),", ",",")&",")),"●","") -> ● | V11: =IF(ISNUMBER(SEARCH(","&$A11&",",","&SUBSTITUTE(INDEX(Propuestas!$E$2:$E$35,20),", ",",")&",")),"●","") -> ● | W11: =IF(ISNUMBER(SEARCH(","&$A11&",",","&SUBSTITUTE(INDEX(Propuestas!$E$2:$E$35,21),", ",",")&",")),"●","") -> ● | X11: =IF(ISNUMBER(SEARCH(","&$A11&",",","&SUBSTITUTE(INDEX(Propuestas!$E$2:$E$35,22),", ",",")&",")),"●","") -> ● | Y11: =IF(ISNUMBER(SEARCH(","&$A11&",",","&SUBSTITUTE(INDEX(Propuestas!$E$2:$E$35,23),", ",",")&",")),"●","") -> ● | Z11: =IF(ISNUMBER(SEARCH(","&$A11&",",","&SUBSTITUTE(INDEX(Propuestas!$E$2:$E$35,24),", ",",")&",")),"●","") | AA11: =IF(ISNUMBER(SEARCH(","&$A11&",",","&SUBSTITUTE(INDEX(Propuestas!$E$2:$E$35,25),", ",",")&",")),"●","") | AB11: =IF(ISNUMBER(SEARCH(","&$A11&",",","&SUBSTITUTE(INDEX(Propuestas!$E$2:$E$35,26),", ",",")&",")),"●","") | AC11: =IF(ISNUMBER(SEARCH(","&$A11&",",","&SUBSTITUTE(INDEX(Propuestas!$E$2:$E$35,27),", ",",")&",")),"●","") -> ● | AD11: =IF(ISNUMBER(SEARCH(","&$A11&",",","&SUBSTITUTE(INDEX(Propuestas!$E$2:$E$35,28),", ",",")&",")),"●","") | AE11: =IF(ISNUMBER(SEARCH(","&$A11&",",","&SUBSTITUTE(INDEX(Propuestas!$E$2:$E$35,29),", ",",")&",")),"●","") | AF11: =IF(ISNUMBER(SEARCH(","&$A11&",",","&SUBSTITUTE(INDEX(Propuestas!$E$2:$E$35,30),", ",",")&",")),"●","") -> ● | AG11: =IF(ISNUMBER(SEARCH(","&$A11&",",","&SUBSTITUTE(INDEX(Propuestas!$E$2:$E$35,31),", ",",")&",")),"●","") | AH11: =IF(ISNUMBER(SEARCH(","&$A11&",",","&SUBSTITUTE(INDEX(Propuestas!$E$2:$E$35,32),", ",",")&",")),"●","") | AI11: =IF(ISNUMBER(SEARCH(","&$A11&",",","&SUBSTITUTE(INDEX(Propuestas!$E$2:$E$35,33),", ",",")&",")),"●","") | AJ11: =IF(ISNUMBER(SEARCH(","&$A11&",",","&SUBSTITUTE(INDEX(Propuestas!$E$2:$E$35,34),", ",",")&",")),"●","") | AK11: =COUNTIF(C11:AJ11,"●") -> 13
A12: ACEITEROS | B12: =INDEX(Sindicatos!F:F,MATCH(A12,Sindicatos!A:A,0)) -> 3 | C12: =IF(ISNUMBER(SEARCH(","&$A12&",",","&SUBSTITUTE(INDEX(Propuestas!$E$2:$E$35,1),", ",",")&",")),"●","") -> ● | D12: =IF(ISNUMBER(SEARCH(","&$A12&",",","&SUBSTITUTE(INDEX(Propuestas!$E$2:$E$35,2),", ",",")&",")),"●","") | E12: =IF(ISNUMBER(SEARCH(","&$A12&",",","&SUBSTITUTE(INDEX(Propuestas!$E$2:$E$35,3),", ",",")&",")),"●","") | F12: =IF(ISNUMBER(SEARCH(","&$A12&",",","&SUBSTITUTE(INDEX(Propuestas!$E$2:$E$35,4),", ",",")&",")),"●","") -> ● | G12: =IF(ISNUMBER(SEARCH(","&$A12&",",","&SUBSTITUTE(INDEX(Propuestas!$E$2:$E$35,5),", ",",")&",")),"●","") -> ● | H12: =IF(ISNUMBER(SEARCH(","&$A12&",",","&SUBSTITUTE(INDEX(Propuestas!$E$2:$E$35,6),", ",",")&",")),"●","") | I12: =IF(ISNUMBER(SEARCH(","&$A12&",",","&SUBSTITUTE(INDEX(Propuestas!$E$2:$E$35,7),", ",",")&",")),"●","") -> ● | J12: =IF(ISNUMBER(SEARCH(","&$A12&",",","&SUBSTITUTE(INDEX(Propuestas!$E$2:$E$35,8),", ",",")&",")),"●","") | K12: =IF(ISNUMBER(SEARCH(","&$A12&",",","&SUBSTITUTE(INDEX(Propuestas!$E$2:$E$35,9),", ",",")&",")),"●","") | L12: =IF(ISNUMBER(SEARCH(","&$A12&",",","&SUBSTITUTE(INDEX(Propuestas!$E$2:$E$35,10),", ",",")&",")),"●","") -> ● | M12: =IF(ISNUMBER(SEARCH(","&$A12&",",","&SUBSTITUTE(INDEX(Propuestas!$E$2:$E$35,11),", ",",")&",")),"●","") | N12: =IF(ISNUMBER(SEARCH(","&$A12&",",","&SUBSTITUTE(INDEX(Propuestas!$E$2:$E$35,12),", ",",")&",")),"●","") -> ● | O12: =IF(ISNUMBER(SEARCH(","&$A12&",",","&SUBSTITUTE(INDEX(Propuestas!$E$2:$E$35,13),", ",",")&",")),"●","") | P12: =IF(ISNUMBER(SEARCH(","&$A12&",",","&SUBSTITUTE(INDEX(Propuestas!$E$2:$E$35,14),", ",",")&",")),"●","") | Q12: =IF(ISNUMBER(SEARCH(","&$A12&",",","&SUBSTITUTE(INDEX(Propuestas!$E$2:$E$35,15),", ",",")&",")),"●","") -> ● | R12: =IF(ISNUMBER(SEARCH(","&$A12&",",","&SUBSTITUTE(INDEX(Propuestas!$E$2:$E$35,16),", ",",")&",")),"●","") -> ● | S12: =IF(ISNUMBER(SEARCH(","&$A12&",",","&SUBSTITUTE(INDEX(Propuestas!$E$2:$E$35,17),", ",",")&",")),"●","") | T12: =IF(ISNUMBER(SEARCH(","&$A12&",",","&SUBSTITUTE(INDEX(Propuestas!$E$2:$E$35,18),", ",",")&",")),"●","") | U12: =IF(ISNUMBER(SEARCH(","&$A12&",",","&SUBSTITUTE(INDEX(Propuestas!$E$2:$E$35,19),", ",",")&",")),"●","") | V12: =IF(ISNUMBER(SEARCH(","&$A12&",",","&SUBSTITUTE(INDEX(Propuestas!$E$2:$E$35,20),", ",",")&",")),"●","") -> ● | W12: =IF(ISNUMBER(SEARCH(","&$A12&",",","&SUBSTITUTE(INDEX(Propuestas!$E$2:$E$35,21),", ",",")&",")),"●","") | X12: =IF(ISNUMBER(SEARCH(","&$A12&",",","&SUBSTITUTE(INDEX(Propuestas!$E$2:$E$35,22),", ",",")&",")),"●","") | Y12: =IF(ISNUMBER(SEARCH(","&$A12&",",","&SUBSTITUTE(INDEX(Propuestas!$E$2:$E$35,23),", ",",")&",")),"●","") -> ● | Z12: =IF(ISNUMBER(SEARCH(","&$A12&",",","&SUBSTITUTE(INDEX(Propuestas!$E$2:$E$35,24),", ",",")&",")),"●","") | AA12: =IF(ISNUMBER(SEARCH(","&$A12&",",","&SUBSTITUTE(INDEX(Propuestas!$E$2:$E$35,25),", ",",")&",")),"●","") -> ● | AB12: =IF(ISNUMBER(SEARCH(","&$A12&",",","&SUBSTITUTE(INDEX(Propuestas!$E$2:$E$35,26),", ",",")&",")),"●","") | AC12: =IF(ISNUMBER(SEARCH(","&$A12&",",","&SUBSTITUTE(INDEX(Propuestas!$E$2:$E$35,27),", ",",")&",")),"●","") | AD12: =IF(ISNUMBER(SEARCH(","&$A12&",",","&SUBSTITUTE(INDEX(Propuestas!$E$2:$E$35,28),", ",",")&",")),"●","") | AE12: =IF(ISNUMBER(SEARCH(","&$A12&",",","&SUBSTITUTE(INDEX(Propuestas!$E$2:$E$35,29),", ",",")&",")),"●","") -> ● | AF12: =IF(ISNUMBER(SEARCH(","&$A12&",",","&SUBSTITUTE(INDEX(Propuestas!$E$2:$E$35,30),", ",",")&",")),"●","") -> ● | AG12: =IF(ISNUMBER(SEARCH(","&$A12&",",","&SUBSTITUTE(INDEX(Propuestas!$E$2:$E$35,31),", ",",")&",")),"●","") | AH12: =IF(ISNUMBER(SEARCH(","&$A12&",",","&SUBSTITUTE(INDEX(Propuestas!$E$2:$E$35,32),", ",",")&",")),"●","") -> ● | AI12: =IF(ISNUMBER(SEARCH(","&$A12&",",","&SUBSTITUTE(INDEX(Propuestas!$E$2:$E$35,33),", ",",")&",")),"●","") | AJ12: =IF(ISNUMBER(SEARCH(","&$A12&",",","&SUBSTITUTE(INDEX(Propuestas!$E$2:$E$35,34),", ",",")&",")),"●","") | AK12: =COUNTIF(C12:AJ12,"●") -> 14
A13: AEFIP | B13: =INDEX(Sindicatos!F:F,MATCH(A13,Sindicatos!A:A,0)) -> 3 | C13: =IF(ISNUMBER(SEARCH(","&$A13&",",","&SUBSTITUTE(INDEX(Propuestas!$E$2:$E$35,1),", ",",")&",")),"●","") | D13: =IF(ISNUMBER(SEARCH(","&$A13&",",","&SUBSTITUTE(INDEX(Propuestas!$E$2:$E$35,2),", ",",")&",")),"●","") -> ● | E13: =IF(ISNUMBER(SEARCH(","&$A13&",",","&SUBSTITUTE(INDEX(Propuestas!$E$2:$E$35,3),", ",",")&",")),"●","") | F13: =IF(ISNUMBER(SEARCH(","&$A13&",",","&SUBSTITUTE(INDEX(Propuestas!$E$2:$E$35,4),", ",",")&",")),"●","") | G13: =IF(ISNUMBER(SEARCH(","&$A13&",",","&SUBSTITUTE(INDEX(Propuestas!$E$2:$E$35,5),", ",",")&",")),"●","") | H13: =IF(ISNUMBER(SEARCH(","&$A13&",",","&SUBSTITUTE(INDEX(Propuestas!$E$2:$E$35,6),", ",",")&",")),"●","") | I13: =IF(ISNUMBER(SEARCH(","&$A13&",",","&SUBSTITUTE(INDEX(Propuestas!$E$2:$E$35,7),", ",",")&",")),"●","") | J13: =IF(ISNUMBER(SEARCH(","&$A13&",",","&SUBSTITUTE(INDEX(Propuestas!$E$2:$E$35,8),", ",",")&",")),"●","") | K13: =IF(ISNUMBER(SEARCH(","&$A13&",",","&SUBSTITUTE(INDEX(Propuestas!$E$2:$E$35,9),", ",",")&",")),"●","") -> ● | L13: =IF(ISNUMBER(SEARCH(","&$A13&",",","&SUBSTITUTE(INDEX(Propuestas!$E$2:$E$35,10),", ",",")&",")),"●","") | M13: =IF(ISNUMBER(SEARCH(","&$A13&",",","&SUBSTITUTE(INDEX(Propuestas!$E$2:$E$35,11),", ",",")&",")),"●","") | N13: =IF(ISNUMBER(SEARCH(","&$A13&",",","&SUBSTITUTE(INDEX(Propuestas!$E$2:$E$35,12),", ",",")&",")),"●","") | O13: =IF(ISNUMBER(SEARCH(","&$A13&",",","&SUBSTITUTE(INDEX(Propuestas!$E$2:$E$35,13),", ",",")&",")),"●","") -> ● | P13: =IF(ISNUMBER(SEARCH(","&$A13&",",","&SUBSTITUTE(INDEX(Propuestas!$E$2:$E$35,14),", ",",")&",")),"●","") | Q13: =IF(ISNUMBER(SEARCH(","&$A13&",",","&SUBSTITUTE(INDEX(Propuestas!$E$2:$E$35,15),", ",",")&",")),"●","") | R13: =IF(ISNUMBER(SEARCH(","&$A13&",",","&SUBSTITUTE(INDEX(Propuestas!$E$2:$E$35,16),", ",",")&",")),"●","") | S13: =IF(ISNUMBER(SEARCH(","&$A13&",",","&SUBSTITUTE(INDEX(Propuestas!$E$2:$E$35,17),", ",",")&",")),"●","") | T13: =IF(ISNUMBER(SEARCH(","&$A13&",",","&SUBSTITUTE(INDEX(Propuestas!$E$2:$E$35,18),", ",",")&",")),"●","") | U13: =IF(ISNUMBER(SEARCH(","&$A13&",",","&SUBSTITUTE(INDEX(Propuestas!$E$2:$E$35,19),", ",",")&",")),"●","") -> ● | V13: =IF(ISNUMBER(SEARCH(","&$A13&",",","&SUBSTITUTE(INDEX(Propuestas!$E$2:$E$35,20),", ",",")&",")),"●","") -> ● | W13: =IF(ISNUMBER(SEARCH(","&$A13&",",","&SUBSTITUTE(INDEX(Propuestas!$E$2:$E$35,21),", ",",")&",")),"●","") | X13: =IF(ISNUMBER(SEARCH(","&$A13&",",","&SUBSTITUTE(INDEX(Propuestas!$E$2:$E$35,22),", ",",")&",")),"●","") -> ● | Y13: =IF(ISNUMBER(SEARCH(","&$A13&",",","&SUBSTITUTE(INDEX(Propuestas!$E$2:$E$35,23),", ",",")&",")),"●","") | Z13: =IF(ISNUMBER(SEARCH(","&$A13&",",","&SUBSTITUTE(INDEX(Propuestas!$E$2:$E$35,24),", ",",")&",")),"●","") | AA13: =IF(ISNUMBER(SEARCH(","&$A13&",",","&SUBSTITUTE(INDEX(Propuestas!$E$2:$E$35,25),", ",",")&",")),"●","") | AB13: =IF(ISNUMBER(SEARCH(","&$A13&",",","&SUBSTITUTE(INDEX(Propuestas!$E$2:$E$35,26),", ",",")&",")),"●","") -> ● | AC13: =IF(ISNUMBER(SEARCH(","&$A13&",",","&SUBSTITUTE(INDEX(Propuestas!$E$2:$E$35,27),", ",",")&",")),"●","") | AD13: =IF(ISNUMBER(SEARCH(","&$A13&",",","&SUBSTITUTE(INDEX(Propuestas!$E$2:$E$35,28),", ",",")&",")),"●","") | AE13: =IF(ISNUMBER(SEARCH(","&$A13&",",","&SUBSTITUTE(INDEX(Propuestas!$E$2:$E$35,29),", ",",")&",")),"●","") | AF13: =IF(ISNUMBER(SEARCH(","&$A13&",",","&SUBSTITUTE(INDEX(Propuestas!$E$2:$E$35,30),", ",",")&",")),"●","") | AG13: =IF(ISNUMBER(SEARCH(","&$A13&",",","&SUBSTITUTE(INDEX(Propuestas!$E$2:$E$35,31),", ",",")&",")),"●","") | AH13: =IF(ISNUMBER(SEARCH(","&$A13&",",","&SUBSTITUTE(INDEX(Propuestas!$E$2:$E$35,32),", ",",")&",")),"●","") | AI13: =IF(ISNUMBER(SEARCH(","&$A13&",",","&SUBSTITUTE(INDEX(Propuestas!$E$2:$E$35,33),", ",",")&",")),"●","") | AJ13: =IF(ISNUMBER(SEARCH(","&$A13&",",","&SUBSTITUTE(INDEX(Propuestas!$E$2:$E$35,34),", ",",")&",")),"●","") | AK13: =COUNTIF(C13:AJ13,"●") -> 7
... A48: UTA | B48: =INDEX(Sindicatos!F:F,MATCH(A48,Sindicatos!A:A,0)) -> 2 | C48: =IF(ISNUMBER(SEARCH(","&$A48&",",","&SUBSTITUTE(INDEX(Propuestas!$E$2:$E$35,1),", ",",")&",")),"●","") | D48: =IF(ISNUMBER(SEARCH(","&$A48&",",","&SUBSTITUTE(INDEX(Propuestas!$E$2:$E$35,2),", ",",")&",")),"●","") -> ● | E48: =IF(ISNUMBER(SEARCH(","&$A48&",",","&SUBSTITUTE(INDEX(Propuestas!$E$2:$E$35,3),", ",",")&",")),"●","") | F48: =IF(ISNUMBER(SEARCH(","&$A48&",",","&SUBSTITUTE(INDEX(Propuestas!$E$2:$E$35,4),", ",",")&",")),"●","") | G48: =IF(ISNUMBER(SEARCH(","&$A48&",",","&SUBSTITUTE(INDEX(Propuestas!$E$2:$E$35,5),", ",",")&",")),"●","") | H48: =IF(ISNUMBER(SEARCH(","&$A48&",",","&SUBSTITUTE(INDEX(Propuestas!$E$2:$E$35,6),", ",",")&",")),"●","") -> ● | I48: =IF(ISNUMBER(SEARCH(","&$A48&",",","&SUBSTITUTE(INDEX(Propuestas!$E$2:$E$35,7),", ",",")&",")),"●","") | J48: =IF(ISNUMBER(SEARCH(","&$A48&",",","&SUBSTITUTE(INDEX(Propuestas!$E$2:$E$35,8),", ",",")&",")),"●","") -> ● | K48: =IF(ISNUMBER(SEARCH(","&$A48&",",","&SUBSTITUTE(INDEX(Propuestas!$E$2:$E$35,9),", ",",")&",")),"●","") | L48: =IF(ISNUMBER(SEARCH(","&$A48&",",","&SUBSTITUTE(INDEX(Propuestas!$E$2:$E$35,10),", ",",")&",")),"●","") | M48: =IF(ISNUMBER(SEARCH(","&$A48&",",","&SUBSTITUTE(INDEX(Propuestas!$E$2:$E$35,11),", ",",")&",")),"●","") | N48: =IF(ISNUMBER(SEARCH(","&$A48&",",","&SUBSTITUTE(INDEX(Propuestas!$E$2:$E$35,12),", ",",")&",")),"●","") | O48: =IF(ISNUMBER(SEARCH(","&$A48&",",","&SUBSTITUTE(INDEX(Propuestas!$E$2:$E$35,13),", ",",")&",")),"●","") | P48: =IF(ISNUMBER(SEARCH(","&$A48&",",","&SUBSTITUTE(INDEX(Propuestas!$E$2:$E$35,14),", ",",")&",")),"●","") | Q48: =IF(ISNUMBER(SEARCH(","&$A48&",",","&SUBSTITUTE(INDEX(Propuestas!$E$2:$E$35,15),", ",",")&",")),"●","") | R48: =IF(ISNUMBER(SEARCH(","&$A48&",",","&SUBSTITUTE(INDEX(Propuestas!$E$2:$E$35,16),", ",",")&",")),"●","") | S48: =IF(ISNUMBER(SEARCH(","&$A48&",",","&SUBSTITUTE(INDEX(Propuestas!$E$2:$E$35,17),", ",",")&",")),"●","") | T48: =IF(ISNUMBER(SEARCH(","&$A48&",",","&SUBSTITUTE(INDEX(Propuestas!$E$2:$E$35,18),", ",",")&",")),"●","") | U48: =IF(ISNUMBER(SEARCH(","&$A48&",",","&SUBSTITUTE(INDEX(Propuestas!$E$2:$E$35,19),", ",",")&",")),"●","") -> ● | V48: =IF(ISNUMBER(SEARCH(","&$A48&",",","&SUBSTITUTE(INDEX(Propuestas!$E$2:$E$35,20),", ",",")&",")),"●","") -> ● | W48: =IF(ISNUMBER(SEARCH(","&$A48&",",","&SUBSTITUTE(INDEX(Propuestas!$E$2:$E$35,21),", ",",")&",")),"●","") | X48: =IF(ISNUMBER(SEARCH(","&$A48&",",","&SUBSTITUTE(INDEX(Propuestas!$E$2:$E$35,22),", ",",")&",")),"●","") | Y48: =IF(ISNUMBER(SEARCH(","&$A48&",",","&SUBSTITUTE(INDEX(Propuestas!$E$2:$E$35,23),", ",",")&",")),"●","") | Z48: =IF(ISNUMBER(SEARCH(","&$A48&",",","&SUBSTITUTE(INDEX(Propuestas!$E$2:$E$35,24),", ",",")&",")),"●","") -> ● | AA48: =IF(ISNUMBER(SEARCH(","&$A48&",",","&SUBSTITUTE(INDEX(Propuestas!$E$2:$E$35,25),", ",",")&",")),"●","") | AB48: =IF(ISNUMBER(SEARCH(","&$A48&",",","&SUBSTITUTE(INDEX(Propuestas!$E$2:$E$35,26),", ",",")&",")),"●","") | AC48: =IF(ISNUMBER(SEARCH(","&$A48&",",","&SUBSTITUTE(INDEX(Propuestas!$E$2:$E$35,27),", ",",")&",")),"●","") | AD48: =IF(ISNUMBER(SEARCH(","&$A48&",",","&SUBSTITUTE(INDEX(Propuestas!$E$2:$E$35,28),", ",",")&",")),"●","") | AE48: =IF(ISNUMBER(SEARCH(","&$A48&",",","&SUBSTITUTE(INDEX(Propuestas!$E$2:$E$35,29),", ",",")&",")),"●","") | AF48: =IF(ISNUMBER(SEARCH(","&$A48&",",","&SUBSTITUTE(INDEX(Propuestas!$E$2:$E$35,30),", ",",")&",")),"●","") | AG48: =IF(ISNUMBER(SEARCH(","&$A48&",",","&SUBSTITUTE(INDEX(Propuestas!$E$2:$E$35,31),", ",",")&",")),"●","") | AH48: =IF(ISNUMBER(SEARCH(","&$A48&",",","&SUBSTITUTE(INDEX(Propuestas!$E$2:$E$35,32),", ",",")&",")),"●","") | AI48: =IF(ISNUMBER(SEARCH(","&$A48&",",","&SUBSTITUTE(INDEX(Propuestas!$E$2:$E$35,33),", ",",")&",")),"●","") | AJ48: =IF(ISNUMBER(SEARCH(","&$A48&",",","&SUBSTITUTE(INDEX(Propuestas!$E$2:$E$35,34),", ",",")&",")),"●","") -> ● | AK48: =COUNTIF(C48:AJ48,"●") -> 7
A49: Sindicatos por propuesta | C49: =COUNTIF(C2:C48,"●") -> 18 | D49: =COUNTIF(D2:D48,"●") -> 16 | E49: =COUNTIF(E2:E48,"●") -> 11 | F49: =COUNTIF(F2:F48,"●") -> 22 | G49: =COUNTIF(G2:G48,"●") -> 11 | H49: =COUNTIF(H2:H48,"●") -> 11 | I49: =COUNTIF(I2:I48,"●") -> 9 | J49: =COUNTIF(J2:J48,"●") -> 12 | ... AJ49: =COUNTIF(AJ2:AJ48,"●") -> 19
